Workbook

Sheet Fluxo de Caixa
F2: =F16/SUM($F16:$O16) -> 0.036503643 | G2: =G16/SUM($F16:$O16) -> 0.13294982 | H2: =H16/SUM($F16:$O16) -> 0.13897895 | I2: =I16/SUM($F16:$O16) -> 0.25335639 | J2: =J16/SUM($F16:$O16) -> 0.067044848 | K2: =K16/SUM($F16:$O16) -> 0.22094563 | L2: =L16/SUM($F16:$O16) -> 0.1049571 | M2: =M16/SUM($F16:$O16) -> 0.045263625 | ... O2: =O16/SUM($F16:$O16) -> 0
C3: 2022 | D3: Recebimentos | E3: Despesas | F3: Transporte | G3: Materiais | H3: Educação | I3: Marketing | J3: Empresa/CRP | K3: Aluguel | L3: Supervisão | M3: Escritório | N3: Reforma | P3: Total
B4: 2022/1 | C4: janeiro | D4: =SUMIF(Entradas!B:B,B4,Entradas!C:C) -> 50 | E4: =SUM(F4:O4) -> 1924.42 | F4: =SUMIFS(Despesas!$C:$C,Despesas!$B:$B,$B4,Despesas!$E:$E,F$3) -> 83.83 | G4: =SUMIFS(Despesas!$C:$C,Despesas!$B:$B,$B4,Despesas!$E:$E,G$3) -> 146.41 | H4: =SUMIFS(Despesas!$C:$C,Despesas!$B:$B,$B4,Despesas!$E:$E,H$3) -> 529.72 | I4: =SUMIFS(Despesas!$C:$C,Despesas!$B:$B,$B4,Despesas!$E:$E,I$3) -> 98.3 | J4: =SUMIFS(Despesas!$C:$C,Despesas!$B:$B,$B4,Despesas!$E:$E,J$3) -> 666.16 | K4: =SUMIFS(Despesas!$C:$C,Despesas!$B:$B,$B4,Despesas!$E:$E,K$3) -> 400 | L4: =SUMIFS(Despesas!$C:$C,Despesas!$B:$B,$B4,Despesas!$E:$E,L$3) -> 0 | M4: =SUMIFS(Despesas!$C:$C,Despesas!$B:$B,$B4,Despesas!$E:$E,M$3) -> 0 | ... O4: =SUMIFS(Despesas!$C:$C,Despesas!$B:$B,$B4,Despesas!$E:$E,O$3) -> 0 | P4: =D4-E4 -> -1874.42
B5: 2022/2 | C5: fevereiro | D5: =SUMIF(Entradas!B:B,B5,Entradas!C:C) -> 350 | E5: =SUM(F5:O5) -> 1557.88 | F5: =SUMIFS(Despesas!$C:$C,Despesas!$B:$B,$B5,Despesas!$E:$E,F$3) -> 22 | G5: =SUMIFS(Despesas!$C:$C,Despesas!$B:$B,$B5,Despesas!$E:$E,G$3) -> 93.01 | H5: =SUMIFS(Despesas!$C:$C,Despesas!$B:$B,$B5,Despesas!$E:$E,H$3) -> 529.72 | I5: =SUMIFS(Despesas!$C:$C,Despesas!$B:$B,$B5,Despesas!$E:$E,I$3) -> 313.15 | J5: =SUMIFS(Despesas!$C:$C,Despesas!$B:$B,$B5,Despesas!$E:$E,J$3) -> 200 | K5: =SUMIFS(Despesas!$C:$C,Despesas!$B:$B,$B5,Despesas!$E:$E,K$3) -> 400 | L5: =SUMIFS(Despesas!$C:$C,Despesas!$B:$B,$B5,Despesas!$E:$E,L$3) -> 0 | M5: =SUMIFS(Despesas!$C:$C,Despesas!$B:$B,$B5,Despesas!$E:$E,M$3) -> 0 | ... O5: =SUMIFS(Despesas!$C:$C,Despesas!$B:$B,$B5,Despesas!$E:$E,O$3) -> 0 | P5: =D5-E5 -> -1207.88
B6: 2022/3 | C6: março | D6: =SUMIF(Entradas!B:B,B6,Entradas!C:C) -> 1745 | E6: =SUM(F6:O6) -> 1952.47 | F6: =SUMIFS(Despesas!$C:$C,Despesas!$B:$B,$B6,Despesas!$E:$E,F$3) -> 179 | G6: =SUMIFS(Despesas!$C:$C,Despesas!$B:$B,$B6,Despesas!$E:$E,G$3) -> 253.97 | H6: =SUMIFS(Despesas!$C:$C,Despesas!$B:$B,$B6,Despesas!$E:$E,H$3) -> 529.72 | I6: =SUMIFS(Despesas!$C:$C,Despesas!$B:$B,$B6,Despesas!$E:$E,I$3) -> 349 | J6: =SUMIFS(Despesas!$C:$C,Despesas!$B:$B,$B6,Despesas!$E:$E,J$3) -> 200 | K6: =SUMIFS(Despesas!$C:$C,Despesas!$B:$B,$B6,Despesas!$E:$E,K$3) -> 400 | L6: =SUMIFS(Despesas!$C:$C,Despesas!$B:$B,$B6,Despesas!$E:$E,L$3) -> 0 | M6: =SUMIFS(Despesas!$C:$C,Despesas!$B:$B,$B6,Despesas!$E:$E,M$3) -> 40.78 | ... O6: =SUMIFS(Despesas!$C:$C,Despesas!$B:$B,$B6,Despesas!$E:$E,O$3) -> 0 | P6: =D6-E6 -> -207.47
B7: 2022/4 | C7: abril | D7: =SUMIF(Entradas!B:B,B7,Entradas!C:C) -> 2450 | E7: =SUM(F7:O7) -> 3588.22 | F7: =SUMIFS(Despesas!$C:$C,Despesas!$B:$B,$B7,Despesas!$E:$E,F$3) -> 119 | G7: =SUMIFS(Despesas!$C:$C,Despesas!$B:$B,$B7,Despesas!$E:$E,G$3) -> 22 | H7: =SUMIFS(Despesas!$C:$C,Despesas!$B:$B,$B7,Despesas!$E:$E,H$3) -> 529.72 | I7: =SUMIFS(Despesas!$C:$C,Despesas!$B:$B,$B7,Despesas!$E:$E,I$3) -> 1689 | J7: =SUMIFS(Despesas!$C:$C,Despesas!$B:$B,$B7,Despesas!$E:$E,J$3) -> 200 | K7: =SUMIFS(Despesas!$C:$C,Despesas!$B:$B,$B7,Despesas!$E:$E,K$3) -> 578.5 | L7: =SUMIFS(Despesas!$C:$C,Despesas!$B:$B,$B7,Despesas!$E:$E,L$3) -> 450 | M7: =SUMIFS(Despesas!$C:$C,Despesas!$B:$B,$B7,Despesas!$E:$E,M$3) -> 0 | ... O7: =SUMIFS(Despesas!$C:$C,Despesas!$B:$B,$B7,Despesas!$E:$E,O$3) -> 0 | P7: =D7-E7 -> -1138.22
B8: 2022/5 | C8: maio | D8: =SUMIF(Entradas!B:B,B8,Entradas!C:C) -> 3350 | E8: =SUM(F8:O8) -> 2881 | F8: =SUMIFS(Despesas!$C:$C,Despesas!$B:$B,$B8,Despesas!$E:$E,F$3) -> 69 | G8: =SUMIFS(Despesas!$C:$C,Despesas!$B:$B,$B8,Despesas!$E:$E,G$3) -> 65 | H8: =SUMIFS(Despesas!$C:$C,Despesas!$B:$B,$B8,Despesas!$E:$E,H$3) -> 529.72 | I8: =SUMIFS(Despesas!$C:$C,Despesas!$B:$B,$B8,Despesas!$E:$E,I$3) -> 1227.3 | J8: =SUMIFS(Despesas!$C:$C,Despesas!$B:$B,$B8,Despesas!$E:$E,J$3) -> 200 | K8: =SUMIFS(Despesas!$C:$C,Despesas!$B:$B,$B8,Despesas!$E:$E,K$3) -> 400 | L8: =SUMIFS(Despesas!$C:$C,Despesas!$B:$B,$B8,Despesas!$E:$E,L$3) -> 300 | M8: =SUMIFS(Despesas!$C:$C,Despesas!$B:$B,$B8,Despesas!$E:$E,M$3) -> 89.98 | ... O8: =SUMIFS(Despesas!$C:$C,Despesas!$B:$B,$B8,Despesas!$E:$E,O$3) -> 0 | P8: =D8-E8 -> 469
B9: 2022/6 | C9: junho | D9: =SUMIF(Entradas!B:B,B9,Entradas!C:C) -> 4250 | E9: =SUM(F9:O9) -> 2634.85 | F9: =SUMIFS(Despesas!$C:$C,Despesas!$B:$B,$B9,Despesas!$E:$E,F$3) -> 149 | G9: =SUMIFS(Despesas!$C:$C,Despesas!$B:$B,$B9,Despesas!$E:$E,G$3) -> 0 | H9: =SUMIFS(Despesas!$C:$C,Despesas!$B:$B,$B9,Despesas!$E:$E,H$3) -> 529.72 | I9: =SUMIFS(Despesas!$C:$C,Despesas!$B:$B,$B9,Despesas!$E:$E,I$3) -> 677.03 | J9: =SUMIFS(Despesas!$C:$C,Despesas!$B:$B,$B9,Despesas!$E:$E,J$3) -> 200 | K9: =SUMIFS(Despesas!$C:$C,Despesas!$B:$B,$B9,Despesas!$E:$E,K$3) -> 437 | L9: =SUMIFS(Despesas!$C:$C,Despesas!$B:$B,$B9,Despesas!$E:$E,L$3) -> 600 | M9: =SUMIFS(Despesas!$C:$C,Despesas!$B:$B,$B9,Despesas!$E:$E,M$3) -> 42.1 | ... O9: =SUMIFS(Despesas!$C:$C,Despesas!$B:$B,$B9,Despesas!$E:$E,O$3) -> 0 | P9: =D9-E9 -> 1615.15
B10: 2022/7 | C10: julho | D10: =SUMIF(Entradas!B:B,B10,Entradas!C:C) -> 4650 | E10: =SUM(F10:O10) -> 3324.51 | F10: =SUMIFS(Despesas!$C:$C,Despesas!$B:$B,$B10,Despesas!$E:$E,F$3) -> 165.54 | G10: =SUMIFS(Despesas!$C:$C,Despesas!$B:$B,$B10,Despesas!$E:$E,G$3) -> 0 | H10: =SUMIFS(Despesas!$C:$C,Despesas!$B:$B,$B10,Despesas!$E:$E,H$3) -> 529.72 | I10: =SUMIFS(Despesas!$C:$C,Despesas!$B:$B,$B10,Despesas!$E:$E,I$3) -> 1538.44 | J10: =SUMIFS(Despesas!$C:$C,Despesas!$B:$B,$B10,Despesas!$E:$E,J$3) -> 200 | K10: =SUMIFS(Despesas!$C:$C,Despesas!$B:$B,$B10,Despesas!$E:$E,K$3) -> 400 | L10: =SUMIFS(Despesas!$C:$C,Despesas!$B:$B,$B10,Despesas!$E:$E,L$3) -> 450 | M10: =SUMIFS(Despesas!$C:$C,Despesas!$B:$B,$B10,Despesas!$E:$E,M$3) -> 40.81 | ... O10: =SUMIFS(Despesas!$C:$C,Despesas!$B:$B,$B10,Despesas!$E:$E,O$3) -> 0 | P10: =D10-E10 -> 1325.49
B11: 2022/8 | C11: agosto | D11: =SUMIF(Entradas!B:B,B11,Entradas!C:C) -> 9700 | E11: =SUM(F11:O11) -> 4024.74 | F11: =SUMIFS(Despesas!$C:$C,Despesas!$B:$B,$B11,Despesas!$E:$E,F$3) -> 155 | G11: =SUMIFS(Despesas!$C:$C,Despesas!$B:$B,$B11,Despesas!$E:$E,G$3) -> 538.43 | H11: =SUMIFS(Despesas!$C:$C,Despesas!$B:$B,$B11,Despesas!$E:$E,H$3) -> 529.72 | I11: =SUMIFS(Despesas!$C:$C,Despesas!$B:$B,$B11,Despesas!$E:$E,I$3) -> 1503.59 | J11: =SUMIFS(Despesas!$C:$C,Despesas!$B:$B,$B11,Despesas!$E:$E,J$3) -> 200 | K11: =SUMIFS(Despesas!$C:$C,Despesas!$B:$B,$B11,Despesas!$E:$E,K$3) -> 458 | L11: =SUMIFS(Despesas!$C:$C,Despesas!$B:$B,$B11,Despesas!$E:$E,L$3) -> 600 | M11: =SUMIFS(Despesas!$C:$C,Despesas!$B:$B,$B11,Despesas!$E:$E,M$3) -> 40 | ... O11: =SUMIFS(Despesas!$C:$C,Despesas!$B:$B,$B11,Despesas!$E:$E,O$3) -> 0 | P11: =D11-E11 -> 5675.26
B12: 2022/9 | C12: setembro | D12: =SUMIF(Entradas!B:B,B12,Entradas!C:C) -> 8000 | E12: =SUM(F12:O12) -> 4929.26 | F12: =SUMIFS(Despesas!$C:$C,Despesas!$B:$B,$B12,Despesas!$E:$E,F$3) -> 173 | G12: =SUMIFS(Despesas!$C:$C,Despesas!$B:$B,$B12,Despesas!$E:$E,G$3) -> 1279.43 | H12: =SUMIFS(Despesas!$C:$C,Despesas!$B:$B,$B12,Despesas!$E:$E,H$3) -> 529.72 | I12: =SUMIFS(Despesas!$C:$C,Despesas!$B:$B,$B12,Despesas!$E:$E,I$3) -> 1199.07 | J12: =SUMIFS(Despesas!$C:$C,Despesas!$B:$B,$B12,Despesas!$E:$E,J$3) -> 200 | K12: =SUMIFS(Despesas!$C:$C,Despesas!$B:$B,$B12,Despesas!$E:$E,K$3) -> 612 | L12: =SUMIFS(Despesas!$C:$C,Despesas!$B:$B,$B12,Despesas!$E:$E,L$3) -> 600 | M12: =SUMIFS(Despesas!$C:$C,Despesas!$B:$B,$B12,Despesas!$E:$E,M$3) -> 336.04 | ... O12: =SUMIFS(Despesas!$C:$C,Despesas!$B:$B,$B12,Despesas!$E:$E,O$3) -> 0 | P12: =D12-E12 -> 3070.74
B13: 2022/10 | C13: outubro | D13: =SUMIF(Entradas!B:B,B13,Entradas!C:C) -> 12689.95 | E13: =SUM(F13:O13) -> 5634.61 | F13: =SUMIFS(Despesas!$C:$C,Despesas!$B:$B,$B13,Despesas!$E:$E,F$3) -> 234.23 | G13: =SUMIFS(Despesas!$C:$C,Despesas!$B:$B,$B13,Despesas!$E:$E,G$3) -> 1337.06 | H13: =SUMIFS(Despesas!$C:$C,Despesas!$B:$B,$B13,Despesas!$E:$E,H$3) -> 529.72 | I13: =SUMIFS(Despesas!$C:$C,Despesas!$B:$B,$B13,Despesas!$E:$E,I$3) -> 1627.56 | J13: =SUMIFS(Despesas!$C:$C,Despesas!$B:$B,$B13,Despesas!$E:$E,J$3) -> 200 | K13: =SUMIFS(Despesas!$C:$C,Despesas!$B:$B,$B13,Despesas!$E:$E,K$3) -> 920 | L13: =SUMIFS(Despesas!$C:$C,Despesas!$B:$B,$B13,Despesas!$E:$E,L$3) -> 750 | M13: =SUMIFS(Despesas!$C:$C,Despesas!$B:$B,$B13,Despesas!$E:$E,M$3) -> 36.04 | ... O13: =SUMIFS(Despesas!$C:$C,Despesas!$B:$B,$B13,Despesas!$E:$E,O$3) -> 0 | P13: =D13-E13 -> 7055.34
B14: 2022/11 | C14: novembro | D14: =SUMIF(Entradas!B:B,B14,Entradas!C:C) -> 12995 | E14: =SUM(F14:O14) -> 4350.35 | F14: =SUMIFS(Despesas!$C:$C,Despesas!$B:$B,$B14,Despesas!$E:$E,F$3) -> 240.82 | G14: =SUMIFS(Despesas!$C:$C,Despesas!$B:$B,$B14,Despesas!$E:$E,G$3) -> 1278.08 | H14: =SUMIFS(Despesas!$C:$C,Despesas!$B:$B,$B14,Despesas!$E:$E,H$3) -> 529.72 | I14: =SUMIFS(Despesas!$C:$C,Despesas!$B:$B,$B14,Despesas!$E:$E,I$3) -> 577.48 | J14: =SUMIFS(Despesas!$C:$C,Despesas!$B:$B,$B14,Despesas!$E:$E,J$3) -> 200 | K14: =SUMIFS(Despesas!$C:$C,Despesas!$B:$B,$B14,Despesas!$E:$E,K$3) -> 889 | L14: =SUMIFS(Despesas!$C:$C,Despesas!$B:$B,$B14,Despesas!$E:$E,L$3) -> 600 | M14: =SUMIFS(Despesas!$C:$C,Despesas!$B:$B,$B14,Despesas!$E:$E,M$3) -> 35.25 | ... O14: =SUMIFS(Despesas!$C:$C,Despesas!$B:$B,$B14,Despesas!$E:$E,O$3) -> 0 | P14: =D14-E14 -> 8644.65
B15: 2022/12 | C15: dezembro | D15: =SUMIF(Entradas!B:B,B15,Entradas!C:C) -> 8000 | E15: =SUM(F15:O15) -> 8930.66 | F15: =SUMIFS(Despesas!$C:$C,Despesas!$B:$B,$B15,Despesas!$E:$E,F$3) -> 79 | G15: =SUMIFS(Despesas!$C:$C,Despesas!$B:$B,$B15,Despesas!$E:$E,G$3) -> 1066.8 | H15: =SUMIFS(Despesas!$C:$C,Despesas!$B:$B,$B15,Despesas!$E:$E,H$3) -> 529 | I15: =SUMIFS(Despesas!$C:$C,Despesas!$B:$B,$B15,Despesas!$E:$E,I$3) -> 786.82 | J15: =SUMIFS(Despesas!$C:$C,Despesas!$B:$B,$B15,Despesas!$E:$E,J$3) -> 400 | K15: =SUMIFS(Despesas!$C:$C,Despesas!$B:$B,$B15,Despesas!$E:$E,K$3) -> 4210 | L15: =SUMIFS(Despesas!$C:$C,Despesas!$B:$B,$B15,Despesas!$E:$E,L$3) -> 450 | M15: =SUMIFS(Despesas!$C:$C,Despesas!$B:$B,$B15,Despesas!$E:$E,M$3) -> 1409.04 | ... O15: =SUMIFS(Despesas!$C:$C,Despesas!$B:$B,$B15,Despesas!$E:$E,O$3) -> 0 | P15: =D15-E15 -> -930.66
C16: Fluxo | D16: =SUM(D4:D15) -> 68229.95 | E16: =SUM(E4:E15) -> 45732.97 | F16: =SUM(F4:F15) -> 1669.42 | G16: =SUM(G4:G15) -> 6080.19 | H16: =SUM(H4:H15) -> 6355.92 | I16: =SUM(I4:I15) -> 11586.74 | J16: =SUM(J4:J15) -> 3066.16 | K16: =SUM(K4:K15) -> 10104.5 | ... P16: =SUM(P4:P15) -> 22496.98
F18: =F32/SUM($F32:$O32) -> 0.008834294 | G18: =G32/SUM($F32:$O32) -> 0.0087708372 | H18: =H32/SUM($F32:$O32) -> 0.044721373 | I18: =I32/SUM($F32:$O32) -> 0.040524978 | J18: =J32/SUM($F32:$O32) -> 0.029775956 | K18: =K32/SUM($F32:$O32) -> 0.38968688 | L18: =L32/SUM($F32:$O32) -> 0.081130413 | M18: =M32/SUM($F32:$O32) -> 0.039570349 | ... O18: =O32/SUM($F32:$O32) -> 0
C19: 2023 | D19: =D3 -> Recebimentos | E19: =E3 -> Despesas | F19: =F3 -> Transporte | G19: =G3 -> Materiais | H19: =H3 -> Educação | I19: =I3 -> Marketing | J19: =J3 -> Empresa/CRP | K19: =K3 -> Aluguel | ... O19: =O3 -> 0 | P19: Total
B20: 2023/1 | C20: janeiro | D20: =SUMIF(Entradas!B:B,B20,Entradas!C:C) -> 10650 | E20: =SUM(F20:O20) -> 14217.29 | F20: =SUMIFS(Despesas!$C:$C,Despesas!$B:$B,$B20,Despesas!$E:$E,F$3) -> 113 | G20: =SUMIFS(Despesas!$C:$C,Despesas!$B:$B,$B20,Despesas!$E:$E,G$3) -> 37 | H20: =SUMIFS(Despesas!$C:$C,Despesas!$B:$B,$B20,Despesas!$E:$E,H$3) -> 529.72 | I20: =SUMIFS(Despesas!$C:$C,Despesas!$B:$B,$B20,Despesas!$E:$E,I$3) -> 716.28 | J20: =SUMIFS(Despesas!$C:$C,Despesas!$B:$B,$B20,Despesas!$E:$E,J$3) -> 738.46 | K20: =SUMIFS(Despesas!$C:$C,Despesas!$B:$B,$B20,Despesas!$E:$E,K$3) -> 3841.4 | L20: =SUMIFS(Despesas!$C:$C,Despesas!$B:$B,$B20,Despesas!$E:$E,L$3) -> 600 | M20: =SUMIFS(Despesas!$C:$C,Despesas!$B:$B,$B20,Despesas!$E:$E,M$3) -> 35.25 | ... O20: =SUMIFS(Despesas!$C:$C,Despesas!$B:$B,$B20,Despesas!$E:$E,O$3) -> 0 | P20: =D20-E20 -> -3567.29
B21: 2023/2 | C21: fevereiro | D21: =SUMIF(Entradas!B:B,B21,Entradas!C:C) -> 12725 | E21: =SUM(F21:O21) -> 20683.86 | F21: =SUMIFS(Despesas!$C:$C,Despesas!$B:$B,$B21,Despesas!$E:$E,F$3) -> 195 | G21: =SUMIFS(Despesas!$C:$C,Despesas!$B:$B,$B21,Despesas!$E:$E,G$3) -> 342 | H21: =SUMIFS(Despesas!$C:$C,Despesas!$B:$B,$B21,Despesas!$E:$E,H$3) -> 529.72 | I21: =SUMIFS(Despesas!$C:$C,Despesas!$B:$B,$B21,Despesas!$E:$E,I$3) -> 306 | J21: =SUMIFS(Despesas!$C:$C,Despesas!$B:$B,$B21,Despesas!$E:$E,J$3) -> 215 | K21: =SUMIFS(Despesas!$C:$C,Despesas!$B:$B,$B21,Despesas!$E:$E,K$3) -> 3946.34 | L21: =SUMIFS(Despesas!$C:$C,Despesas!$B:$B,$B21,Despesas!$E:$E,L$3) -> 750 | M21: =SUMIFS(Despesas!$C:$C,Despesas!$B:$B,$B21,Despesas!$E:$E,M$3) -> 21 | ... O21: =SUMIFS(Despesas!$C:$C,Despesas!$B:$B,$B21,Despesas!$E:$E,O$3) -> 0 | P21: =D21-E21 -> -7958.86
B22: 2023/3 | C22: março | D22: =SUMIF(Entradas!B:B,B22,Entradas!C:C) -> 12809.36 | E22: =SUM(F22:O22) -> 13173.61 | F22: =SUMIFS(Despesas!$C:$C,Despesas!$B:$B,$B22,Despesas!$E:$E,F$3) -> 60 | G22: =SUMIFS(Despesas!$C:$C,Despesas!$B:$B,$B22,Despesas!$E:$E,G$3) -> 0 | H22: =SUMIFS(Despesas!$C:$C,Despesas!$B:$B,$B22,Despesas!$E:$E,H$3) -> 794.58 | I22: =SUMIFS(Despesas!$C:$C,Despesas!$B:$B,$B22,Despesas!$E:$E,I$3) -> 271 | J22: =SUMIFS(Despesas!$C:$C,Despesas!$B:$B,$B22,Despesas!$E:$E,J$3) -> 215 | K22: =SUMIFS(Despesas!$C:$C,Despesas!$B:$B,$B22,Despesas!$E:$E,K$3) -> 3771.74 | L22: =SUMIFS(Despesas!$C:$C,Despesas!$B:$B,$B22,Despesas!$E:$E,L$3) -> 600 | M22: =SUMIFS(Despesas!$C:$C,Despesas!$B:$B,$B22,Despesas!$E:$E,M$3) -> 96.4 | ... O22: =SUMIFS(Despesas!$C:$C,Despesas!$B:$B,$B22,Despesas!$E:$E,O$3) -> 0 | P22: =D22-E22 -> -364.25
B23: 2023/4 | C23: abril | D23: =SUMIF(Entradas!B:B,B23,Entradas!C:C) -> 11101.25 | E23: =SUM(F23:O23) -> 12244.3 | F23: 60 | G23: =SUMIFS(Despesas!$C:$C,Despesas!$B:$B,$B23,Despesas!$E:$E,G$3) -> 0 | H23: =SUMIFS(Despesas!$C:$C,Despesas!$B:$B,$B23,Despesas!$E:$E,H$3) -> 629.72 | I23: =SUMIFS(Despesas!$C:$C,Despesas!$B:$B,$B23,Despesas!$E:$E,I$3) -> 249 | J23: =SUMIFS(Despesas!$C:$C,Despesas!$B:$B,$B23,Despesas!$E:$E,J$3) -> 215 | K23: =SUMIFS(Despesas!$C:$C,Despesas!$B:$B,$B23,Despesas!$E:$E,K$3) -> 5514.99 | L23: =SUMIFS(Despesas!$C:$C,Despesas!$B:$B,$B23,Despesas!$E:$E,L$3) -> 950 | M23: =SUMIFS(Despesas!$C:$C,Despesas!$B:$B,$B23,Despesas!$E:$E,M$3) -> 339.3 | N23: =SUMIFS(Despesas!$C:$C,Despesas!$B:$B,$B23,Despesas!$E:$E,N$3) -> 4286.29 | O23: =SUMIFS(Despesas!$C:$C,Despesas!$B:$B,$B23,Despesas!$E:$E,O$3) -> 0 | P23: =D23-E23 -> -1143.05
B24: 2023/5 | C24: maio | D24: =SUMIF(Entradas!B:B,B24,Entradas!C:C) -> 8906.25 | E24: =SUM(F24:O24) -> 9868.9 | F24: =SUMIFS(Despesas!$C:$C,Despesas!$B:$B,$B24,Despesas!$E:$E,F$3) -> 60 | G24: =SUMIFS(Despesas!$C:$C,Despesas!$B:$B,$B24,Despesas!$E:$E,G$3) -> 0 | H24: =SUMIFS(Despesas!$C:$C,Despesas!$B:$B,$B24,Despesas!$E:$E,H$3) -> 529.72 | I24: =SUMIFS(Despesas!$C:$C,Despesas!$B:$B,$B24,Despesas!$E:$E,I$3) -> 249 | J24: =SUMIFS(Despesas!$C:$C,Despesas!$B:$B,$B24,Despesas!$E:$E,J$3) -> 215 | K24: =SUMIFS(Despesas!$C:$C,Despesas!$B:$B,$B24,Despesas!$E:$E,K$3) -> 3642.96 | L24: =SUMIFS(Despesas!$C:$C,Despesas!$B:$B,$B24,Despesas!$E:$E,L$3) -> 600 | M24: =SUMIFS(Despesas!$C:$C,Despesas!$B:$B,$B24,Despesas!$E:$E,M$3) -> 370.95 | ... O24: =SUMIFS(Despesas!$C:$C,Despesas!$B:$B,$B24,Despesas!$E:$E,O$3) -> 0 | P24: =D24-E24 -> -962.65
B25: 2023/6 | C25: junho | D25: =SUMIF(Entradas!B:B,B25,Entradas!C:C) -> 13011.25 | E25: =SUM(F25:O25) -> 8560.26 | F25: =SUMIFS(Despesas!$C:$C,Despesas!$B:$B,$B25,Despesas!$E:$E,F$3) -> 70 | G25: =SUMIFS(Despesas!$C:$C,Despesas!$B:$B,$B25,Despesas!$E:$E,G$3) -> 475.36 | H25: =SUMIFS(Despesas!$C:$C,Despesas!$B:$B,$B25,Despesas!$E:$E,H$3) -> 529.72 | I25: =SUMIFS(Despesas!$C:$C,Despesas!$B:$B,$B25,Despesas!$E:$E,I$3) -> 1048 | J25: =SUMIFS(Despesas!$C:$C,Despesas!$B:$B,$B25,Despesas!$E:$E,J$3) -> 215 | K25: =SUMIFS(Despesas!$C:$C,Despesas!$B:$B,$B25,Despesas!$E:$E,K$3) -> 3642.96 | L25: =SUMIFS(Despesas!$C:$C,Despesas!$B:$B,$B25,Despesas!$E:$E,L$3) -> 810 | M25: =SUMIFS(Despesas!$C:$C,Despesas!$B:$B,$B25,Despesas!$E:$E,M$3) -> 115.7 | ... O25: =SUMIFS(Despesas!$C:$C,Despesas!$B:$B,$B25,Despesas!$E:$E,O$3) -> 0 | P25: =D25-E25 -> 4450.99
B26: 2023/7 | C26: julho | D26: =SUMIF(Entradas!B:B,B26,Entradas!C:C) -> 11471.25 | E26: =SUM(F26:O26) -> 5784.28 | F26: =SUMIFS(Despesas!$C:$C,Despesas!$B:$B,$B26,Despesas!$E:$E,F$3) -> 50 | G26: =SUMIFS(Despesas!$C:$C,Despesas!$B:$B,$B26,Despesas!$E:$E,G$3) -> 0 | H26: =SUMIFS(Despesas!$C:$C,Despesas!$B:$B,$B26,Despesas!$E:$E,H$3) -> 529.72 | I26: =SUMIFS(Despesas!$C:$C,Despesas!$B:$B,$B26,Despesas!$E:$E,I$3) -> 249 | J26: =SUMIFS(Despesas!$C:$C,Despesas!$B:$B,$B26,Despesas!$E:$E,J$3) -> 239 | K26: =SUMIFS(Despesas!$C:$C,Despesas!$B:$B,$B26,Despesas!$E:$E,K$3) -> 3642.9 | L26: =SUMIFS(Despesas!$C:$C,Despesas!$B:$B,$B26,Despesas!$E:$E,L$3) -> 720 | M26: =SUMIFS(Despesas!$C:$C,Despesas!$B:$B,$B26,Despesas!$E:$E,M$3) -> 211.73 | ... O26: =SUMIFS(Despesas!$C:$C,Despesas!$B:$B,$B26,Despesas!$E:$E,O$3) -> 0 | P26: =D26-E26 -> 5686.97
B27: 2023/8 | C27: agosto | D27: =SUMIF(Entradas!B:B,B27,Entradas!C:C) -> 18066.88 | E27: =SUM(F27:O27) -> 8728.21 | F27: =SUMIFS(Despesas!$C:$C,Despesas!$B:$B,$B27,Despesas!$E:$E,F$3) -> 85.16 | G27: =SUMIFS(Despesas!$C:$C,Despesas!$B:$B,$B27,Despesas!$E:$E,G$3) -> 0 | H27: =SUMIFS(Despesas!$C:$C,Despesas!$B:$B,$B27,Despesas!$E:$E,H$3) -> 529.72 | I27: =SUMIFS(Despesas!$C:$C,Despesas!$B:$B,$B27,Despesas!$E:$E,I$3) -> 249 | J27: =SUMIFS(Despesas!$C:$C,Despesas!$B:$B,$B27,Despesas!$E:$E,J$3) -> 231 | K27: =SUMIFS(Despesas!$C:$C,Despesas!$B:$B,$B27,Despesas!$E:$E,K$3) -> 3642.96 | L27: =SUMIFS(Despesas!$C:$C,Despesas!$B:$B,$B27,Despesas!$E:$E,L$3) -> 970 | M27: =SUMIFS(Despesas!$C:$C,Despesas!$B:$B,$B27,Despesas!$E:$E,M$3) -> 235.93 | ... O27: =SUMIFS(Despesas!$C:$C,Despesas!$B:$B,$B27,Despesas!$E:$E,O$3) -> 0 | P27: =D27-E27 -> 9338.67
B28: 2023/9 | C28: setembro | D28: =SUMIF(Entradas!B:B,B28,Entradas!C:C) -> 20177.74 | E28: =SUM(F28:O28) -> 6394.48 | F28: =SUMIFS(Despesas!$C:$C,Despesas!$B:$B,$B28,Despesas!$E:$E,F$3) -> 80 | G28: =SUMIFS(Despesas!$C:$C,Despesas!$B:$B,$B28,Despesas!$E:$E,G$3) -> 0 | H28: =SUMIFS(Despesas!$C:$C,Despesas!$B:$B,$B28,Despesas!$E:$E,H$3) -> 529.72 | I28: =SUMIFS(Despesas!$C:$C,Despesas!$B:$B,$B28,Despesas!$E:$E,I$3) -> 640.99 | J28: =SUMIFS(Despesas!$C:$C,Despesas!$B:$B,$B28,Despesas!$E:$E,J$3) -> 472.13 | K28: =SUMIFS(Despesas!$C:$C,Despesas!$B:$B,$B28,Despesas!$E:$E,K$3) -> 3651.4 | L28: =SUMIFS(Despesas!$C:$C,Despesas!$B:$B,$B28,Despesas!$E:$E,L$3) -> 840 | M28: =SUMIFS(Despesas!$C:$C,Despesas!$B:$B,$B28,Despesas!$E:$E,M$3) -> 180.24 | ... O28: =SUMIFS(Despesas!$C:$C,Despesas!$B:$B,$B28,Despesas!$E:$E,O$3) -> 0 | P28: =D28-E28 -> 13783.26
B29: 2023/10 | C29: outubro | D29: =SUMIF(Entradas!B:B,B29,Entradas!C:C) -> 23650 | E29: =SUM(F29:O29) -> 5942.14 | F29: =SUMIFS(Despesas!$C:$C,Despesas!$B:$B,$B29,Despesas!$E:$E,F$3) -> 116.53 | G29: =SUMIFS(Despesas!$C:$C,Despesas!$B:$B,$B29,Despesas!$E:$E,G$3) -> 0 | H29: =SUMIFS(Despesas!$C:$C,Despesas!$B:$B,$B29,Despesas!$E:$E,H$3) -> 181.5 | I29: =SUMIFS(Despesas!$C:$C,Despesas!$B:$B,$B29,Despesas!$E:$E,I$3) -> 263.86 | J29: =SUMIFS(Despesas!$C:$C,Despesas!$B:$B,$B29,Despesas!$E:$E,J$3) -> 254.4 | K29: =SUMIFS(Despesas!$C:$C,Despesas!$B:$B,$B29,Despesas!$E:$E,K$3) -> 3642.83 | L29: =SUMIFS(Despesas!$C:$C,Despesas!$B:$B,$B29,Despesas!$E:$E,L$3) -> 920 | M29: =SUMIFS(Despesas!$C:$C,Despesas!$B:$B,$B29,Despesas!$E:$E,M$3) -> 563.02 | ... O29: =SUMIFS(Despesas!$C:$C,Despesas!$B:$B,$B29,Despesas!$E:$E,O$3) -> 0 | P29: =D29-E29 -> 17707.86
B30: 2023/11 | C30: novembro | D30: =SUMIF(Entradas!B:B,B30,Entradas!C:C) -> 23470 | E30: =SUM(F30:O30) -> 6533.93 | F30: =SUMIFS(Despesas!$C:$C,Despesas!$B:$B,$B30,Despesas!$E:$E,F$3) -> 63 | G30: =SUMIFS(Despesas!$C:$C,Despesas!$B:$B,$B30,Despesas!$E:$E,G$3) -> 187.8 | H30: =SUMIFS(Despesas!$C:$C,Despesas!$B:$B,$B30,Despesas!$E:$E,H$3) -> 0 | I30: =SUMIFS(Despesas!$C:$C,Despesas!$B:$B,$B30,Despesas!$E:$E,I$3) -> 294.09 | J30: =SUMIFS(Despesas!$C:$C,Despesas!$B:$B,$B30,Despesas!$E:$E,J$3) -> 289.4 | K30: =SUMIFS(Despesas!$C:$C,Despesas!$B:$B,$B30,Despesas!$E:$E,K$3) -> 3681.26 | L30: =SUMIFS(Despesas!$C:$C,Despesas!$B:$B,$B30,Despesas!$E:$E,L$3) -> 1190 | M30: =SUMIFS(Despesas!$C:$C,Despesas!$B:$B,$B30,Despesas!$E:$E,M$3) -> 828.38 | ... O30: =SUMIFS(Despesas!$C:$C,Despesas!$B:$B,$B30,Despesas!$E:$E,O$3) -> 0 | P30: =D30-E30 -> 16936.07
B31: 2023/12 | C31: dezembro | D31: =SUMIF(Entradas!B:B,B31,Entradas!C:C) -> 19700 | E31: =SUM(F31:O31) -> 6689.78 | F31: =SUMIFS(Despesas!$C:$C,Despesas!$B:$B,$B31,Despesas!$E:$E,F$3) -> 97.01 | G31: =SUMIFS(Despesas!$C:$C,Despesas!$B:$B,$B31,Despesas!$E:$E,G$3) -> 0 | H31: =SUMIFS(Despesas!$C:$C,Despesas!$B:$B,$B31,Despesas!$E:$E,H$3) -> 0 | I31: =SUMIFS(Despesas!$C:$C,Despesas!$B:$B,$B31,Despesas!$E:$E,I$3) -> 279 | J31: =SUMIFS(Despesas!$C:$C,Despesas!$B:$B,$B31,Despesas!$E:$E,J$3) -> 238.62 | K31: =SUMIFS(Despesas!$C:$C,Despesas!$B:$B,$B31,Despesas!$E:$E,K$3) -> 3681.26 | L31: =SUMIFS(Despesas!$C:$C,Despesas!$B:$B,$B31,Despesas!$E:$E,L$3) -> 690 | M31: =SUMIFS(Despesas!$C:$C,Despesas!$B:$B,$B31,Despesas!$E:$E,M$3) -> 1703.89 | ... O31: =SUMIFS(Despesas!$C:$C,Despesas!$B:$B,$B31,Despesas!$E:$E,O$3) -> 0 | P31: =D31-E31 -> 13010.22
C32: Fluxo | D32: =SUM(D20:D31) -> 185738.98 | E32: =SUM(E20:E31) -> 118821.04 | F32: =SUM(F20:F31) -> 1049.7 | G32: =SUM(G20:G31) -> 1042.16 | H32: =SUM(H20:H31) -> 5313.84 | I32: =SUM(I20:I31) -> 4815.22 | J32: =SUM(J20:J31) -> 3538.01 | K32: =SUM(K20:K31) -> 46303 | ... P32: =SUM(P20:P31) -> 66917.94
F34: =F48/SUM($F48:$O48) -> 0.010001561 | G34: =G48/SUM($F48:$O48) -> 0.08725148 | H34: =H48/SUM($F48:$O48) -> 0.010446343 | I34: =I48/SUM($F48:$O48) -> 0.031779095 | J34: =J48/SUM($F48:$O48) -> 0.096668905 | K34: =K48/SUM($F48:$O48) -> 0.49802808 | L34: =L48/SUM($F48:$O48) -> 0.094299985 | M34: =M48/SUM($F48:$O48) -> 0.094286364 | ... O34: =O48/SUM($F48:$O48) -> 0
C35: 2024 | D35: =D19 -> Recebimentos | E35: =E19 -> Despesas | F35: =F19 -> Transporte | G35: =G19 -> Materiais | H35: =H19 -> Educação | I35: =I19 -> Marketing | J35: =J19 -> Empresa/CRP | K35: =K19 -> Aluguel | ... N35: =N19 -> Reforma | P35: =P19 -> Total
B36: 2024/1 | C36: janeiro | D36: =SUMIF(Entradas!B:B,B36,Entradas!C:C) -> 15930 | E36: =SUM(F36:O36) -> 6553.57 | F36: =SUMIFS(Despesas!$C:$C,Despesas!$B:$B,$B36,Despesas!$E:$E,F$3) -> 50 | G36: =SUMIFS(Despesas!$C:$C,Despesas!$B:$B,$B36,Despesas!$E:$E,G$3) -> 32 | H36: =SUMIFS(Despesas!$C:$C,Despesas!$B:$B,$B36,Despesas!$E:$E,H$3) -> 997 | I36: =SUMIFS(Despesas!$C:$C,Despesas!$B:$B,$B36,Despesas!$E:$E,I$3) -> 269 | J36: =SUMIFS(Despesas!$C:$C,Despesas!$B:$B,$B36,Despesas!$E:$E,J$3) -> 246.2 | K36: =SUMIFS(Despesas!$C:$C,Despesas!$B:$B,$B36,Despesas!$E:$E,K$3) -> 3895.11 | L36: =SUMIFS(Despesas!$C:$C,Despesas!$B:$B,$B36,Despesas!$E:$E,L$3) -> 600 | M36: =SUMIFS(Despesas!$C:$C,Despesas!$B:$B,$B36,Despesas!$E:$E,M$3) -> 464.26 | ... O36: =SUMIFS(Despesas!$C:$C,Despesas!$B:$B,$B36,Despesas!$E:$E,O$3) -> 0 | P36: =D36-E36 -> 9376.43
B37: 2024/2 | C37: fevereiro | D37: =SUMIF(Entradas!B:B,B37,Entradas!C:C) -> 25710 | E37: =SUM(F37:O37) -> 6573.42 | F37: =SUMIFS(Despesas!$C:$C,Despesas!$B:$B,$B37,Despesas!$E:$E,F$3) -> 100 | G37: =SUMIFS(Despesas!$C:$C,Despesas!$B:$B,$B37,Despesas!$E:$E,G$3) -> 0 | H37: =SUMIFS(Despesas!$C:$C,Despesas!$B:$B,$B37,Despesas!$E:$E,H$3) -> 0 | I37: =SUMIFS(Despesas!$C:$C,Despesas!$B:$B,$B37,Despesas!$E:$E,I$3) -> 274 | J37: =SUMIFS(Despesas!$C:$C,Despesas!$B:$B,$B37,Despesas!$E:$E,J$3) -> 902.43 | K37: =SUMIFS(Despesas!$C:$C,Despesas!$B:$B,$B37,Despesas!$E:$E,K$3) -> 3975.37 | L37: =SUMIFS(Despesas!$C:$C,Despesas!$B:$B,$B37,Despesas!$E:$E,L$3) -> 800 | M37: =SUMIFS(Despesas!$C:$C,Despesas!$B:$B,$B37,Despesas!$E:$E,M$3) -> 316.62 | ... O37: =SUMIFS(Despesas!$C:$C,Despesas!$B:$B,$B37,Despesas!$E:$E,O$3) -> 0 | P37: =D37-E37 -> 19136.58
B38: 2024/3 | C38: março | D38: =SUMIF(Entradas!B:B,B38,Entradas!C:C) -> 21254 | E38: =SUM(F38:O38) -> 5965.4 | F38: =SUMIFS(Despesas!$C:$C,Despesas!$B:$B,$B38,Despesas!$E:$E,F$3) -> 50 | G38: =SUMIFS(Despesas!$C:$C,Despesas!$B:$B,$B38,Despesas!$E:$E,G$3) -> 0 | H38: =SUMIFS(Despesas!$C:$C,Despesas!$B:$B,$B38,Despesas!$E:$E,H$3) -> 0 | I38: =SUMIFS(Despesas!$C:$C,Despesas!$B:$B,$B38,Despesas!$E:$E,I$3) -> 249 | J38: =SUMIFS(Despesas!$C:$C,Despesas!$B:$B,$B38,Despesas!$E:$E,J$3) -> 295.57 | K38: =SUMIFS(Despesas!$C:$C,Despesas!$B:$B,$B38,Despesas!$E:$E,K$3) -> 3975.27 | L38: =SUMIFS(Despesas!$C:$C,Despesas!$B:$B,$B38,Despesas!$E:$E,L$3) -> 850 | M38: =SUMIFS(Despesas!$C:$C,Despesas!$B:$B,$B38,Despesas!$E:$E,M$3) -> 545.56 | ... O38: =SUMIFS(Despesas!$C:$C,Despesas!$B:$B,$B38,Despesas!$E:$E,O$3) -> 0 | P38: =D38-E38 -> 15288.6
B39: 2024/4 | C39: abril | D39: =SUMIF(Entradas!B:B,B39,Entradas!C:C) -> 25153.45 | E39: =SUM(F39:O39) -> 10377.44 | F39: =SUMIFS(Despesas!$C:$C,Despesas!$B:$B,$B39,Despesas!$E:$E,F$3) -> 60 | G39: =SUMIFS(Despesas!$C:$C,Despesas!$B:$B,$B39,Despesas!$E:$E,G$3) -> 0 | H39: =SUMIFS(Despesas!$C:$C,Despesas!$B:$B,$B39,Despesas!$E:$E,H$3) -> 0 | I39: =SUMIFS(Despesas!$C:$C,Despesas!$B:$B,$B39,Despesas!$E:$E,I$3) -> 249 | J39: =SUMIFS(Despesas!$C:$C,Despesas!$B:$B,$B39,Despesas!$E:$E,J$3) -> 613.12 | K39: =SUMIFS(Despesas!$C:$C,Despesas!$B:$B,$B39,Despesas!$E:$E,K$3) -> 4060.02 | L39: =SUMIFS(Despesas!$C:$C,Despesas!$B:$B,$B39,Despesas!$E:$E,L$3) -> 800 | M39: =SUMIFS(Despesas!$C:$C,Despesas!$B:$B,$B39,Despesas!$E:$E,M$3) -> 728.68 | ... O39: =SUMIFS(Despesas!$C:$C,Despesas!$B:$B,$B39,Despesas!$E:$E,O$3) -> 0 | P39: =D39-E39 -> 14776.01
B40: 2024/5 | C40: maio | D40: =SUMIF(Entradas!B:B,B40,Entradas!C:C) -> 26466.9 | E40: =SUM(F40:O40) -> 7285.3 | F40: =SUMIFS(Despesas!$C:$C,Despesas!$B:$B,$B40,Despesas!$E:$E,F$3) -> 70 | G40: =SUMIFS(Despesas!$C:$C,Despesas!$B:$B,$B40,Despesas!$E:$E,G$3) -> 0 | H40: =SUMIFS(Despesas!$C:$C,Despesas!$B:$B,$B40,Despesas!$E:$E,H$3) -> 0 | I40: =SUMIFS(Despesas!$C:$C,Despesas!$B:$B,$B40,Despesas!$E:$E,I$3) -> 249 | J40: =SUMIFS(Despesas!$C:$C,Despesas!$B:$B,$B40,Despesas!$E:$E,J$3) -> 309.2 | K40: =SUMIFS(Despesas!$C:$C,Despesas!$B:$B,$B40,Despesas!$E:$E,K$3) -> 3953.26 | L40: =SUMIFS(Despesas!$C:$C,Despesas!$B:$B,$B40,Despesas!$E:$E,L$3) -> 300 | M40: =SUMIFS(Despesas!$C:$C,Despesas!$B:$B,$B40,Despesas!$E:$E,M$3) -> 703.84 | ... O40: =SUMIFS(Despesas!$C:$C,Despesas!$B:$B,$B40,Despesas!$E:$E,O$3) -> 0 | P40: =D40-E40 -> 19181.6
B41: 2024/6 | C41: junho | D41: =SUMIF(Entradas!B:B,B41,Entradas!C:C) -> 30623.45 | E41: =SUM(F41:O41) -> 6505.78 | F41: =SUMIFS(Despesas!$C:$C,Despesas!$B:$B,$B41,Despesas!$E:$E,F$3) -> 64.55 | G41: =SUMIFS(Despesas!$C:$C,Despesas!$B:$B,$B41,Despesas!$E:$E,G$3) -> 0 | H41: =SUMIFS(Despesas!$C:$C,Despesas!$B:$B,$B41,Despesas!$E:$E,H$3) -> 0 | I41: =SUMIFS(Despesas!$C:$C,Despesas!$B:$B,$B41,Despesas!$E:$E,I$3) -> 249 | J41: =SUMIFS(Despesas!$C:$C,Despesas!$B:$B,$B41,Despesas!$E:$E,J$3) -> 672.12 | K41: =SUMIFS(Despesas!$C:$C,Despesas!$B:$B,$B41,Despesas!$E:$E,K$3) -> 3953.26 | L41: =SUMIFS(Despesas!$C:$C,Despesas!$B:$B,$B41,Despesas!$E:$E,L$3) -> 750 | M41: =SUMIFS(Despesas!$C:$C,Despesas!$B:$B,$B41,Despesas!$E:$E,M$3) -> 816.85 | ... O41: =SUMIFS(Despesas!$C:$C,Despesas!$B:$B,$B41,Despesas!$E:$E,O$3) -> 0 | P41: =D41-E41 -> 24117.67
B42: 2024/7 | C42: julho | D42: =SUMIF(Entradas!B:B,B42,Entradas!C:C) -> 27510 | E42: =SUM(F42:O42) -> 6656.1 | F42: =SUMIFS(Despesas!$C:$C,Despesas!$B:$B,$B42,Despesas!$E:$E,F$3) -> 100 | G42: =SUMIFS(Despesas!$C:$C,Despesas!$B:$B,$B42,Despesas!$E:$E,G$3) -> 0 | H42: =SUMIFS(Despesas!$C:$C,Despesas!$B:$B,$B42,Despesas!$E:$E,H$3) -> 0 | I42: =SUMIFS(Despesas!$C:$C,Despesas!$B:$B,$B42,Despesas!$E:$E,I$3) -> 249 | J42: =SUMIFS(Despesas!$C:$C,Despesas!$B:$B,$B42,Despesas!$E:$E,J$3) -> 1203.04 | K42: =SUMIFS(Despesas!$C:$C,Despesas!$B:$B,$B42,Despesas!$E:$E,K$3) -> 3953.26 | L42: =SUMIFS(Despesas!$C:$C,Despesas!$B:$B,$B42,Despesas!$E:$E,L$3) -> 700 | M42: =SUMIFS(Despesas!$C:$C,Despesas!$B:$B,$B42,Despesas!$E:$E,M$3) -> 450.8 | ... O42: =SUMIFS(Despesas!$C:$C,Despesas!$B:$B,$B42,Despesas!$E:$E,O$3) -> 0 | P42: =D42-E42 -> 20853.9
B43: 2024/8 | C43: agosto | D43: =SUMIF(Entradas!B:B,B43,Entradas!C:C) -> 28065 | E43: =SUM(F43:O43) -> 7116.86 | F43: =SUMIFS(Despesas!$C:$C,Despesas!$B:$B,$B43,Despesas!$E:$E,F$3) -> 80 | G43: =SUMIFS(Despesas!$C:$C,Despesas!$B:$B,$B43,Despesas!$E:$E,G$3) -> 0 | H43: =SUMIFS(Despesas!$C:$C,Despesas!$B:$B,$B43,Despesas!$E:$E,H$3) -> 0 | I43: =SUMIFS(Despesas!$C:$C,Despesas!$B:$B,$B43,Despesas!$E:$E,I$3) -> 249 | J43: =SUMIFS(Despesas!$C:$C,Despesas!$B:$B,$B43,Despesas!$E:$E,J$3) -> 882.04 | K43: =SUMIFS(Despesas!$C:$C,Despesas!$B:$B,$B43,Despesas!$E:$E,K$3) -> 3953.26 | L43: =SUMIFS(Despesas!$C:$C,Despesas!$B:$B,$B43,Despesas!$E:$E,L$3) -> 1150 | M43: =SUMIFS(Despesas!$C:$C,Despesas!$B:$B,$B43,Despesas!$E:$E,M$3) -> 802.56 | ... O43: =SUMIFS(Despesas!$C:$C,Despesas!$B:$B,$B43,Despesas!$E:$E,O$3) -> 0 | P43: =D43-E43 -> 20948.14
B44: 2024/9 | C44: setembro | D44: =SUMIF(Entradas!B:B,B44,Entradas!C:C) -> 26895 | E44: =SUM(F44:O44) -> 7369.01 | F44: =SUMIFS(Despesas!$C:$C,Despesas!$B:$B,$B44,Despesas!$E:$E,F$3) -> 100 | G44: =SUMIFS(Despesas!$C:$C,Despesas!$B:$B,$B44,Despesas!$E:$E,G$3) -> 233.4 | H44: =SUMIFS(Despesas!$C:$C,Despesas!$B:$B,$B44,Despesas!$E:$E,H$3) -> 0 | I44: =SUMIFS(Despesas!$C:$C,Despesas!$B:$B,$B44,Despesas!$E:$E,I$3) -> 249 | J44: =SUMIFS(Despesas!$C:$C,Despesas!$B:$B,$B44,Despesas!$E:$E,J$3) -> 1102.24 | K44: =SUMIFS(Despesas!$C:$C,Despesas!$B:$B,$B44,Despesas!$E:$E,K$3) -> 3953.26 | L44: =SUMIFS(Despesas!$C:$C,Despesas!$B:$B,$B44,Despesas!$E:$E,L$3) -> 1000 | M44: =SUMIFS(Despesas!$C:$C,Despesas!$B:$B,$B44,Despesas!$E:$E,M$3) -> 731.11 | ... O44: =SUMIFS(Despesas!$C:$C,Despesas!$B:$B,$B44,Despesas!$E:$E,O$3) -> 0 | P44: =D44-E44 -> 19525.99
B45: 2024/10 | C45: outubro | D45: =SUMIF(Entradas!B:B,B45,Entradas!C:C) -> 31340 | E45: =SUM(F45:O45) -> 15004.71 | F45: =SUMIFS(Despesas!$C:$C,Despesas!$B:$B,$B45,Despesas!$E:$E,F$3) -> 100 | G45: =SUMIFS(Despesas!$C:$C,Despesas!$B:$B,$B45,Despesas!$E:$E,G$3) -> 8061.89 | H45: =SUMIFS(Despesas!$C:$C,Despesas!$B:$B,$B45,Despesas!$E:$E,H$3) -> 0 | I45: =SUMIFS(Despesas!$C:$C,Despesas!$B:$B,$B45,Despesas!$E:$E,I$3) -> 249 | J45: =SUMIFS(Despesas!$C:$C,Despesas!$B:$B,$B45,Despesas!$E:$E,J$3) -> 886.85 | K45: =SUMIFS(Despesas!$C:$C,Despesas!$B:$B,$B45,Despesas!$E:$E,K$3) -> 3953.26 | L45: =SUMIFS(Despesas!$C:$C,Despesas!$B:$B,$B45,Despesas!$E:$E,L$3) -> 850 | M45: =SUMIFS(Despesas!$C:$C,Despesas!$B:$B,$B45,Despesas!$E:$E,M$3) -> 903.71 | ... O45: =SUMIFS(Despesas!$C:$C,Despesas!$B:$B,$B45,Despesas!$E:$E,O$3) -> 0 | P45: =D45-E45 -> 16335.29
B46: 2024/11 | C46: novembro | D46: =SUMIF(Entradas!B:B,B46,Entradas!C:C) -> 29054.64 | E46: =SUM(F46:O46) -> 8184.31 | F46: =SUMIFS(Despesas!$C:$C,Despesas!$B:$B,$B46,Despesas!$E:$E,F$3) -> 100 | G46: =SUMIFS(Despesas!$C:$C,Despesas!$B:$B,$B46,Despesas!$E:$E,G$3) -> 0 | H46: =SUMIFS(Despesas!$C:$C,Despesas!$B:$B,$B46,Despesas!$E:$E,H$3) -> 0 | I46: =SUMIFS(Despesas!$C:$C,Despesas!$B:$B,$B46,Despesas!$E:$E,I$3) -> 249 | J46: =SUMIFS(Despesas!$C:$C,Despesas!$B:$B,$B46,Despesas!$E:$E,J$3) -> 1243.84 | K46: =SUMIFS(Despesas!$C:$C,Despesas!$B:$B,$B46,Despesas!$E:$E,K$3) -> 3953.26 | L46: =SUMIFS(Despesas!$C:$C,Despesas!$B:$B,$B46,Despesas!$E:$E,L$3) -> 850 | M46: =SUMIFS(Despesas!$C:$C,Despesas!$B:$B,$B46,Despesas!$E:$E,M$3) -> 1788.21 | ... O46: =SUMIFS(Despesas!$C:$C,Despesas!$B:$B,$B46,Despesas!$E:$E,O$3) -> 0 | P46: =D46-E46 -> 20870.33
B47: 2024/12 | C47: dezembro | D47: =SUMIF(Entradas!B:B,B47,Entradas!C:C) -> 11600 | E47: =SUM(F47:O47) -> 7848.2 | F47: =SUMIFS(Despesas!$C:$C,Despesas!$B:$B,$B47,Despesas!$E:$E,F$3) -> 80 | G47: =SUMIFS(Despesas!$C:$C,Despesas!$B:$B,$B47,Despesas!$E:$E,G$3) -> 0 | H47: =SUMIFS(Despesas!$C:$C,Despesas!$B:$B,$B47,Despesas!$E:$E,H$3) -> 0 | I47: =SUMIFS(Despesas!$C:$C,Despesas!$B:$B,$B47,Despesas!$E:$E,I$3) -> 249 | J47: =SUMIFS(Despesas!$C:$C,Despesas!$B:$B,$B47,Despesas!$E:$E,J$3) -> 869.44 | K47: =SUMIFS(Despesas!$C:$C,Despesas!$B:$B,$B47,Despesas!$E:$E,K$3) -> 3953.26 | L47: =SUMIFS(Despesas!$C:$C,Despesas!$B:$B,$B47,Despesas!$E:$E,L$3) -> 350 | M47: =SUMIFS(Despesas!$C:$C,Despesas!$B:$B,$B47,Despesas!$E:$E,M$3) -> 746.5 | ... O47: =SUMIFS(Despesas!$C:$C,Despesas!$B:$B,$B47,Despesas!$E:$E,O$3) -> 0 | P47: =D47-E47 -> 3751.8
C48: Fluxo | D48: =SUM(D36:D47) -> 299602.44 | E48: =SUM(E36:E47) -> 95440.1 | F48: =SUM(F36:F47) -> 954.55 | G48: =SUM(G36:G47) -> 8327.29 | H48: =SUM(H36:H47) -> 997 | I48: =SUM(I36:I47) -> 3033 | J48: =SUM(J36:J47) -> 9226.09 | K48: =SUM(K36:K47) -> 47531.85 | ... P48: =SUM(P36:P47) -> 204162.34
C51: 2025 | D51: =D35 -> Recebimentos | E51: =E35 -> Despesas | F51: =F35 -> Transporte | G51: =G35 -> Materiais | H51: =H35 -> Educação | I51: =I35 -> Marketing | J51: =J35 -> Empresa/CRP | K51: =K35 -> Aluguel | ... P51: =P35 -> Total
B52: 2025/1 | C52: janeiro | D52: =SUMIF(Entradas!B:B,B52,Entradas!C:C) -> 16106.91 | E52: =SUM(F52:O52) -> 8798.54 | F52: =SUMIFS(Despesas!$C:$C,Despesas!$B:$B,$B52,Despesas!$E:$E,F$3) -> 50 | G52: =SUMIFS(Despesas!$C:$C,Despesas!$B:$B,$B52,Despesas!$E:$E,G$3) -> 0 | H52: =SUMIFS(Despesas!$C:$C,Despesas!$B:$B,$B52,Despesas!$E:$E,H$3) -> 0 | I52: =SUMIFS(Despesas!$C:$C,Despesas!$B:$B,$B52,Despesas!$E:$E,I$3) -> 249 | J52: =SUMIFS(Despesas!$C:$C,Despesas!$B:$B,$B52,Despesas!$E:$E,J$3) -> 1558.07 | K52: =SUMIFS(Despesas!$C:$C,Despesas!$B:$B,$B52,Despesas!$E:$E,K$3) -> 3953.26 | L52: =SUMIFS(Despesas!$C:$C,Despesas!$B:$B,$B52,Despesas!$E:$E,L$3) -> 480 | M52: =SUMIFS(Despesas!$C:$C,Despesas!$B:$B,$B52,Despesas!$E:$E,M$3) -> 2508.21 | ... O52: =SUMIFS(Despesas!$C:$C,Despesas!$B:$B,$B52,Despesas!$E:$E,O$3) -> 0 | P52: =D52-E52 -> 7308.37
B53: 2025/2 | C53: fevereiro | D53: =SUMIF(Entradas!B:B,B53,Entradas!C:C) -> 21507.6 | E53: =SUM(F53:O53) -> 9261.27 | F53: =SUMIFS(Despesas!$C:$C,Despesas!$B:$B,$B53,Despesas!$E:$E,F$3) -> 64.71 | G53: =SUMIFS(Despesas!$C:$C,Despesas!$B:$B,$B53,Despesas!$E:$E,G$3) -> 392.09 | H53: =SUMIFS(Despesas!$C:$C,Despesas!$B:$B,$B53,Despesas!$E:$E,H$3) -> 0 | I53: =SUMIFS(Despesas!$C:$C,Despesas!$B:$B,$B53,Despesas!$E:$E,I$3) -> 299 | J53: =SUMIFS(Despesas!$C:$C,Despesas!$B:$B,$B53,Despesas!$E:$E,J$3) -> 886.24 | K53: =SUMIFS(Despesas!$C:$C,Despesas!$B:$B,$B53,Despesas!$E:$E,K$3) -> 5573.5 | L53: =SUMIFS(Despesas!$C:$C,Despesas!$B:$B,$B53,Despesas!$E:$E,L$3) -> 930 | M53: =SUMIFS(Despesas!$C:$C,Despesas!$B:$B,$B53,Despesas!$E:$E,M$3) -> 1115.73 | ... O53: =SUMIFS(Despesas!$C:$C,Despesas!$B:$B,$B53,Despesas!$E:$E,O$3) -> 0 | P53: =D53-E53 -> 12246.33
B54: 2025/3 | C54: março | D54: =SUMIF(Entradas!B:B,B54,Entradas!C:C) -> 18930 | E54: =SUM(F54:O54) -> 7669 | F54: =SUMIFS(Despesas!$C:$C,Despesas!$B:$B,$B54,Despesas!$E:$E,F$3) -> 80 | G54: =SUMIFS(Despesas!$C:$C,Despesas!$B:$B,$B54,Despesas!$E:$E,G$3) -> 376.46 | H54: =SUMIFS(Despesas!$C:$C,Despesas!$B:$B,$B54,Despesas!$E:$E,H$3) -> 0 | I54: =SUMIFS(Despesas!$C:$C,Despesas!$B:$B,$B54,Despesas!$E:$E,I$3) -> 589 | J54: =SUMIFS(Despesas!$C:$C,Despesas!$B:$B,$B54,Despesas!$E:$E,J$3) -> 1019.98 | K54: =SUMIFS(Despesas!$C:$C,Despesas!$B:$B,$B54,Despesas!$E:$E,K$3) -> 4253.26 | L54: =SUMIFS(Despesas!$C:$C,Despesas!$B:$B,$B54,Despesas!$E:$E,L$3) -> 810 | M54: =SUMIFS(Despesas!$C:$C,Despesas!$B:$B,$B54,Despesas!$E:$E,M$3) -> 540.3 | ... O54: =SUMIFS(Despesas!$C:$C,Despesas!$B:$B,$B54,Despesas!$E:$E,O$3) -> 0 | P54: =D54-E54 -> 11261
B55: 2025/4 | C55: abril | D55: =SUMIF(Entradas!B:B,B55,Entradas!C:C) -> 15870 | E55: =SUM(F55:O55) -> 7291.82 | F55: =SUMIFS(Despesas!$C:$C,Despesas!$B:$B,$B55,Despesas!$E:$E,F$3) -> 70 | G55: =SUMIFS(Despesas!$C:$C,Despesas!$B:$B,$B55,Despesas!$E:$E,G$3) -> 0 | H55: =SUMIFS(Despesas!$C:$C,Despesas!$B:$B,$B55,Despesas!$E:$E,H$3) -> 0 | I55: =SUMIFS(Despesas!$C:$C,Despesas!$B:$B,$B55,Despesas!$E:$E,I$3) -> 299 | J55: =SUMIFS(Despesas!$C:$C,Despesas!$B:$B,$B55,Despesas!$E:$E,J$3) -> 872.44 | K55: =SUMIFS(Despesas!$C:$C,Despesas!$B:$B,$B55,Despesas!$E:$E,K$3) -> 4373.79 | L55: =SUMIFS(Despesas!$C:$C,Despesas!$B:$B,$B55,Despesas!$E:$E,L$3) -> 1000 | M55: =SUMIFS(Despesas!$C:$C,Despesas!$B:$B,$B55,Despesas!$E:$E,M$3) -> 676.59 | ... O55: =SUMIFS(Despesas!$C:$C,Despesas!$B:$B,$B55,Despesas!$E:$E,O$3) -> 0 | P55: =D55-E55 -> 8578.18
B56: 2025/5 | C56: maio | D56: =SUMIF(Entradas!B:B,B56,Entradas!C:C) -> 16758 | E56: =SUM(F56:O56) -> 7020.52 | F56: =SUMIFS(Despesas!$C:$C,Despesas!$B:$B,$B56,Despesas!$E:$E,F$3) -> 80 | G56: =SUMIFS(Despesas!$C:$C,Despesas!$B:$B,$B56,Despesas!$E:$E,G$3) -> 0 | H56: =SUMIFS(Despesas!$C:$C,Despesas!$B:$B,$B56,Despesas!$E:$E,H$3) -> 0 | I56: =SUMIFS(Despesas!$C:$C,Despesas!$B:$B,$B56,Despesas!$E:$E,I$3) -> 299 | J56: =SUMIFS(Despesas!$C:$C,Despesas!$B:$B,$B56,Despesas!$E:$E,J$3) -> 827.43 | K56: =SUMIFS(Despesas!$C:$C,Despesas!$B:$B,$B56,Despesas!$E:$E,K$3) -> 4373.79 | L56: =SUMIFS(Despesas!$C:$C,Despesas!$B:$B,$B56,Despesas!$E:$E,L$3) -> 800 | M56: =SUMIFS(Despesas!$C:$C,Despesas!$B:$B,$B56,Despesas!$E:$E,M$3) -> 640.3 | ... O56: =SUMIFS(Despesas!$C:$C,Despesas!$B:$B,$B56,Despesas!$E:$E,O$3) -> 0 | P56: =D56-E56 -> 9737.48
B57: 2025/6 | C57: junho | D57: =SUMIF(Entradas!B:B,B57,Entradas!C:C) -> 14868 | E57: =SUM(F57:O57) -> 7612.21 | F57: =SUMIFS(Despesas!$C:$C,Despesas!$B:$B,$B57,Despesas!$E:$E,F$3) -> 80 | G57: =SUMIFS(Despesas!$C:$C,Despesas!$B:$B,$B57,Despesas!$E:$E,G$3) -> 0 | H57: =SUMIFS(Despesas!$C:$C,Despesas!$B:$B,$B57,Despesas!$E:$E,H$3) -> 0 | I57: =SUMIFS(Despesas!$C:$C,Despesas!$B:$B,$B57,Despesas!$E:$E,I$3) -> 299 | J57: =SUMIFS(Despesas!$C:$C,Despesas!$B:$B,$B57,Despesas!$E:$E,J$3) -> 728.96 | K57: =SUMIFS(Despesas!$C:$C,Despesas!$B:$B,$B57,Despesas!$E:$E,K$3) -> 4373.79 | L57: =SUMIFS(Despesas!$C:$C,Despesas!$B:$B,$B57,Despesas!$E:$E,L$3) -> 600 | M57: =SUMIFS(Despesas!$C:$C,Despesas!$B:$B,$B57,Despesas!$E:$E,M$3) -> 1530.46 | ... O57: =SUMIFS(Despesas!$C:$C,Despesas!$B:$B,$B57,Despesas!$E:$E,O$3) -> 0 | P57: =D57-E57 -> 7255.79
B58: 2025/7 | C58: julho | D58: =SUMIF(Entradas!B:B,B58,Entradas!C:C) -> 13083 | E58: =SUM(F58:O58) -> 3865.9 | F58: =SUMIFS(Despesas!$C:$C,Despesas!$B:$B,$B58,Despesas!$E:$E,F$3) -> 0 | G58: =SUMIFS(Despesas!$C:$C,Despesas!$B:$B,$B58,Despesas!$E:$E,G$3) -> 0 | H58: =SUMIFS(Despesas!$C:$C,Despesas!$B:$B,$B58,Despesas!$E:$E,H$3) -> 0 | I58: =SUMIFS(Despesas!$C:$C,Despesas!$B:$B,$B58,Despesas!$E:$E,I$3) -> 299 | J58: =SUMIFS(Despesas!$C:$C,Despesas!$B:$B,$B58,Despesas!$E:$E,J$3) -> 0 | K58: =SUMIFS(Despesas!$C:$C,Despesas!$B:$B,$B58,Despesas!$E:$E,K$3) -> 3500 | L58: =SUMIFS(Despesas!$C:$C,Despesas!$B:$B,$B58,Despesas!$E:$E,L$3) -> 0 | M58: =SUMIFS(Despesas!$C:$C,Despesas!$B:$B,$B58,Despesas!$E:$E,M$3) -> 66.9 | ... O58: =SUMIFS(Despesas!$C:$C,Despesas!$B:$B,$B58,Despesas!$E:$E,O$3) -> 0 | P58: =D58-E58 -> 9217.1
B59: 2025/8 | C59: agosto | D59: =SUMIF(Entradas!B:B,B59,Entradas!C:C) -> 8800 | E59: =SUM(F59:O59) -> 3865.9 | F59: =SUMIFS(Despesas!$C:$C,Despesas!$B:$B,$B59,Despesas!$E:$E,F$3) -> 0 | G59: =SUMIFS(Despesas!$C:$C,Despesas!$B:$B,$B59,Despesas!$E:$E,G$3) -> 0 | H59: =SUMIFS(Despesas!$C:$C,Despesas!$B:$B,$B59,Despesas!$E:$E,H$3) -> 0 | I59: =SUMIFS(Despesas!$C:$C,Despesas!$B:$B,$B59,Despesas!$E:$E,I$3) -> 299 | J59: =SUMIFS(Despesas!$C:$C,Despesas!$B:$B,$B59,Despesas!$E:$E,J$3) -> 0 | K59: =SUMIFS(Despesas!$C:$C,Despesas!$B:$B,$B59,Despesas!$E:$E,K$3) -> 3500 | L59: =SUMIFS(Despesas!$C:$C,Despesas!$B:$B,$B59,Despesas!$E:$E,L$3) -> 0 | M59: =SUMIFS(Despesas!$C:$C,Despesas!$B:$B,$B59,Despesas!$E:$E,M$3) -> 66.9 | ... O59: =SUMIFS(Despesas!$C:$C,Despesas!$B:$B,$B59,Despesas!$E:$E,O$3) -> 0 | P59: =D59-E59 -> 4934.1
B60: 2025/9 | C60: setembro | D60: =SUMIF(Entradas!B:B,B60,Entradas!C:C) -> 13735 | E60: =SUM(F60:O60) -> 3865.9 | F60: =SUMIFS(Despesas!$C:$C,Despesas!$B:$B,$B60,Despesas!$E:$E,F$3) -> 0 | G60: =SUMIFS(Despesas!$C:$C,Despesas!$B:$B,$B60,Despesas!$E:$E,G$3) -> 0 | H60: =SUMIFS(Despesas!$C:$C,Despesas!$B:$B,$B60,Despesas!$E:$E,H$3) -> 0 | I60: =SUMIFS(Despesas!$C:$C,Despesas!$B:$B,$B60,Despesas!$E:$E,I$3) -> 299 | J60: =SUMIFS(Despesas!$C:$C,Despesas!$B:$B,$B60,Despesas!$E:$E,J$3) -> 0 | K60: =SUMIFS(Despesas!$C:$C,Despesas!$B:$B,$B60,Despesas!$E:$E,K$3) -> 3500 | L60: =SUMIFS(Despesas!$C:$C,Despesas!$B:$B,$B60,Despesas!$E:$E,L$3) -> 0 | M60: =SUMIFS(Despesas!$C:$C,Despesas!$B:$B,$B60,Despesas!$E:$E,M$3) -> 66.9 | ... O60: =SUMIFS(Despesas!$C:$C,Despesas!$B:$B,$B60,Despesas!$E:$E,O$3) -> 0 | P60: =D60-E60 -> 9869.1
B61: 2025/10 | C61: outubro | D61: =SUMIF(Entradas!B:B,B61,Entradas!C:C) -> 20775 | E61: =SUM(F61:O61) -> 7464.4 | F61: =SUMIFS(Despesas!$C:$C,Despesas!$B:$B,$B61,Despesas!$E:$E,F$3) -> 80 | G61: =SUMIFS(Despesas!$C:$C,Despesas!$B:$B,$B61,Despesas!$E:$E,G$3) -> 0 | H61: =SUMIFS(Despesas!$C:$C,Despesas!$B:$B,$B61,Despesas!$E:$E,H$3) -> 0 | I61: =SUMIFS(Despesas!$C:$C,Despesas!$B:$B,$B61,Despesas!$E:$E,I$3) -> 507.84 | J61: =SUMIFS(Despesas!$C:$C,Despesas!$B:$B,$B61,Despesas!$E:$E,J$3) -> 511.4 | K61: =SUMIFS(Despesas!$C:$C,Despesas!$B:$B,$B61,Despesas!$E:$E,K$3) -> 4387.36 | L61: =SUMIFS(Despesas!$C:$C,Despesas!$B:$B,$B61,Despesas!$E:$E,L$3) -> 1000 | M61: =SUMIFS(Despesas!$C:$C,Despesas!$B:$B,$B61,Despesas!$E:$E,M$3) -> 977.8 | ... O61: =SUMIFS(Despesas!$C:$C,Despesas!$B:$B,$B61,Despesas!$E:$E,O$3) -> 0 | P61: =D61-E61 -> 13310.6
B62: 2025/11 | C62: novembro | D62: =SUMIF(Entradas!B:B,B62,Entradas!C:C) -> 18585 | E62: =SUM(F62:O62) -> 4084.83 | F62: =SUMIFS(Despesas!$C:$C,Despesas!$B:$B,$B62,Despesas!$E:$E,F$3) -> 0 | G62: =SUMIFS(Despesas!$C:$C,Despesas!$B:$B,$B62,Despesas!$E:$E,G$3) -> 0 | H62: =SUMIFS(Despesas!$C:$C,Despesas!$B:$B,$B62,Despesas!$E:$E,H$3) -> 0 | I62: =SUMIFS(Despesas!$C:$C,Despesas!$B:$B,$B62,Despesas!$E:$E,I$3) -> 299 | J62: =SUMIFS(Despesas!$C:$C,Despesas!$B:$B,$B62,Despesas!$E:$E,J$3) -> 0 | K62: =SUMIFS(Despesas!$C:$C,Despesas!$B:$B,$B62,Despesas!$E:$E,K$3) -> 3500 | L62: =SUMIFS(Despesas!$C:$C,Despesas!$B:$B,$B62,Despesas!$E:$E,L$3) -> 0 | M62: =SUMIFS(Despesas!$C:$C,Despesas!$B:$B,$B62,Despesas!$E:$E,M$3) -> 285.83 | ... O62: =SUMIFS(Despesas!$C:$C,Despesas!$B:$B,$B62,Despesas!$E:$E,O$3) -> 0 | P62: =D62-E62 -> 14500.17
B63: 2025/12 | C63: dezembro | D63: =SUMIF(Entradas!B:B,B63,Entradas!C:C) -> 12340 | E63: =SUM(F63:O63) -> 0 | F63: =SUMIFS(Despesas!$C:$C,Despesas!$B:$B,$B63,Despesas!$E:$E,F$3) -> 0 | G63: =SUMIFS(Despesas!$C:$C,Despesas!$B:$B,$B63,Despesas!$E:$E,G$3) -> 0 | H63: =SUMIFS(Despesas!$C:$C,Despesas!$B:$B,$B63,Despesas!$E:$E,H$3) -> 0 | I63: =SUMIFS(Despesas!$C:$C,Despesas!$B:$B,$B63,Despesas!$E:$E,I$3) -> 0 | J63: =SUMIFS(Despesas!$C:$C,Despesas!$B:$B,$B63,Despesas!$E:$E,J$3) -> 0 | K63: =SUMIFS(Despesas!$C:$C,Despesas!$B:$B,$B63,Despesas!$E:$E,K$3) -> 0 | L63: =SUMIFS(Despesas!$C:$C,Despesas!$B:$B,$B63,Despesas!$E:$E,L$3) -> 0 | M63: =SUMIFS(Despesas!$C:$C,Despesas!$B:$B,$B63,Despesas!$E:$E,M$3) -> 0 | ... O63: =SUMIFS(Despesas!$C:$C,Despesas!$B:$B,$B63,Despesas!$E:$E,O$3) -> 0 | P63: =D63-E63 -> 12340
C64: Fluxo | D64: =SUM(D52:D63) -> 191358.51 | E64: =SUM(E52:E63) -> 70800.29 | F64: =SUM(F52:F63) -> 504.71 | G64: =SUM(G52:G63) -> 768.55 | H64: =SUM(H52:H63) -> 0 | I64: =SUM(I52:I63) -> 3737.84 | J64: =SUM(J52:J63) -> 6404.52 | K64: =SUM(K52:K63) -> 45288.75 | ... P64: =SUM(P52:P63) -> 120558.22

Sheet Entradas
C1: =IF(SUM(C3:C995)=0,"",SUM(C3:C995)) -> 752394.88 | E1: =IF(SUM(E3:E995)=0,"",SUM(E3:E995)) -> 4250 | F1: =IF(SUM(F3:F995)=0,"",SUM(F3:F995)) -> 300 | G1: =IF(SUM(G3:G995)=0,"",SUM(G3:G995)) -> 900 | H1: =IF(SUM(H3:H995)=0,"",SUM(H3:H995)) -> 150 | I1: =IF(SUM(I3:I995)=0,"",SUM(I3:I995)) -> 150 | J1: =IF(SUM(J3:J995)=0,"",SUM(J3:J995)) -> 150 | K1: =IF(SUM(K3:K995)=0,"",SUM(K3:K995)) -> 150 | L1: =IF(SUM(L3:L995)=0,"",SUM(L3:L995)) -> 150 | ... EC1: =IF(SUM(EC3:EC995)=0,"",SUM(EC3:EC995)) -> 1500 | EE1: =IF(SUM(EE3:EE995)=0,"",SUM(EE3:EE995)) -> 46429
C2: Recebido No Dia | D2: Data | E2: Flávio | F2: João | G2: Mariane | H2: Mariana Menezes | I2: Isaac | J2: Thyara (Wallyson) | K2: Daniel Berg | L2: Paulo Luz | M2: Gustavo | N2: Thales | O2: Andre Junio | P2: Matheus Av Neuro | Q2: Polliani | R2: Vctor Morato | S2: Estelita | T2: Maria Aparecida | U2: Pedro Av neuro | V2: Davi Lucas | W2: Thaís Couto | X2: José W. Av Neuro | Y2: Carlos Augusto | Z2: Italo vactomia | AA2: Aredson | AB2: Beatriz Av neuro | AC2: Diogo Alberto AV. Neuro | AD2: Bruno | AE2: Jefferson | AF2: Caio | AG2: Ivone | AH2: Juscelia | AI2: Luana Godinho | AJ2: Elisa | AK2: Yuri | AL2: Luiz Felipe Av neuro | AM2: Tatiane | AN2: Aurélio | AO2: Arthur Av. Neuro | AP2: Ana Paula | AQ2: Stela | AR2: Ayke | AS2: Vitória | AT2: Neivander | AU2: Jaqueline | AV2: Mateus Av neuro | AW2: Vinicius Garcês | AX2: Alerte | AY2: Fabiano | AZ2: FACULDADE | BA2: Jhessica | BB2: Eurico | BC2: Suyara Av neuro | BD2: Terezinha Maria | BE2: Nayara de Souza | BF2: Ana Carolina Caio | BG2: Paula Amorim | BH2: Anna Flávia | BI2: Thais av | BJ2: Jordana | BK2: Flaviany | BL2: Jarbas | BM2: Arthur Apolo Av. neuro | BN2: Joseane | BO2: Marcelo Cardoso | BP2: Paulo H. Pinheiro | BQ2: Luisa Leal Gomes | BR2: Miriane | BS2: Amanda | BT2: Larissa Silva | BU2: Paulo Pinho | BV2: Estefânia | BW2: Rosimere | BX2: João Guilherme | BY2: Renata Dias | BZ2: Júlia Olegario | CA2: João Luiz | CB2: Leandro | CC2: Constância | CD2: Lucimeire | CE2: Ricardo | CF2: Renata Ribeiro | CG2: Cleide | CH2: Renata Gonçalves | CI2: Alexandra | CJ2: Élida | CK2: Valcy | CL2: Júlia | CM2: Luanna (mãe de Marianna) | CN2: Gabriel | CO2: Alinne | CP2: Alexandre | CQ2: Nátalia | CR2: Wesley | CS2: Marianna | CT2: Ludmilla | CU2: Luana | CV2: Allyson | CW2: Gercina | CX2: Caio Dornelas Av neuro | CY2: Silvana | CZ2: Luiza | DA2: Lenira Av neuro | DB2: Núbia | DC2: Renata Av neuro | DD2: Cleidlene | DE2: Witian | DF2: Nathalia | DG2: Vitória Av neuro | DH2: Mayara | DI2: Ávila (mae Rosana) | DJ2: Ana Laura (Pacoquinha) | DK2: Nilda | DL2: Tatiana | DM2: Heitor (pai Alessandro) | DN2: Gilbrair | DO2: Ariadna | DP2: Ana karolina Lucimeire | DQ2: Vanessa | DR2: Isabel | DS2: Mathilde | DT2: Yara Kelly | DU2: Victor Queiroz | DV2: Miguel | DW2: Hannanh | DX2: Maria Laura Av Neuro | DY2: Geovanna | DZ2: Juliana | EA2: Klaus | EB2: Murillo | EC2: Marcus | EE2: Sublocação
B3: =IF(D3>0, CONCATENATE(YEAR(D3),"/",MONTH(D3)),"") -> 2022/1 | C3: =IF(SUM(E3:EG3)=0,"",SUM(E3:EG3)) -> 50 | D3: 44585 | F3: 50
B4: =IF(D4>0, CONCATENATE(YEAR(D4),"/",MONTH(D4)),"") -> 2022/2 | C4: =IF(SUM(E4:EG4)=0,"",SUM(E4:EG4)) -> 150 | D4: 44599 | G4: 150
B5: =IF(D5>0, CONCATENATE(YEAR(D5),"/",MONTH(D5)),"") -> 2022/2 | C5: =IF(SUM(E5:EG5)=0,"",SUM(E5:EG5)) -> 200 | D5: 44620 | F5: 50 | G5: 150
B6: =IF(D6>0, CONCATENATE(YEAR(D6),"/",MONTH(D6)),"") -> 2022/3 | C6: =IF(SUM(E6:EG6)=0,"",SUM(E6:EG6)) -> 150 | D6: 44628 | N6: 150
B7: =IF(D7>0, CONCATENATE(YEAR(D7),"/",MONTH(D7)),"") -> 2022/3 | C7: =IF(SUM(E7:EG7)=0,"",SUM(E7:EG7)) -> 150 | D7: 44630 | N7: 150
B8: =IF(D8>0, CONCATENATE(YEAR(D8),"/",MONTH(D8)),"") -> 2022/3 | C8: =IF(SUM(E8:EG8)=0,"",SUM(E8:EG8)) -> 150 | D8: 44631 | CZ8: 150
B9: =IF(D9>0, CONCATENATE(YEAR(D9),"/",MONTH(D9)),"") -> 2022/3 | C9: =IF(SUM(E9:EG9)=0,"",SUM(E9:EG9)) -> 350 | D9: 44634 | F9: 50 | AJ9: 300
B10: =IF(D10>0, CONCATENATE(YEAR(D10),"/",MONTH(D10)),"") -> 2022/3 | C10: =IF(SUM(E10:EG10)=0,"",SUM(E10:EG10)) -> 150 | D10: 44637 | CZ10: 150
B11: =IF(D11>0, CONCATENATE(YEAR(D11),"/",MONTH(D11)),"") -> 2022/3 | C11: =IF(SUM(E11:EG11)=0,"",SUM(E11:EG11)) -> 450 | D11: 44644 | N11: 300 | CZ11: 150
B12: =IF(D12>0, CONCATENATE(YEAR(D12),"/",MONTH(D12)),"") -> 2022/3 | C12: =IF(SUM(E12:EG12)=0,"",SUM(E12:EG12)) -> 195 | D12: 44649 | N12: 195
B13: =IF(D13>0, CONCATENATE(YEAR(D13),"/",MONTH(D13)),"") -> 2022/3 | C13: =IF(SUM(E13:EG13)=0,"",SUM(E13:EG13)) -> 150 | D13: 44651 | AQ13: 150
B14: =IF(D14>0, CONCATENATE(YEAR(D14),"/",MONTH(D14)),"") -> 2022/4 | C14: =IF(SUM(E14:EG14)=0,"",SUM(E14:EG14)) -> 150 | D14: 44655 | H14: 150
B15: =IF(D15>0, CONCATENATE(YEAR(D15),"/",MONTH(D15)),"") -> 2022/4 | C15: =IF(SUM(E15:EG15)=0,"",SUM(E15:EG15)) -> 450 | D15: 44658 | AQ15: 300 | CZ15: 150
B16: =IF(D16>0, CONCATENATE(YEAR(D16),"/",MONTH(D16)),"") -> 2022/4 | C16: =IF(SUM(E16:EG16)=0,"",SUM(E16:EG16)) -> 450 | D16: 44662 | N16: 150 | AF16: 300
B17: =IF(D17>0, CONCATENATE(YEAR(D17),"/",MONTH(D17)),"") -> 2022/4 | C17: =IF(SUM(E17:EG17)=0,"",SUM(E17:EG17)) -> 150 | D17: 44664 | AQ17: 150
B18: =IF(D18>0, CONCATENATE(YEAR(D18),"/",MONTH(D18)),"") -> 2022/4 | C18: =IF(SUM(E18:EG18)=0,"",SUM(E18:EG18)) -> 150 | D18: 44665 | CZ18: 150
B19: =IF(D19>0, CONCATENATE(YEAR(D19),"/",MONTH(D19)),"") -> 2022/4 | C19: =IF(SUM(E19:EG19)=0,"",SUM(E19:EG19)) -> 200 | D19: 44669 | F19: 50 | G19: 150
B20: =IF(D20>0, CONCATENATE(YEAR(D20),"/",MONTH(D20)),"") -> 2022/4 | C20: =IF(SUM(E20:EG20)=0,"",SUM(E20:EG20)) -> 600 | D20: 44670 | N20: 300 | AJ20: 300
B21: =IF(D21>0, CONCATENATE(YEAR(D21),"/",MONTH(D21)),"") -> 2022/4 | C21: =IF(SUM(E21:EG21)=0,"",SUM(E21:EG21)) | D21: 44676
B22: =IF(D22>0, CONCATENATE(YEAR(D22),"/",MONTH(D22)),"") -> 2022/4 | C22: =IF(SUM(E22:EG22)=0,"",SUM(E22:EG22)) -> 150 | D22: 44677 | CZ22: 150
B23: =IF(D23>0, CONCATENATE(YEAR(D23),"/",MONTH(D23)),"") -> 2022/4 | C23: =IF(SUM(E23:EG23)=0,"",SUM(E23:EG23)) -> 150 | D23: 44679 | G23: Não 150 | AQ23: 150
B24: =IF(D24>0, CONCATENATE(YEAR(D24),"/",MONTH(D24)),"") -> 2022/5 | C24: =IF(SUM(E24:EG24)=0,"",SUM(E24:EG24)) -> 200 | D24: 44683 | F24: 50 | G24: 150
B25: =IF(D25>0, CONCATENATE(YEAR(D25),"/",MONTH(D25)),"") -> 2022/5 | C25: =IF(SUM(E25:EG25)=0,"",SUM(E25:EG25)) -> 750 | D25: 44686 | N25: 300 | AF25: 450
B26: =IF(D26>0, CONCATENATE(YEAR(D26),"/",MONTH(D26)),"") -> 2022/5 | C26: =IF(SUM(E26:EG26)=0,"",SUM(E26:EG26)) | D26: 44687
B27: =IF(D27>0, CONCATENATE(YEAR(D27),"/",MONTH(D27)),"") -> 2022/5 | C27: =IF(SUM(E27:EG27)=0,"",SUM(E27:EG27)) -> 300 | D27: 44690 | AQ27: 150 | CZ27: 150
B28: =IF(D28>0, CONCATENATE(YEAR(D28),"/",MONTH(D28)),"") -> 2022/5 | C28: =IF(SUM(E28:EG28)=0,"",SUM(E28:EG28)) -> 300 | D28: 44693 | AJ28: 300
B29: =IF(D29>0, CONCATENATE(YEAR(D29),"/",MONTH(D29)),"") -> 2022/5 | C29: =IF(SUM(E29:EG29)=0,"",SUM(E29:EG29)) -> 150 | D29: 44694 | AQ29: 150
B30: =IF(D30>0, CONCATENATE(YEAR(D30),"/",MONTH(D30)),"") -> 2022/5 | C30: =IF(SUM(E30:EG30)=0,"",SUM(E30:EG30)) -> 150 | D30: 44697 | CF30: 150
B31: =IF(D31>0, CONCATENATE(YEAR(D31),"/",MONTH(D31)),"") -> 2022/5 | C31: =IF(SUM(E31:EG31)=0,"",SUM(E31:EG31)) | D31: 44700
B32: =IF(D32>0, CONCATENATE(YEAR(D32),"/",MONTH(D32)),"") -> 2022/5 | C32: =IF(SUM(E32:EG32)=0,"",SUM(E32:EG32)) -> 750 | D32: 44707 | I32: 150 | AN32: 150 | CF32: 450
B33: =IF(D33>0, CONCATENATE(YEAR(D33),"/",MONTH(D33)),"") -> 2022/5 | C33: =IF(SUM(E33:EG33)=0,"",SUM(E33:EG33)) -> 300 | D33: 44708 | N33: 150 | AQ33: 150
B34: =IF(D34>0, CONCATENATE(YEAR(D34),"/",MONTH(D34)),"") -> 2022/5 | C34: =IF(SUM(E34:EG34)=0,"",SUM(E34:EG34)) -> 150 | D34: 44711 | J34: 150
B35: =IF(D35>0, CONCATENATE(YEAR(D35),"/",MONTH(D35)),"") -> 2022/5 | C35: =IF(SUM(E35:EG35)=0,"",SUM(E35:EG35)) -> 300 | D35: 44712 | AN35: 150 | CZ35: 150
B36: =IF(D36>0, CONCATENATE(YEAR(D36),"/",MONTH(D36)),"") -> 2022/6 | C36: =IF(SUM(E36:EG36)=0,"",SUM(E36:EG36)) -> 150 | D36: 44713 | K36: 150
B37: =IF(D37>0, CONCATENATE(YEAR(D37),"/",MONTH(D37)),"") -> 2022/6 | C37: =IF(SUM(E37:EG37)=0,"",SUM(E37:EG37)) | D37: 44715
B38: =IF(D38>0, CONCATENATE(YEAR(D38),"/",MONTH(D38)),"") -> 2022/6 | C38: =IF(SUM(E38:EG38)=0,"",SUM(E38:EG38)) -> 150 | D38: 44718 | L38: 150
B39: =IF(D39>0, CONCATENATE(YEAR(D39),"/",MONTH(D39)),"") -> 2022/6 | C39: =IF(SUM(E39:EG39)=0,"",SUM(E39:EG39)) -> 600 | D39: 44719 | AF39: 600
B40: =IF(D40>0, CONCATENATE(YEAR(D40),"/",MONTH(D40)),"") -> 2022/6 | C40: =IF(SUM(E40:EG40)=0,"",SUM(E40:EG40)) -> 600 | D40: 44721 | CF40: 600
B41: =IF(D41>0, CONCATENATE(YEAR(D41),"/",MONTH(D41)),"") -> 2022/6 | C41: =IF(SUM(E41:EG41)=0,"",SUM(E41:EG41)) -> 450 | D41: 44722 | N41: 150 | AN41: 150 | AQ41: 150
B42: =IF(D42>0, CONCATENATE(YEAR(D42),"/",MONTH(D42)),"") -> 2022/6 | C42: =IF(SUM(E42:EG42)=0,"",SUM(E42:EG42)) -> 350 | D42: 44725 | F42: 50 | G42: 150 | CZ42: 150
B43: =IF(D43>0, CONCATENATE(YEAR(D43),"/",MONTH(D43)),"") -> 2022/6 | C43: =IF(SUM(E43:EG43)=0,"",SUM(E43:EG43)) -> 300 | D43: 44726 | AJ43: 300
B44: =IF(D44>0, CONCATENATE(YEAR(D44),"/",MONTH(D44)),"") -> 2022/6 | C44: =IF(SUM(E44:EG44)=0,"",SUM(E44:EG44)) -> 150 | D44: 44729 | AN44: 150
B45: =IF(D45>0, CONCATENATE(YEAR(D45),"/",MONTH(D45)),"") -> 2022/6 | C45: =IF(SUM(E45:EG45)=0,"",SUM(E45:EG45)) -> 150 | D45: 44732 | AQ45: 150
B46: =IF(D46>0, CONCATENATE(YEAR(D46),"/",MONTH(D46)),"") -> 2022/6 | C46: =IF(SUM(E46:EG46)=0,"",SUM(E46:EG46)) -> 150 | D46: 44734 | O46: 150
B47: =IF(D47>0, CONCATENATE(YEAR(D47),"/",MONTH(D47)),"") -> 2022/6 | C47: =IF(SUM(E47:EG47)=0,"",SUM(E47:EG47)) -> 750 | D47: 44735 | AN47: 150 | AQ47: 150 | CF47: 450
B48: =IF(D48>0, CONCATENATE(YEAR(D48),"/",MONTH(D48)),"") -> 2022/6 | C48: =IF(SUM(E48:EG48)=0,"",SUM(E48:EG48)) -> 150 | D48: 44739 | O48: 150
B49: =IF(D49>0, CONCATENATE(YEAR(D49),"/",MONTH(D49)),"") -> 2022/6 | C49: =IF(SUM(E49:EG49)=0,"",SUM(E49:EG49)) -> 300 | D49: 44742 | AN49: 150 | AQ49: 150
B50: =IF(D50>0, CONCATENATE(YEAR(D50),"/",MONTH(D50)),"") -> 2022/7 | C50: =IF(SUM(E50:EG50)=0,"",SUM(E50:EG50)) -> 150 | D50: 44748 | O50: 150
B51: =IF(D51>0, CONCATENATE(YEAR(D51),"/",MONTH(D51)),"") -> 2022/7 | C51: =IF(SUM(E51:EG51)=0,"",SUM(E51:EG51)) -> 900 | D51: 44749 | AF51: 600 | AN51: 150 | AQ51: 150
B52: =IF(D52>0, CONCATENATE(YEAR(D52),"/",MONTH(D52)),"") -> 2022/7 | C52: =IF(SUM(E52:EG52)=0,"",SUM(E52:EG52)) -> 600 | D52: 44750 | CF52: 600
B53: =IF(D53>0, CONCATENATE(YEAR(D53),"/",MONTH(D53)),"") -> 2022/7 | C53: =IF(SUM(E53:EG53)=0,"",SUM(E53:EG53)) -> 150 | D53: 44753 | CZ53: 150
B54: =IF(D54>0, CONCATENATE(YEAR(D54),"/",MONTH(D54)),"") -> 2022/7 | C54: =IF(SUM(E54:EG54)=0,"",SUM(E54:EG54)) -> 300 | D54: 44755 | O54: 150 | AN54: 150
B55: =IF(D55>0, CONCATENATE(YEAR(D55),"/",MONTH(D55)),"") -> 2022/7 | C55: =IF(SUM(E55:EG55)=0,"",SUM(E55:EG55)) | D55: 44756
B56: =IF(D56>0, CONCATENATE(YEAR(D56),"/",MONTH(D56)),"") -> 2022/7 | C56: =IF(SUM(E56:EG56)=0,"",SUM(E56:EG56)) -> 1000 | D56: 44757 | AJ56: 300 | DN56: 700
B57: =IF(D57>0, CONCATENATE(YEAR(D57),"/",MONTH(D57)),"") -> 2022/7 | C57: =IF(SUM(E57:EG57)=0,"",SUM(E57:EG57)) -> 200 | D57: 44763 | X57: 200
B58: =IF(D58>0, CONCATENATE(YEAR(D58),"/",MONTH(D58)),"") -> 2022/7 | C58: =IF(SUM(E58:EG58)=0,"",SUM(E58:EG58)) -> 750 | D58: 44764 | O58: 150 | CF58: 600
B59: =IF(D59>0, CONCATENATE(YEAR(D59),"/",MONTH(D59)),"") -> 2022/7 | C59: =IF(SUM(E59:EG59)=0,"",SUM(E59:EG59)) -> 450 | D59: 44767 | G59: 150 | AN59: 150 | CZ59: 150 | DN59: 2°
B60: =IF(D60>0, CONCATENATE(YEAR(D60),"/",MONTH(D60)),"") -> 2022/7 | C60: =IF(SUM(E60:EG60)=0,"",SUM(E60:EG60)) | D60: 44768
B61: =IF(D61>0, CONCATENATE(YEAR(D61),"/",MONTH(D61)),"") -> 2022/7 | C61: =IF(SUM(E61:EG61)=0,"",SUM(E61:EG61)) -> 150 | D61: 44769 | O61: 150
B62: =IF(D62>0, CONCATENATE(YEAR(D62),"/",MONTH(D62)),"") -> 2022/8 | C62: =IF(SUM(E62:EG62)=0,"",SUM(E62:EG62)) -> 2050 | D62: 44778 | AF62: 3° | AO62: 1600 | CF62: 450 | DN62: 3°
B63: =IF(D63>0, CONCATENATE(YEAR(D63),"/",MONTH(D63)),"") -> 2022/8 | C63: =IF(SUM(E63:EG63)=0,"",SUM(E63:EG63)) -> 150 | D63: 44781 | CZ63: 150
B64: =IF(D64>0, CONCATENATE(YEAR(D64),"/",MONTH(D64)),"") -> 2022/8 | C64: =IF(SUM(E64:EG64)=0,"",SUM(E64:EG64)) | D64: 44782 | AF64: 4°
B65: =IF(D65>0, CONCATENATE(YEAR(D65),"/",MONTH(D65)),"") -> 2022/8 | C65: =IF(SUM(E65:EG65)=0,"",SUM(E65:EG65)) -> 300 | D65: 44783 | AF65: 1° | AN65: 150 | AQ65: 150 | DN65: 4°
B66: =IF(D66>0, CONCATENATE(YEAR(D66),"/",MONTH(D66)),"") -> 2022/8 | C66: =IF(SUM(E66:EG66)=0,"",SUM(E66:EG66)) | D66: 44784
B67: =IF(D67>0, CONCATENATE(YEAR(D67),"/",MONTH(D67)),"") -> 2022/8 | C67: =IF(SUM(E67:EG67)=0,"",SUM(E67:EG67)) -> 150 | D67: 44785 | O67: 150
B68: =IF(D68>0, CONCATENATE(YEAR(D68),"/",MONTH(D68)),"") -> 2022/8 | C68: =IF(SUM(E68:EG68)=0,"",SUM(E68:EG68)) -> 700 | D68: 44788 | BL68: 700
B69: =IF(D69>0, CONCATENATE(YEAR(D69),"/",MONTH(D69)),"") -> 2022/8 | C69: =IF(SUM(E69:EG69)=0,"",SUM(E69:EG69)) -> 800 | D69: 44789 | N69: 200 | AF69: 600
B70: =IF(D70>0, CONCATENATE(YEAR(D70),"/",MONTH(D70)),"") -> 2022/8 | C70: =IF(SUM(E70:EG70)=0,"",SUM(E70:EG70)) -> 1900 | D70: 44790 | N70: 200 | AD70: 200 | AE70: 200 | AF70: 2° | AJ70: 300 | AN70: 150 | AQ70: 150 | DN70: 700
B71: =IF(D71>0, CONCATENATE(YEAR(D71),"/",MONTH(D71)),"") -> 2022/8 | C71: =IF(SUM(E71:EG71)=0,"",SUM(E71:EG71)) -> 800 | D71: 44791 | M71: 200 | CF71: 600
B72: =IF(D72>0, CONCATENATE(YEAR(D72),"/",MONTH(D72)),"") -> 2022/8 | C72: =IF(SUM(E72:EG72)=0,"",SUM(E72:EG72)) | D72: 44796
B73: =IF(D73>0, CONCATENATE(YEAR(D73),"/",MONTH(D73)),"") -> 2022/8 | C73: =IF(SUM(E73:EG73)=0,"",SUM(E73:EG73)) | D73: 44797 | BL73: 1° | DN73: 2°
B74: =IF(D74>0, CONCATENATE(YEAR(D74),"/",MONTH(D74)),"") -> 2022/8 | C74: =IF(SUM(E74:EG74)=0,"",SUM(E74:EG74)) -> 200 | D74: 44798 | AF74: 3° | AG74: 200
B75: =IF(D75>0, CONCATENATE(YEAR(D75),"/",MONTH(D75)),"") -> 2022/8 | C75: =IF(SUM(E75:EG75)=0,"",SUM(E75:EG75)) -> 300 | D75: 44799 | AD75: 1° | AE75: 1° | AN75: 150 | AQ75: 150
B76: =IF(D76>0, CONCATENATE(YEAR(D76),"/",MONTH(D76)),"") -> 2022/8 | C76: =IF(SUM(E76:EG76)=0,"",SUM(E76:EG76)) -> 1500 | D76: 44803 | N76: 1° | AD76: 750 | AE76: 750 | AF76: 4° | BL76: 2°
B77: =IF(D77>0, CONCATENATE(YEAR(D77),"/",MONTH(D77)),"") -> 2022/8 | C77: =IF(SUM(E77:EG77)=0,"",SUM(E77:EG77)) -> 850 | D77: 44804 | N77: 700 | AD77: 2° | AE77: 2° | CZ77: 150 | DN77: 3°
B78: =IF(D78>0, CONCATENATE(YEAR(D78),"/",MONTH(D78)),"") -> 2022/9 | C78: =IF(SUM(E78:EG78)=0,"",SUM(E78:EG78)) -> 800 | D78: 44805 | AG78: 200 | AN78: 150 | CF78: 450
B79: =IF(D79>0, CONCATENATE(YEAR(D79),"/",MONTH(D79)),"") -> 2022/9 | C79: =IF(SUM(E79:EG79)=0,"",SUM(E79:EG79)) -> 350 | D79: 44810 | AQ79: 150 | BL79: 3° | DM79: 200 | DN79: 4°
B80: =IF(D80>0, CONCATENATE(YEAR(D80),"/",MONTH(D80)),"") -> 2022/9 | C80: =IF(SUM(E80:EG80)=0,"",SUM(E80:EG80)) | D80: 44811
B81: =IF(D81>0, CONCATENATE(YEAR(D81),"/",MONTH(D81)),"") -> 2022/9 | C81: =IF(SUM(E81:EG81)=0,"",SUM(E81:EG81)) -> 400 | D81: 44812 | P81: 200 | AG81: 200
B82: =IF(D82>0, CONCATENATE(YEAR(D82),"/",MONTH(D82)),"") -> 2022/9 | C82: =IF(SUM(E82:EG82)=0,"",SUM(E82:EG82)) -> 200 | D82: 44813 | N82: 2° | AD82: 3° | AE82: 3° | DM82: 200
B83: =IF(D83>0, CONCATENATE(YEAR(D83),"/",MONTH(D83)),"") -> 2022/9 | C83: =IF(SUM(E83:EG83)=0,"",SUM(E83:EG83)) -> 350 | D83: 44817 | AF83: 1° | AQ83: 150 | BL83: 4° | DN83: 200
B84: =IF(D84>0, CONCATENATE(YEAR(D84),"/",MONTH(D84)),"") -> 2022/9 | C84: =IF(SUM(E84:EG84)=0,"",SUM(E84:EG84)) -> 500 | D84: 44818 | CF84: 350 | CZ84: 150 | DN84: 1°
B85: =IF(D85>0, CONCATENATE(YEAR(D85),"/",MONTH(D85)),"") -> 2022/9 | C85: =IF(SUM(E85:EG85)=0,"",SUM(E85:EG85)) -> 200 | D85: 44819 | N85: 3° | AG85: 200
B86: =IF(D86>0, CONCATENATE(YEAR(D86),"/",MONTH(D86)),"") -> 2022/9 | C86: =IF(SUM(E86:EG86)=0,"",SUM(E86:EG86)) -> 200 | D86: 44820 | AD86: 4° | AE86: 4° | DM86: 200
B87: =IF(D87>0, CONCATENATE(YEAR(D87),"/",MONTH(D87)),"") -> 2022/9 | C87: =IF(SUM(E87:EG87)=0,"",SUM(E87:EG87)) -> 1300 | D87: 44823 | P87: 1300
B88: =IF(D88>0, CONCATENATE(YEAR(D88),"/",MONTH(D88)),"") -> 2022/9 | C88: =IF(SUM(E88:EG88)=0,"",SUM(E88:EG88)) | D88: 44824 | AF88: 2° | BL88: 1°
B89: =IF(D89>0, CONCATENATE(YEAR(D89),"/",MONTH(D89)),"") -> 2022/9 | C89: =IF(SUM(E89:EG89)=0,"",SUM(E89:EG89)) -> 1700 | D89: 44825 | AE89: 1° | AF89: 600 | AJ89: 300 | BL89: 800
B90: =IF(D90>0, CONCATENATE(YEAR(D90),"/",MONTH(D90)),"") -> 2022/9 | C90: =IF(SUM(E90:EG90)=0,"",SUM(E90:EG90)) -> 650 | D90: 44826 | N90: 4° | AD90: 1° | AN90: 150 | DN90: 500
B91: =IF(D91>0, CONCATENATE(YEAR(D91),"/",MONTH(D91)),"") -> 2022/9 | C91: =IF(SUM(E91:EG91)=0,"",SUM(E91:EG91)) -> 200 | D91: 44827 | DM91: 200 | DN91: 2°
B92: =IF(D92>0, CONCATENATE(YEAR(D92),"/",MONTH(D92)),"") -> 2022/9 | C92: =IF(SUM(E92:EG92)=0,"",SUM(E92:EG92)) -> 200 | D92: 44831 | AC92: 200 | AF92: 3° | BL92: 2°
B93: =IF(D93>0, CONCATENATE(YEAR(D93),"/",MONTH(D93)),"") -> 2022/9 | C93: =IF(SUM(E93:EG93)=0,"",SUM(E93:EG93)) -> 500 | D93: 44833 | N93: 1° não | AD93: 2° | AE93: 2° | AG93: 200 | AQ93: 150 | CZ93: 150
B94: =IF(D94>0, CONCATENATE(YEAR(D94),"/",MONTH(D94)),"") -> 2022/9 | C94: =IF(SUM(E94:EG94)=0,"",SUM(E94:EG94)) -> 450 | D94: 44834 | CF94: 250 | DM94: 200 | DN94: 3°
B95: =IF(D95>0, CONCATENATE(YEAR(D95),"/",MONTH(D95)),"") -> 2022/10 | C95: =IF(SUM(E95:EG95)=0,"",SUM(E95:EG95)) -> 600 | D95: 44838 | AF95: 600 | BL95: 3°
B96: =IF(D96>0, CONCATENATE(YEAR(D96),"/",MONTH(D96)),"") -> 2022/10 | C96: =IF(SUM(E96:EG96)=0,"",SUM(E96:EG96)) -> 300 | D96: 44839 | AE96: 3° | AN96: 300 | DN96: 4°
B97: =IF(D97>0, CONCATENATE(YEAR(D97),"/",MONTH(D97)),"") -> 2022/10 | C97: =IF(SUM(E97:EG97)=0,"",SUM(E97:EG97)) -> 200 | D97: 44840 | N97: não | AD97: 3° | AG97: 200
B98: =IF(D98>0, CONCATENATE(YEAR(D98),"/",MONTH(D98)),"") -> 2022/10 | C98: =IF(SUM(E98:EG98)=0,"",SUM(E98:EG98)) -> 200 | D98: 44841 | DM98: 200
B99: =IF(D99>0, CONCATENATE(YEAR(D99),"/",MONTH(D99)),"") -> 2022/10 | C99: =IF(SUM(E99:EG99)=0,"",SUM(E99:EG99)) -> 4140 | D99: 44847 | N99: não | P99: 390 | AC99: 1750 | AD99: 4° | AE99: 1500 | AG99: 200 | AQ99: 150 | CZ99: 150
B100: =IF(D100>0, CONCATENATE(YEAR(D100),"/",MONTH(D100)),"") -> 2022/10 | C100: =IF(SUM(E100:EG100)=0,"",SUM(E100:EG100)) -> 2100 | D100: 44848 | AD100: 1500 | AE100: 4° | AF100: 4° | AJ100: 300 | BL100: 4° | CF100: 300
...

Sheet Despesas
B2: Invest. | C2: Valor | D2: Data | E2: Tipo | F2: Observação
B3: =IF(D3>0, CONCATENATE(YEAR(D3),"/",MONTH(D3)),"") -> 2022/1 | C3: 48.3 | D3: 44567 | E3: Marketing
B4: =IF(D4>0, CONCATENATE(YEAR(D4),"/",MONTH(D4)),"") -> 2022/1 | C4: 30 | D4: 44567 | E4: Materiais
B5: =IF(D5>0, CONCATENATE(YEAR(D5),"/",MONTH(D5)),"") -> 2022/1 | C5: 529.72 | D5: 44571 | E5: Educação
B6: =IF(D6>0, CONCATENATE(YEAR(D6),"/",MONTH(D6)),"") -> 2022/1 | C6: 11 | D6: 44578 | E6: Transporte
B7: =IF(D7>0, CONCATENATE(YEAR(D7),"/",MONTH(D7)),"") -> 2022/1 | C7: 6 | D7: 44578 | E7: Transporte
B8: =IF(D8>0, CONCATENATE(YEAR(D8),"/",MONTH(D8)),"") -> 2022/1 | C8: 86.3 | D8: 44581 | E8: Materiais
B9: =IF(D9>0, CONCATENATE(YEAR(D9),"/",MONTH(D9)),"") -> 2022/1 | C9: 30.11 | D9: 44582 | E9: Materiais
B10: =IF(D10>0, CONCATENATE(YEAR(D10),"/",MONTH(D10)),"") -> 2022/1 | C10: 50 | D10: 44582 | E10: Marketing
B11: =IF(D11>0, CONCATENATE(YEAR(D11),"/",MONTH(D11)),"") -> 2022/1 | C11: 50 | D11: 44585 | E11: Recebimentos | F11: João (valor mensal simbólico)
B12: =IF(D12>0, CONCATENATE(YEAR(D12),"/",MONTH(D12)),"") -> 2022/1 | C12: 33.73 | D12: 44585 | E12: Transporte
B13: =IF(D13>0, CONCATENATE(YEAR(D13),"/",MONTH(D13)),"") -> 2022/1 | C13: 666.16 | D13: 44585 | E13: Empresa/CRP
B14: =IF(D14>0, CONCATENATE(YEAR(D14),"/",MONTH(D14)),"") -> 2022/1 | C14: 33.1 | D14: 44592 | E14: Transporte
B15: =IF(D15>0, CONCATENATE(YEAR(D15),"/",MONTH(D15)),"") -> 2022/1 | C15: 400 | D15: 44592 | E15: Aluguel
B16: =IF(D16>0, CONCATENATE(YEAR(D16),"/",MONTH(D16)),"") -> 2022/2 | C16: 51.09 | D16: 44594 | E16: Materiais
B17: =IF(D17>0, CONCATENATE(YEAR(D17),"/",MONTH(D17)),"") -> 2022/2 | C17: 24.15 | D17: 44598 | E17: Marketing | F17: canva
B18: =IF(D18>0, CONCATENATE(YEAR(D18),"/",MONTH(D18)),"") -> 2022/2 | C18: 16 | D18: 44599 | E18: Transporte
B19: =IF(D19>0, CONCATENATE(YEAR(D19),"/",MONTH(D19)),"") -> 2022/2 | C19: 150 | D19: 44599 | E19: Recebimentos | F19: Mariane - 1° parcela de fevereiro da (total mensal de 300 - 50% desconto)
B20: =IF(D20>0, CONCATENATE(YEAR(D20),"/",MONTH(D20)),"") -> 2022/2 | C20: 529.72 | D20: 44602 | E20: Educação
B21: =IF(D21>0, CONCATENATE(YEAR(D21),"/",MONTH(D21)),"") -> 2022/2 | C21: 289 | D21: 44610 | E21: Marketing | F21: doctoralia
B22: =IF(D22>0, CONCATENATE(YEAR(D22),"/",MONTH(D22)),"") -> 2022/2 | C22: 20.96 | D22: 44616 | E22: Materiais
B23: =IF(D23>0, CONCATENATE(YEAR(D23),"/",MONTH(D23)),"") -> 2022/2 | C23: 20.96 | D23: 44616 | E23: Materiais
B24: =IF(D24>0, CONCATENATE(YEAR(D24),"/",MONTH(D24)),"") -> 2022/2 | C24: 6 | D24: 44620 | E24: Transporte
B25: =IF(D25>0, CONCATENATE(YEAR(D25),"/",MONTH(D25)),"") -> 2022/2 | C25: 400 | D25: 44620 | E25: Aluguel
B26: =IF(D26>0, CONCATENATE(YEAR(D26),"/",MONTH(D26)),"") -> 2022/2 | C26: 150 | D26: 44620 | E26: Recebimentos | F26: Mariane - 2° parcela de fevereiro (pag atrasado 08/03)
B27: =IF(D27>0, CONCATENATE(YEAR(D27),"/",MONTH(D27)),"") -> 2022/2 | C27: 50 | D27: 44620 | E27: Recebimentos | F27: João (valor mensal simbólico)
B28: =IF(D28>0, CONCATENATE(YEAR(D28),"/",MONTH(D28)),"") -> 2022/2 | C28: 200 | D28: 44620 | E28: Empresa/CRP | F28: contador
B29: =IF(D29>0, CONCATENATE(YEAR(D29),"/",MONTH(D29)),"") -> 2022/3 | C29: 49.07 | D29: 44623 | E29: Materiais
B30: =IF(D30>0, CONCATENATE(YEAR(D30),"/",MONTH(D30)),"") -> 2022/3 | C30: 240 | D30: 44624 | E30: Aluguel
B31: =IF(D31>0, CONCATENATE(YEAR(D31),"/",MONTH(D31)),"") -> 2022/3 | C31: 20 | D31: 44627 | E31: Transporte
B32: =IF(D32>0, CONCATENATE(YEAR(D32),"/",MONTH(D32)),"") -> 2022/3 | C32: 16 | D32: 44628 | E32: Transporte
B33: =IF(D33>0, CONCATENATE(YEAR(D33),"/",MONTH(D33)),"") -> 2022/3 | C33: 150 | D33: 44628 | E33: Recebimentos | F33: Thales - valor da sessão
B34: =IF(D34>0, CONCATENATE(YEAR(D34),"/",MONTH(D34)),"") -> 2022/3 | C34: 150 | D34: 44630 | E34: Recebimentos | F34: Thales - valor da sessão
B35: =IF(D35>0, CONCATENATE(YEAR(D35),"/",MONTH(D35)),"") -> 2022/3 | C35: 20 | D35: 44630 | E35: Transporte
B36: =IF(D36>0, CONCATENATE(YEAR(D36),"/",MONTH(D36)),"") -> 2022/3 | C36: 529.72 | D36: 44630 | E36: Educação
B37: =IF(D37>0, CONCATENATE(YEAR(D37),"/",MONTH(D37)),"") -> 2022/3 | C37: 200 | D37: 44630 | E37: Empresa/CRP
B38: =IF(D38>0, CONCATENATE(YEAR(D38),"/",MONTH(D38)),"") -> 2022/3 | C38: 150 | D38: 44631 | E38: Recebimentos | F38: Luiza - valor da sessão da mãe
B39: =IF(D39>0, CONCATENATE(YEAR(D39),"/",MONTH(D39)),"") -> 2022/3 | C39: 16 | D39: 44634 | E39: Transporte
B40: =IF(D40>0, CONCATENATE(YEAR(D40),"/",MONTH(D40)),"") -> 2022/3 | C40: 50 | D40: 44634 | E40: Recebimentos | F40: João (valor mensal simbólico)
B41: =IF(D41>0, CONCATENATE(YEAR(D41),"/",MONTH(D41)),"") -> 2022/3 | C41: 300 | D41: 44634 | E41: Recebimentos | F41: Elisa (valor mensal com 50% de desconto online, 17/02 a 14/03 - 4 sessões)
B42: =IF(D42>0, CONCATENATE(YEAR(D42),"/",MONTH(D42)),"") -> 2022/3 | C42: 63.9 | D42: 44635 | E42: Materiais
B43: =IF(D43>0, CONCATENATE(YEAR(D43),"/",MONTH(D43)),"") -> 2022/3 | C43: 16 | D43: 44637 | E43: Transporte
B44: =IF(D44>0, CONCATENATE(YEAR(D44),"/",MONTH(D44)),"") -> 2022/3 | C44: 150 | D44: 44637 | E44: Recebimentos | F44: Luiza - valor da sessão
B45: =IF(D45>0, CONCATENATE(YEAR(D45),"/",MONTH(D45)),"") -> 2022/3 | C45: 40.78 | D45: 44637 | E45: Escritório
B46: =IF(D46>0, CONCATENATE(YEAR(D46),"/",MONTH(D46)),"") -> 2022/3 | C46: 289 | D46: 44638 | E46: Marketing | F46: Doctoralia
B47: =IF(D47>0, CONCATENATE(YEAR(D47),"/",MONTH(D47)),"") -> 2022/3 | C47: 20 | D47: 44641 | E47: Transporte
B48: =IF(D48>0, CONCATENATE(YEAR(D48),"/",MONTH(D48)),"") -> 2022/3 | C48: 160 | D48: 44643 | E48: Aluguel
B49: =IF(D49>0, CONCATENATE(YEAR(D49),"/",MONTH(D49)),"") -> 2022/3 | C49: 60 | D49: 44643 | E49: Marketing
B50: =IF(D50>0, CONCATENATE(YEAR(D50),"/",MONTH(D50)),"") -> 2022/3 | C50: 20 | D50: 44644 | E50: Transporte
B51: =IF(D51>0, CONCATENATE(YEAR(D51),"/",MONTH(D51)),"") -> 2022/3 | C51: 150 | D51: 44644 | E51: Recebimentos | F51: Luiza - valor da sessão
B52: =IF(D52>0, CONCATENATE(YEAR(D52),"/",MONTH(D52)),"") -> 2022/3 | C52: 300 | D52: 44644 | E52: Recebimentos | F52: Thales - valor de 2 sessões (uma foi falta)
B53: =IF(D53>0, CONCATENATE(YEAR(D53),"/",MONTH(D53)),"") -> 2022/3 | C53: 115 | D53: 44645 | E53: Materiais | F53: livros infantins
B54: =IF(D54>0, CONCATENATE(YEAR(D54),"/",MONTH(D54)),"") -> 2022/3 | C54: 20 | D54: 44648 | E54: Transporte
B55: =IF(D55>0, CONCATENATE(YEAR(D55),"/",MONTH(D55)),"") -> 2022/3 | C55: 195 | D55: 44649 | E55: Recebimentos | F55: Thales - valor sessão + multa de falta
B56: =IF(D56>0, CONCATENATE(YEAR(D56),"/",MONTH(D56)),"") -> 2022/3 | C56: 17 | D56: 44649 | E56: Transporte
B57: =IF(D57>0, CONCATENATE(YEAR(D57),"/",MONTH(D57)),"") -> 2022/3 | C57: 26 | D57: 44651 | E57: Materiais | F57: testes
B58: =IF(D58>0, CONCATENATE(YEAR(D58),"/",MONTH(D58)),"") -> 2022/3 | C58: 150 | D58: 44651 | E58: Recebimentos | F58: Stella - primeira sessão
B59: =IF(D59>0, CONCATENATE(YEAR(D59),"/",MONTH(D59)),"") -> 2022/3 | C59: 14 | D59: 44651 | E59: Transporte
B60: =IF(D60>0, CONCATENATE(YEAR(D60),"/",MONTH(D60)),"") -> 2022/4 | C60: 27 | D60: 44655 | E60: Transporte
B61: =IF(D61>0, CONCATENATE(YEAR(D61),"/",MONTH(D61)),"") -> 2022/4 | C61: 150 | D61: 44655 | E61: Recebimentos | F61: Mariana Menezes - sessão única
B62: =IF(D62>0, CONCATENATE(YEAR(D62),"/",MONTH(D62)),"") -> 2022/4 | C62: 150 | D62: 44657 | E62: Supervisão | F62: referente a duas supervisão em dupla
B63: =IF(D63>0, CONCATENATE(YEAR(D63),"/",MONTH(D63)),"") -> 2022/4 | C63: 16 | D63: 44658 | E63: Transporte
B64: =IF(D64>0, CONCATENATE(YEAR(D64),"/",MONTH(D64)),"") -> 2022/4 | C64: 300 | D64: 44658 | E64: Recebimentos | F64: Stella - duas sessões da semana
B65: =IF(D65>0, CONCATENATE(YEAR(D65),"/",MONTH(D65)),"") -> 2022/4 | C65: 150 | D65: 44658 | E65: Recebimentos | F65: Luiza
B66: =IF(D66>0, CONCATENATE(YEAR(D66),"/",MONTH(D66)),"") -> 2022/4 | C66: 1300 | D66: 44658 | E66: Marketing | F66: site
B67: =IF(D67>0, CONCATENATE(YEAR(D67),"/",MONTH(D67)),"") -> 2022/4 | C67: 300 | D67: 44662 | E67: Recebimentos | F67: Caio - duas sessões
B68: =IF(D68>0, CONCATENATE(YEAR(D68),"/",MONTH(D68)),"") -> 2022/4 | C68: 26 | D68: 44662 | E68: Transporte
B69: =IF(D69>0, CONCATENATE(YEAR(D69),"/",MONTH(D69)),"") -> 2022/4 | C69: 150 | D69: 44662 | E69: Recebimentos | F69: Thales
B70: =IF(D70>0, CONCATENATE(YEAR(D70),"/",MONTH(D70)),"") -> 2022/4 | C70: 529.72 | D70: 44662 | E70: Educação
B71: =IF(D71>0, CONCATENATE(YEAR(D71),"/",MONTH(D71)),"") -> 2022/4 | C71: 578.5 | D71: 44663 | E71: Aluguel
B72: =IF(D72>0, CONCATENATE(YEAR(D72),"/",MONTH(D72)),"") -> 2022/4 | C72: 150 | D72: 44664 | E72: Recebimentos | F72: Stella
B73: =IF(D73>0, CONCATENATE(YEAR(D73),"/",MONTH(D73)),"") -> 2022/4 | C73: 150 | D73: 44665 | E73: Recebimentos | F73: Luiza
B74: =IF(D74>0, CONCATENATE(YEAR(D74),"/",MONTH(D74)),"") -> 2022/4 | C74: 50 | D74: 44669 | E74: Recebimentos | F74: João - valor simbólico do mês
B75: =IF(D75>0, CONCATENATE(YEAR(D75),"/",MONTH(D75)),"") -> 2022/4 | C75: 24 | D75: 44669 | E75: Transporte
B76: =IF(D76>0, CONCATENATE(YEAR(D76),"/",MONTH(D76)),"") -> 2022/4 | C76: 150 | D76: 44669 | E76: Recebimentos | F76: Mariana - valor de março
B77: =IF(D77>0, CONCATENATE(YEAR(D77),"/",MONTH(D77)),"") -> 2022/4 | C77: 289 | D77: 44669 | E77: Marketing | F77: doctoralia
B78: =IF(D78>0, CONCATENATE(YEAR(D78),"/",MONTH(D78)),"") -> 2022/4 | C78: 300 | D78: 44670 | E78: Recebimentos | F78: Thales - duas sessões
B79: =IF(D79>0, CONCATENATE(YEAR(D79),"/",MONTH(D79)),"") -> 2022/4 | C79: 300 | D79: 44670 | E79: Recebimentos | F79: Elisa - valor mês
B80: =IF(D80>0, CONCATENATE(YEAR(D80),"/",MONTH(D80)),"") -> 2022/4 | C80: 150 | D80: 44671 | E80: Supervisão | F80: uma sessão individual
B81: =IF(D81>0, CONCATENATE(YEAR(D81),"/",MONTH(D81)),"") -> 2022/4 | C81: 22 | D81: 44671 | E81: Materiais | F81: teste
B82: =IF(D82>0, CONCATENATE(YEAR(D82),"/",MONTH(D82)),"") -> 2022/4 | C82: 26 | D82: 44676 | E82: Transporte
B83: =IF(D83>0, CONCATENATE(YEAR(D83),"/",MONTH(D83)),"") -> 2022/4 | C83: 150 | D83: 44677 | E83: Recebimentos | F83: Luiza
B84: =IF(D84>0, CONCATENATE(YEAR(D84),"/",MONTH(D84)),"") -> 2022/4 | C84: 150 | D84: 44678 | E84: Supervisão
B85: =IF(D85>0, CONCATENATE(YEAR(D85),"/",MONTH(D85)),"") -> 2022/4 | C85: 100 | D85: 44679 | E85: Marketing | F85: edição vídeo
B86: =IF(D86>0, CONCATENATE(YEAR(D86),"/",MONTH(D86)),"") -> 2022/4 | C86: 200 | D86: 44681 | E86: Empresa/CRP
B87: =IF(D87>0, CONCATENATE(YEAR(D87),"/",MONTH(D87)),"") -> 2022/5 | C87: 20 | D87: 44683 | E87: Transporte
B88: =IF(D88>0, CONCATENATE(YEAR(D88),"/",MONTH(D88)),"") -> 2022/5 | C88: 40 | D88: 44684 | E88: Marketing | F88: domínio do site
B89: =IF(D89>0, CONCATENATE(YEAR(D89),"/",MONTH(D89)),"") -> 2022/5 | C89: 700 | D89: 44688 | E89: Marketing | F89: site
B90: =IF(D90>0, CONCATENATE(YEAR(D90),"/",MONTH(D90)),"") -> 2022/5 | C90: 23 | D90: 44690 | E90: Transporte
B91: =IF(D91>0, CONCATENATE(YEAR(D91),"/",MONTH(D91)),"") -> 2022/5 | C91: 44.99 | D91: 44690 | E91: Escritório | F91: telefone
B92: =IF(D92>0, CONCATENATE(YEAR(D92),"/",MONTH(D92)),"") -> 2022/5 | C92: 400 | D92: 44691 | E92: Aluguel
B93: =IF(D93>0, CONCATENATE(YEAR(D93),"/",MONTH(D93)),"") -> 2022/5 | C93: 529.72 | D93: 44691 | E93: Educação
B94: =IF(D94>0, CONCATENATE(YEAR(D94),"/",MONTH(D94)),"") -> 2022/5 | C94: 300 | D94: 44692 | E94: Supervisão
B95: =IF(D95>0, CONCATENATE(YEAR(D95),"/",MONTH(D95)),"") -> 2022/5 | C95: 65 | D95: 44692 | E95: Materiais | F95: testes nepneuro
B96: =IF(D96>0, CONCATENATE(YEAR(D96),"/",MONTH(D96)),"") -> 2022/5 | C96: 44.99 | D96: 44699 | E96: Escritório
B97: =IF(D97>0, CONCATENATE(YEAR(D97),"/",MONTH(D97)),"") -> 2022/5 | C97: 289 | D97: 44699 | E97: Marketing | F97: doctoralia
B98: =IF(D98>0, CONCATENATE(YEAR(D98),"/",MONTH(D98)),"") -> 2022/5 | C98: 48.3 | D98: 44699 | E98: Marketing | F98: dois meses de canva
B99: =IF(D99>0, CONCATENATE(YEAR(D99),"/",MONTH(D99)),"") -> 2022/5 | C99: 26 | D99: 44707 | E99: Transporte
B100: =IF(D100>0, CONCATENATE(YEAR(D100),"/",MONTH(D100)),"") -> 2022/5 | C100: 150 | D100: 44711 | E100: Marketing | F100: instragran
B101: =IF(D101>0, CONCATENATE(YEAR(D101),"/",MONTH(D101)),"") -> 2022/5 | C101: 200 | D101: 44711 | E101: Empresa/CRP | F101: contador
...

Sheet Informações
B2: Classe | C2: Paciente | D2: Tratamento | E2: Data de Nascimento | F2: Idade | G2: Iniciou | H2: Fim | I2: Tempo de Terapia | J2: Telefone | K2: Profissão | L2: Contato de Emergência | M2: Nome | N2: E-mail | O2: Endereço | P2: Bairro | Q2: Cidade | R2: CEP | S2: Nome do Pai | T2: Nome da Mãe | U2: finalizou | V2: CPF | W2: Origem | X2: Observações
A3: =IF(E3<>0, MONTH(E3),"") -> 9 | B3: =IF(F3="","", IF(F3<12,"Criança",IF(F3<18,"Adolescente",IF(F3<26,"Jovem",IF(F3<60,"Adulto", "Idoso"))))) -> Adolescente | C3: João Pedro Cardoso de Oliveira | D3: Terapia | E3: 40443 | F3: =IF(E3>0, DATEDIF(E3,TODAY(),"Y"),"") -> 15 | G3: 44592 | H3: =IF(U3>0,U3,TODAY()) -> 44755 | I3: =IF(G3>0, ROUNDDOWN((H3-G3)/365,0)& " Anos e "& ROUNDDOWN(((H3-G3)-ROUNDDOWN((H3-G3)/365,0)*365)/30,0)&" meses","") -> 0 Anos e 5 meses | J3: 62 991135413 | K3: estudante | L3: 63 991135413 | M3: tia vó Maria | N3: rosariooliveira270452@gmail.com | O3: Av. Cândido Portinari Qd. 57, Lt. 12 | P3: St. Gentil Meirelles | Q3: Goiânia | S3: Wander Telis Cardoso | T3: Cristina Melo de Oliveira | U3: 44755 | W3: estágio da puc/outro | X3: valor social do estágio da puc - deficiência intelectual e TDAH
A4: =IF(E4<>0, MONTH(E4),"") -> 7 | B4: Adolescente | C4: Ioshua de Santana Santos | D4: Terapia | E4: 38187 | F4: =IF(E4>0, DATEDIF(E4,TODAY(),"Y"),"") -> 21 | G4: 44592 | H4: =IF(U4>0,U4,TODAY()) -> 44755 | I4: =IF(G4>0, ROUNDDOWN((H4-G4)/365,0)& " Anos e "& ROUNDDOWN(((H4-G4)-ROUNDDOWN((H4-G4)/365,0)*365)/30,0)&" meses","") -> 0 Anos e 5 meses | J4: 62 981553961 | K4: estudante | L4: 63 981553961/ 6299314 0718 | M4: mãe/pai | N4: ioshua.santos@outlook.com | O4: Rua Bauru Quadra 25 Lote 02 | P4: Jd. Novo Mundo | Q4: Goiânia | R4: 74715-070 | S4: Paulo César Gonçalves Santos | T4: Maria Lucilene de Santana | U4: 44755 | W4: estágio da puc/outro | X4: valor social do estágio da puc
A5: =IF(E5<>0, MONTH(E5),"") -> 9 | B5: =IF(F5="","", IF(F5<12,"Criança",IF(F5<18,"Adolescente",IF(F5<26,"Jovem",IF(F5<60,"Adulto", "Idoso"))))) -> Adulto | C5: Mariane Rezende Magalhães | D5: Terapia | E5: 35675 | F5: =IF(E5>0, DATEDIF(E5,TODAY(),"Y"),"") -> 28 | G5: 44592 | H5: =IF(U5>0,U5,TODAY()) -> 44719 | I5: =IF(G5>0, ROUNDDOWN((H5-G5)/365,0)& " Anos e "& ROUNDDOWN(((H5-G5)-ROUNDDOWN((H5-G5)/365,0)*365)/30,0)&" meses","") -> 0 Anos e 4 meses | J5: 62 999361248 | K5: engenheiro civil | L5: 62 999652885 | M5: mãe Mária | N5: marianemaggs@gmail.com | O5: Rua das Paineiras, Qd. 67, Lt. 16, casa 2 | P5: Jardim Mariliza | Q5: Goiânia | R5: 74885-340 | S5: Arlindo Magalhães Filho | T5: Márcia Morais Rezende Magalhães | U5: 44719 | W5: Indicação amigo Marcelo | X5: valor social
A6: =IF(E6<>0, MONTH(E6),"") -> 6 | B6: =IF(F6="","", IF(F6<12,"Criança",IF(F6<18,"Adolescente",IF(F6<26,"Jovem",IF(F6<60,"Adulto", "Idoso"))))) -> Adulto | C6: Thales Rafael Gomes de Castro | D6: Terapia | E6: 34142 | F6: =IF(E6>0, DATEDIF(E6,TODAY(),"Y"),"") -> 32 | G6: 44628 | H6: =IF(U6>0,U6,TODAY()) -> 44855 | I6: =IF(G6>0, ROUNDDOWN((H6-G6)/365,0)& " Anos e "& ROUNDDOWN(((H6-G6)-ROUNDDOWN((H6-G6)/365,0)*365)/30,0)&" meses","") -> 0 Anos e 7 meses | J6: 62 998158180 | K6: engenheiro civil | L6: 62 996370517 | M6: pai José Henrique | N6: akiamacastro@gmail.com | O6: Rua S4, 20 - Ed. Resi. dos girrassóis, ap 700 | P6: St. Bela vista | Q6: Goiânia | S6: José Henrique | U6: 44855 | W6: doctoralia
A7: =IF(E7<>0, MONTH(E7),"") -> 11 | B7: =IF(F7="","", IF(F7<12,"Criança",IF(F7<18,"Adolescente",IF(F7<26,"Jovem",IF(F7<60,"Adulto", "Idoso"))))) -> Jovem | C7: Elisa Nunes de Castro Borges | D7: Terapia | E7: 37942 | F7: =IF(E7>0, DATEDIF(E7,TODAY(),"Y"),"") -> 22 | G7: 44609 | H7: =IF(U7>0,U7,TODAY()) -> 44994 | I7: =IF(G7>0, ROUNDDOWN((H7-G7)/365,0)& " Anos e "& ROUNDDOWN(((H7-G7)-ROUNDDOWN((H7-G7)/365,0)*365)/30,0)&" meses","") -> 1 Anos e 0 meses | J7: 64 996718220 | K7: estudante - computação | L7: 64 996956863 | M7: mãe Cristiane | N7: elisancb096@gmail.com | O7: Avenida: Contorno, Quadra: 36, Lote: 21 | P7: Santa Maria | Q7: Arizona/GO | R7: 75280-000 | S7: Leonardo Nunes de Castro | T7: Cristiane Aparecida Borges | U7: 44994 | W7: indicação amiga Livia | X7: valor social
A8: =IF(E8<>0, MONTH(E8),"") -> 4 | B8: =IF(F8="","", IF(F8<12,"Criança",IF(F8<18,"Adolescente",IF(F8<26,"Jovem",IF(F8<60,"Adulto", "Idoso"))))) -> Adulto | C8: Stella Leal Souza Furlanetto | D8: Terapia | E8: 32985 | F8: =IF(E8>0, DATEDIF(E8,TODAY(),"Y"),"") -> 35 | G8: 44651 | H8: =IF(U8>0,U8,TODAY()) -> 45028 | I8: =IF(G8>0, ROUNDDOWN((H8-G8)/365,0)& " Anos e "& ROUNDDOWN(((H8-G8)-ROUNDDOWN((H8-G8)/365,0)*365)/30,0)&" meses","") -> 1 Anos e 0 meses | J8: 62 991701318 | K8: controle de qualidade | L8: 62 984084481 | M8: Marido Henrique | N8: stellalealsouza@hotmail.com | O8: Av.T14, 535 - Ed. Borges Landeiro Athenas, ap 2802 | P8: Setor Bueno | Q8: Goiânia | R8: 74230-130 | S8: Benedito Felisbino de Souza | T8: Lucineide Leal Souza | U8: 45028 | W8: indicação Dayse
A9: =IF(E9<>0, MONTH(E9),"") | B9: Adulto | C9: Mariana Gonçalves de Menezes | D9: Seção Avulsa | F9: =IF(E9>0, DATEDIF(E9,TODAY(),"Y"),"") | G9: 44655 | H9: =IF(U9>0,U9,TODAY()) -> 44655 | I9: =IF(G9>0, ROUNDDOWN((H9-G9)/365,0)& " Anos e "& ROUNDDOWN(((H9-G9)-ROUNDDOWN((H9-G9)/365,0)*365)/30,0)&" meses","") -> 0 Anos e 0 meses | J9: 62 993003429 | K9: personal | L9: 62 993003566 | M9: esposa Isadora | N9: izadora.zootec@gmail.com | Q9: Goiânia | U9: 44655 | W9: doctoralia
A10: =IF(E10<>0, MONTH(E10),"") -> 9 | B10: =IF(F10="","", IF(F10<12,"Criança",IF(F10<18,"Adolescente",IF(F10<26,"Jovem",IF(F10<60,"Adulto", "Idoso"))))) -> Adulto | C10: Caio Andrade de Souza | D10: Terapia | E10: 33877 | F10: =IF(E10>0, DATEDIF(E10,TODAY(),"Y"),"") -> 33 | G10: 44658 | H10: =IF(U10>0,U10,TODAY()) -> 44972 | I10: =IF(G10>0, ROUNDDOWN((H10-G10)/365,0)& " Anos e "& ROUNDDOWN(((H10-G10)-ROUNDDOWN((H10-G10)/365,0)*365)/30,0)&" meses","") -> 0 Anos e 10 meses | J10: 62 981389186 | K10: engenheiro civil | L10: 62 983007799 | M10: irmão Lucas | N10: caio.souzaeng@outlook.com | O10: Rua T37, 2300 - Ed. DNA Smart Style Bloco G, ap 1401 | P10: Setor Bueno | Q10: Goiânia | R10: 74230-022 | U10: 44972 | V10: 9535323644 | W10: indicação de paciente - Mariane
A11: =IF(E11<>0, MONTH(E11),"") -> 3 | B11: =IF(F11="","", IF(F11<12,"Criança",IF(F11<18,"Adolescente",IF(F11<26,"Jovem",IF(F11<60,"Adulto", "Idoso"))))) -> Adulto | C11: Renata Ribeiro | D11: Terapia | E11: 32575 | F11: =IF(E11>0, DATEDIF(E11,TODAY(),"Y"),"") -> 36 | G11: 44667 | H11: =IF(U11>0,U11,TODAY()) -> 45490 | I11: =IF(G11>0, ROUNDDOWN((H11-G11)/365,0)& " Anos e "& ROUNDDOWN(((H11-G11)-ROUNDDOWN((H11-G11)/365,0)*365)/30,0)&" meses","") -> 2 Anos e 3 meses | J11: 62 999757543 | K11: contadora | L11: 62 984329324 | M11: mãe Veracine | N11: renata_rib@hotmail.co. | O11: Rua R17, 335 - Ed. Feel Home Lago das Rosas, ap 1504 | P11: Setor Oeste | Q11: Goiânia | R11: 74125-170 | S11: Elias Araújo Ribeiro + | T11: Veranice Machado Mesquita Ribeiro | U11: 45490 | V11: 3265415198 | W11: doctoralia
A12: =IF(E12<>0, MONTH(E12),"") | B12: Adulto | C12: Isaac Costa da Silva | D12: Seção Avulsa | F12: 30 | G12: 44707 | H12: =IF(U12>0,U12,TODAY()) -> 44707 | I12: =IF(G12>0, ROUNDDOWN((H12-G12)/365,0)& " Anos e "& ROUNDDOWN(((H12-G12)-ROUNDDOWN((H12-G12)/365,0)*365)/30,0)&" meses","") -> 0 Anos e 0 meses | J12: 62 991459990 | Q12: Goiânia | U12: 44707 | W12: doctoralia
A13: =IF(E13<>0, MONTH(E13),"") -> 11 | B13: =IF(F13="","", IF(F13<12,"Criança",IF(F13<18,"Adolescente",IF(F13<26,"Jovem",IF(F13<60,"Adulto", "Idoso"))))) -> Adulto | C13: Aurélio Rezende Lelis | D13: Terapia | E13: 28802 | F13: =IF(E13>0, DATEDIF(E13,TODAY(),"Y"),"") -> 47 | G13: 44707 | H13: =IF(U13>0,U13,TODAY()) -> 45042 | I13: =IF(G13>0, ROUNDDOWN((H13-G13)/365,0)& " Anos e "& ROUNDDOWN(((H13-G13)-ROUNDDOWN((H13-G13)/365,0)*365)/30,0)&" meses","") -> 0 Anos e 11 meses | J13: 62 985341313 | K13: empresário - farmácias | L13: 62 35111459 | M13: mãe Marilda | N13: aureliolelis@hotmail.com | O13: Rua Leopoldo de Bulhões, 1310 | P13: Centro | Q13: Inhumas/GO | R13: 75400-568 | U13: 45042 | W13: doctoralia
A14: =IF(E14<>0, MONTH(E14),"") -> 5 | B14: =IF(F14="","", IF(F14<12,"Criança",IF(F14<18,"Adolescente",IF(F14<26,"Jovem",IF(F14<60,"Adulto", "Idoso"))))) -> Criança | C14: Wallyson Guimarães Brito | D14: Seção Avulsa | E14: 42881 | F14: =IF(E14>0, DATEDIF(E14,TODAY(),"Y"),"") -> 8 | G14: 44711 | H14: =IF(U14>0,U14,TODAY()) -> 44711 | I14: =IF(G14>0, ROUNDDOWN((H14-G14)/365,0)& " Anos e "& ROUNDDOWN(((H14-G14)-ROUNDDOWN((H14-G14)/365,0)*365)/30,0)&" meses","") -> 0 Anos e 0 meses | L14: 62 982619515 | M14: mãe Thyara | N14: thyaraguimaraes05@gmail.com | O14: Rua Antônio Dumont Alves, Qd 66,Lt 23 Cs 2 | P14: Vila Maria | Q14: Aparecida de Goiânia/GO | R14: 74919-395 | S14: Uanderson Alves de Brito | T14: Thyara Guimarães Crispinho | U14: 44711 | W14: doctoralia
A15: =IF(E15<>0, MONTH(E15),"") | B15: =IF(F15="","", IF(F15<12,"Criança",IF(F15<18,"Adolescente",IF(F15<26,"Jovem",IF(F15<60,"Adulto", "Idoso"))))) -> Adulto | C15: Daniel Berg | D15: Seção Avulsa | F15: 28 | G15: 44713 | H15: =IF(U15>0,U15,TODAY()) -> 44713 | I15: =IF(G15>0, ROUNDDOWN((H15-G15)/365,0)& " Anos e "& ROUNDDOWN(((H15-G15)-ROUNDDOWN((H15-G15)/365,0)*365)/30,0)&" meses","") -> 0 Anos e 0 meses | J15: 62 984605723 | N15: bergdaniel309@gmail.com | Q15: Goiânia | U15: 44713 | W15: doctoralia
A16: =IF(E16<>0, MONTH(E16),"") | B16: Adulto | C16: Paulo Cezar Rodrigues Luz | D16: Seção Avulsa | G16: 44718 | H16: =IF(U16>0,U16,TODAY()) -> 44718 | I16: =IF(G16>0, ROUNDDOWN((H16-G16)/365,0)& " Anos e "& ROUNDDOWN(((H16-G16)-ROUNDDOWN((H16-G16)/365,0)*365)/30,0)&" meses","") -> 0 Anos e 0 meses | J16: 62 9820 5643 | N16: pcluz62@gmail.com | Q16: Goiânia | U16: 44718 | V16: 70264190130 | W16: doctoralia
A17: =IF(E17<>0, MONTH(E17),"") -> 5 | B17: =IF(F17="","", IF(F17<12,"Criança",IF(F17<18,"Adolescente",IF(F17<26,"Jovem",IF(F17<60,"Adulto", "Idoso"))))) -> Adulto | C17: Andre Junio Bons Olhos Fernandes | D17: Terapia | E17: 36293 | F17: =IF(E17>0, DATEDIF(E17,TODAY(),"Y"),"") -> 26 | G17: 44734 | H17: =IF(U17>0,U17,TODAY()) -> 44785 | I17: =IF(G17>0, ROUNDDOWN((H17-G17)/365,0)& " Anos e "& ROUNDDOWN(((H17-G17)-ROUNDDOWN((H17-G17)/365,0)*365)/30,0)&" meses","") -> 0 Anos e 1 meses | J17: 62993339167 | L17: 62 984447421 | M17: mãe Ana Flávia | N17: andrejunior1305@gmail.com | O17: Rua Aluísio Alvarenga Qd 36 Lt 20 | P17: Residencial Santa Fé | Q17: Goiânia | R17: 74356-285 | U17: 44785 | W17: doctoralia
A18: =IF(E18<>0, MONTH(E18),"") -> 11 | B18: =IF(F18="","", IF(F18<12,"Criança",IF(F18<18,"Adolescente",IF(F18<26,"Jovem",IF(F18<60,"Adulto", "Idoso"))))) -> Jovem | C18: José Wictor Rodrigues Moura | D18: Avaliação | E18: 36847 | F18: =IF(E18>0, DATEDIF(E18,TODAY(),"Y"),"") -> 25 | G18: 44763 | H18: =IF(U18>0,U18,TODAY()) -> 44966 | I18: =IF(G18>0, ROUNDDOWN((H18-G18)/365,0)& " Anos e "& ROUNDDOWN(((H18-G18)-ROUNDDOWN((H18-G18)/365,0)*365)/30,0)&" meses","") -> 0 Anos e 6 meses | J18: 62 991521595 | K18: desing gráfico | L18: 64 981327690 | M18: mãe | N18: wictorrodrigueslg@gmail.com | Q18: Goiânia | U18: 44966 | V18: 70333973135 | W18: doctoralia
A19: =IF(E19<>0, MONTH(E19),"") -> 9 | B19: =IF(F19="","", IF(F19<12,"Criança",IF(F19<18,"Adolescente",IF(F19<26,"Jovem",IF(F19<60,"Adulto", "Idoso"))))) -> Jovem | C19: Arthur Augusthus Ferreira Cabral | D19: Avaliação/Terapia | E19: 38233 | F19: =IF(E19>0, DATEDIF(E19,TODAY(),"Y"),"") -> 21 | G19: 44778 | H19: =IF(U19>0,U19,TODAY()) -> 45021 | I19: =IF(G19>0, ROUNDDOWN((H19-G19)/365,0)& " Anos e "& ROUNDDOWN(((H19-G19)-ROUNDDOWN((H19-G19)/365,0)*365)/30,0)&" meses","") -> 0 Anos e 8 meses | K19: estudante - medicina | L19: 62 981260166 | M19: mãe Renata | O19: Rua T.29, 484, Qd.41, Lt.08/09 - Ed. Excellence ap 1303 | P19: Setor Bueno | Q19: Goiânia | R19: 74210-050 | S19: Allyson Ribeiro e Silva Cabral | T19: Renata Claudia Santos Ferreira Cabral | U19: 45021 | V19: 03534079175 | W19: doctoralia
A20: =IF(E20<>0, MONTH(E20),"") -> 4 | B20: =IF(F20="","", IF(F20<12,"Criança",IF(F20<18,"Adolescente",IF(F20<26,"Jovem",IF(F20<60,"Adulto", "Idoso"))))) -> Adulto | C20: Jefferson Bevenuto dos Santos | D20: Terapia | E20: 33353 | F20: =IF(E20>0, DATEDIF(E20,TODAY(),"Y"),"") -> 34 | G20: 44790 | H20: =IF(U20>0,U20,TODAY()) -> 44912 | I20: =IF(G20>0, ROUNDDOWN((H20-G20)/365,0)& " Anos e "& ROUNDDOWN(((H20-G20)-ROUNDDOWN((H20-G20)/365,0)*365)/30,0)&" meses","") -> 0 Anos e 4 meses | J20: 62 999657858 | K20: cantor | L20: 62 981785672 | M20: empresário Thiago | Q20: Terezópolis/GO | U20: 44912 | W20: doctoralia
A21: =IF(E21<>0, MONTH(E21),"") -> 9 | B21: =IF(F21="","", IF(F21<12,"Criança",IF(F21<18,"Adolescente",IF(F21<26,"Jovem",IF(F21<60,"Adulto", "Idoso"))))) -> Adulto | C21: Bruno Machado de Aguiar | D21: Terapia | E21: 32393 | F21: =IF(E21>0, DATEDIF(E21,TODAY(),"Y"),"") -> 37 | G21: 44790 | H21: =IF(U21>0,U21,TODAY()) -> 44912 | I21: =IF(G21>0, ROUNDDOWN((H21-G21)/365,0)& " Anos e "& ROUNDDOWN(((H21-G21)-ROUNDDOWN((H21-G21)/365,0)*365)/30,0)&" meses","") -> 0 Anos e 4 meses | J21: 62 981785672 | K21: cantor | L21: 62 981785672 | M21: empresário Thiago | Q21: Terezópolis/GO | U21: 44912 | W21: doctoralia
A22: =IF(E22<>0, MONTH(E22),"") | B22: Adulto | C22: Gustavo Henrique Luz Resende | D22: Seção Avulsa | F22: 29 | G22: 44791 | H22: =IF(U22>0,U22,TODAY()) -> 44791 | I22: =IF(G22>0, ROUNDDOWN((H22-G22)/365,0)& " Anos e "& ROUNDDOWN(((H22-G22)-ROUNDDOWN((H22-G22)/365,0)*365)/30,0)&" meses","") -> 0 Anos e 0 meses | J22: 62 994245909 | U22: 44791 | W22: doctoralia
A23: =IF(E23<>0, MONTH(E23),"") -> 8 | B23: =IF(F23="","", IF(F23<12,"Criança",IF(F23<18,"Adolescente",IF(F23<26,"Jovem",IF(F23<60,"Adulto", "Idoso"))))) -> Adulto | C23: Jarbas Martins Jesuino Junior | D23: Terapia | E23: 32365 | F23: =IF(E23>0, DATEDIF(E23,TODAY(),"Y"),"") -> 37 | G23: 44797 | H23: =IF(U23>0,U23,TODAY()) -> 45261 | I23: =IF(G23>0, ROUNDDOWN((H23-G23)/365,0)& " Anos e "& ROUNDDOWN(((H23-G23)-ROUNDDOWN((H23-G23)/365,0)*365)/30,0)&" meses","") -> 1 Anos e 3 meses | J23: 62 996344824 | K23: engenheiro agronômo | L23: 16 993146855 | M23: pai | N23: jarbas.jesuino@corteva.com | O23: Rua Bento Peneago, 241 | P23: Centro | Q23: Jataí/GO | R23: 75800-055 | U23: 45261 | V23: 36907569876 | W23: indicação supervisora Juliana
A24: =IF(E24<>0, MONTH(E24),"") -> 3 | B24: =IF(F24="","", IF(F24<12,"Criança",IF(F24<18,"Adolescente",IF(F24<26,"Jovem",IF(F24<60,"Adulto", "Idoso"))))) -> Adulto | C24: Ivone Rodrigues de Castro | D24: Terapia | E24: 24924 | F24: =IF(E24>0, DATEDIF(E24,TODAY(),"Y"),"") -> 57 | G24: 44798 | H24: =IF(U24>0,U24,TODAY()) -> 44973 | I24: =IF(G24>0, ROUNDDOWN((H24-G24)/365,0)& " Anos e "& ROUNDDOWN(((H24-G24)-ROUNDDOWN((H24-G24)/365,0)*365)/30,0)&" meses","") -> 0 Anos e 5 meses | J24: 31 997261778 | K24: engenheiro civil | L24: 11 995165444 | M24: irmã Magda | N24: ivonecastro.gyn@gmail.com | O24: Avenida José Batista Gregório, acesso 03, casa 52 | P24: Conj Resid Terra Nova | Q24: Goiânia | R24: 74477-700 | U24: 44973 | W24: doctoralia
A25: =IF(E25<>0, MONTH(E25),"") -> 7 | B25: =IF(F25="","", IF(F25<12,"Criança",IF(F25<18,"Adolescente",IF(F25<26,"Jovem",IF(F25<60,"Adulto", "Idoso"))))) -> Adulto | C25: Matheus de Paula Carvalho | D25: Avaliação | E25: 35255 | F25: =IF(E25>0, DATEDIF(E25,TODAY(),"Y"),"") -> 29 | G25: 44812 | H25: =IF(U25>0,U25,TODAY()) -> 44896 | I25: =IF(G25>0, ROUNDDOWN((H25-G25)/365,0)& " Anos e "& ROUNDDOWN(((H25-G25)-ROUNDDOWN((H25-G25)/365,0)*365)/30,0)&" meses","") -> 0 Anos e 2 meses | J25: 62 985268791 | K25: empresário - produtos hospitalares | O25: Rua Joana Darc, Qd 24 Lt. 06 | P25: Centro | Q25: Santo Antônio de Goiás/GO | R25: 75375-000 | T25: Eliane Marques de Paula | U25: 44896 | V25: 04777044173 | W25: doctoralia
A26: =IF(E26<>0, MONTH(E26),"") -> 4 | B26: =IF(F26="","", IF(F26<12,"Criança",IF(F26<18,"Adolescente",IF(F26<26,"Jovem",IF(F26<60,"Adulto", "Idoso"))))) -> Adulto | C26: Diogo Alberto da Silva | D26: Avaliação | E26: 31870 | F26: =IF(E26>0, DATEDIF(E26,TODAY(),"Y"),"") -> 38 | G26: 44832 | H26: =IF(U26>0,U26,TODAY()) -> 44917 | I26: =IF(G26>0, ROUNDDOWN((H26-G26)/365,0)& " Anos e "& ROUNDDOWN(((H26-G26)-ROUNDDOWN((H26-G26)/365,0)*365)/30,0)&" meses","") -> 0 Anos e 2 meses | J26: 62 994622755 | K26: desing gráfico | L26: 62 981439141 | M26: esposa Lorena | Q26: Goiânia | U26: 44917 | V26: 02112768123 | W26: doctoralia
A27: =IF(E27<>0, MONTH(E27),"") -> 6 | B27: =IF(F27="","", IF(F27<12,"Criança",IF(F27<18,"Adolescente",IF(F27<26,"Jovem",IF(F27<60,"Adulto", "Idoso"))))) -> Criança | C27: Beatriz Bezerra Almeida | D27: Avaliação | E27: 42156 | F27: =IF(E27>0, DATEDIF(E27,TODAY(),"Y"),"") -> 10 | G27: 44853 | H27: =IF(U27>0,U27,TODAY()) -> 44951 | I27: =IF(G27>0, ROUNDDOWN((H27-G27)/365,0)& " Anos e "& ROUNDDOWN(((H27-G27)-ROUNDDOWN((H27-G27)/365,0)*365)/30,0)&" meses","") -> 0 Anos e 3 meses | K27: estudante | L27: 62 981449193 / 62 981236788 | M27: pai / mãe | Q27: Goiânia | S27: Fagner A. Morais de Almeida | T27: Marlise de Sousa Bezerra | U27: 44951 | V27: 07740251151 | W27: doctoralia
A28: =IF(E28<>0, MONTH(E28),"") -> 11 | B28: =IF(F28="","", IF(F28<12,"Criança",IF(F28<18,"Adolescente",IF(F28<26,"Jovem",IF(F28<60,"Adulto", "Idoso"))))) -> Adulto | C28: Thais Couto de Brito | D28: Terapia | E28: 29173 | F28: =IF(E28>0, DATEDIF(E28,TODAY(),"Y"),"") -> 46 | G28: 44854 | H28: =IF(U28>0,U28,TODAY()) -> 44874 | I28: =IF(G28>0, ROUNDDOWN((H28-G28)/365,0)& " Anos e "& ROUNDDOWN(((H28-G28)-ROUNDDOWN((H28-G28)/365,0)*365)/30,0)&" meses","") -> 0 Anos e 0 meses | J28: 62 999420092 | L28: 62 984066256 | M28: marido Carlos | N28: thais.coutodebrito@gmail.com | O28: Rua C-178, 20 | P28: Jardim América | Q28: Goiânia | R28: 74275-227 | U28: 44874 | W28: indicação paciente - Stella
A29: =IF(E29<>0, MONTH(E29),"") | B29: Adulto | C29: Polliani Silva de Araujo | D29: Seção Avulsa | F29: =IF(E29>0, DATEDIF(E29,TODAY(),"Y"),"") | G29: 44865 | H29: =IF(U29>0,U29,TODAY()) -> 44865 | I29: =IF(G29>0, ROUNDDOWN((H29-G29)/365,0)& " Anos e "& ROUNDDOWN(((H29-G29)-ROUNDDOWN((H29-G29)/365,0)*365)/30,0)&" meses","") -> 0 Anos e 0 meses | J29: 62 993700000 | Q29: Aparecida de Goiânia/GO | U29: 44865 | W29: doctoralia
A30: =IF(E30<>0, MONTH(E30),"") -> 3 | B30: =IF(F30="","", IF(F30<12,"Criança",IF(F30<18,"Adolescente",IF(F30<26,"Jovem",IF(F30<60,"Adulto", "Idoso"))))) -> Adulto | C30: Leandro Silva Oliveira | D30: Terapia | E30: 32572 | F30: =IF(E30>0, DATEDIF(E30,TODAY(),"Y"),"") -> 36 | G30: 44874 | H30: =IF(U30>0,U30,TODAY()) -> 45427 | I30: =IF(G30>0, ROUNDDOWN((H30-G30)/365,0)& " Anos e "& ROUNDDOWN(((H30-G30)-ROUNDDOWN((H30-G30)/365,0)*365)/30,0)&" meses","") -> 1 Anos e 6 meses | J30: 99 992125634 | K30: corretor de imóveis | L30: 94 991061014 | M30: irmã | N30: eng.leandrooliveira@hotmail.com | O30: Rua piraporã, 65 | P30: Alto da Glória | Q30: Goiânia | R30: 74815-230 | S30: Vicente Dias de Oliveira | T30: Edilene Silva Oliveira | U30: 45427 | W30: Google - pagina site
A31: =IF(E31<>0, MONTH(E31),"") -> 5 | B31: Adulto | C31: Pedro Pinheiro de Menezes | D31: Avaliação | E31: 38848 | F31: =IF(E31>0, DATEDIF(E31,TODAY(),"Y"),"") -> 19 | G31: 44874 | H31: =IF(U31>0,U31,TODAY()) -> 45030 | I31: =IF(G31>0, ROUNDDOWN((H31-G31)/365,0)& " Anos e "& ROUNDDOWN(((H31-G31)-ROUNDDOWN((H31-G31)/365,0)*365)/30,0)&" meses","") -> 0 Anos e 5 meses | K31: estudante | L31: 62 98162 9368 | M31: pai Kalazans | Q31: Goiânia | S31: Kalazans Pinheiro Costa | U31: 45030 | V31: 07710566138 | W31: indicação Dayse
A32: =IF(E32<>0, MONTH(E32),"") -> 2 | B32: =IF(F32="","", IF(F32<12,"Criança",IF(F32<18,"Adolescente",IF(F32<26,"Jovem",IF(F32<60,"Adulto", "Idoso"))))) -> Adulto | C32: Victor de Oliveira Morato | D32: Seção Avulsa | E32: 31835 | F32: =IF(E32>0, DATEDIF(E32,TODAY(),"Y"),"") -> 38 | G32: 44879 | H32: =IF(U32>0,U32,TODAY()) -> 44879 | I32: =IF(G32>0, ROUNDDOWN((H32-G32)/365,0)& " Anos e "& ROUNDDOWN(((H32-G32)-ROUNDDOWN((H32-G32)/365,0)*365)/30,0)&" meses","") -> 0 Anos e 0 meses | J32: 64 981187068 | U32: 44879 | W32: doctoralia
B33: Criança | C33: Davi Lucas Oliveira | D33: Terapia | F33: 9 | G33: 44879 | H33: =IF(U33>0,U33,TODAY()) -> 44890 | I33: =IF(G33>0, ROUNDDOWN((H33-G33)/365,0)& " Anos e "& ROUNDDOWN(((H33-G33)-ROUNDDOWN((H33-G33)/365,0)*365)/30,0)&" meses","") -> 0 Anos e 0 meses | K33: estudante | L33: 62 982943988 | M33: mãe Tatiane | Q33: Goiânia | T33: Tatiane Gomes de Oliveira | U33: 44890 | W33: doctoralia
A34: =IF(E34<>0, MONTH(E34),"") -> 2 | B34: =IF(F34="","", IF(F34<12,"Criança",IF(F34<18,"Adolescente",IF(F34<26,"Jovem",IF(F34<60,"Adulto", "Idoso"))))) -> Adulto | C34: Paulo Henrique de Souza Pinheiro | D34: Terapia | E34: 32190 | F34: =IF(E34>0, DATEDIF(E34,TODAY(),"Y"),"") -> 37 | G34: 44882 | H34: =IF(U34>0,U34,TODAY()) -> 45308 | I34: =IF(G34>0, ROUNDDOWN((H34-G34)/365,0)& " Anos e "& ROUNDDOWN(((H34-G34)-ROUNDDOWN((H34-G34)/365,0)*365)/30,0)&" meses","") -> 1 Anos e 2 meses | J34: 62 993245399 | K34: computação | L34: 62 992194873 | M34: pai | N34: phsp.analista@gmail.com | O34: Rua da Liberdade, 222 - Bloco D, ap 201 | P34: Vila Martins | Q34: Goiânia | R34: 74703-210 | U34: 45308 | V34: 01496535146 | W34: Doctoralia/Google
A35: =IF(E35<>0, MONTH(E35),"") | B35: Adulto | C35: Carlos Augusto | D35: Seção Avulsa | F35: =IF(E35>0, DATEDIF(E35,TODAY(),"Y"),"") | G35: 44882 | H35: =IF(U35>0,U35,TODAY()) -> 44882 | I35: =IF(G35>0, ROUNDDOWN((H35-G35)/365,0)& " Anos e "& ROUNDDOWN(((H35-G35)-ROUNDDOWN((H35-G35)/365,0)*365)/30,0)&" meses","") -> 0 Anos e 0 meses | U35: 44882 | W35: não tem registro
A36: =IF(E36<>0, MONTH(E36),"") | B36: Idoso | C36: Estelita Gomes de Almeida + | D36: Seção Avulsa | F36: 62 | G36: 44888 | H36: =IF(U36>0,U36,TODAY()) -> 44890 | I36: =IF(G36>0, ROUNDDOWN((H36-G36)/365,0)& " Anos e "& ROUNDDOWN(((H36-G36)-ROUNDDOWN((H36-G36)/365,0)*365)/30,0)&" meses","") -> 0 Anos e 0 meses | K36: empresária - vestuário | L36: 62 982943988 | M36: filha Tatiane | Q36: Goiânia | U36: 44890 | W36: doctoralia
A37: =IF(E37<>0, MONTH(E37),"") -> 5 | B37: =IF(F37="","", IF(F37<12,"Criança",IF(F37<18,"Adolescente",IF(F37<26,"Jovem",IF(F37<60,"Adulto", "Idoso"))))) -> Adulto | C37: Juscelia Nogueira de Almeida | D37: Terapia | E37: 30817 | F37: =IF(E37>0, DATEDIF(E37,TODAY(),"Y"),"") -> 41 | G37: 44888 | H37: =IF(U37>0,U37,TODAY()) -> 44952 | I37: =IF(G37>0, ROUNDDOWN((H37-G37)/365,0)& " Anos e "& ROUNDDOWN(((H37-G37)-ROUNDDOWN((H37-G37)/365,0)*365)/30,0)&" meses","") -> 0 Anos e 2 meses | J37: 62 991462430 | K37: salão beleza | Q37: Goiânia | U37: 44952 | W37: doctoralia
A38: =IF(E38<>0, MONTH(E38),"") -> 3 | B38: =IF(F38="","", IF(F38<12,"Criança",IF(F38<18,"Adolescente",IF(F38<26,"Jovem",IF(F38<60,"Adulto", "Idoso"))))) -> Idoso | C38: Maria Aparecida da Silva | D38: Seção Avulsa | E38: 23466 | F38: =IF(E38>0, DATEDIF(E38,TODAY(),"Y"),"") -> 61 | G38: 44895 | H38: =IF(U38>0,U38,TODAY()) -> 44895 | I38: =IF(G38>0, ROUNDDOWN((H38-G38)/365,0)& " Anos e "& ROUNDDOWN(((H38-G38)-ROUNDDOWN((H38-G38)/365,0)*365)/30,0)&" meses","") -> 0 Anos e 0 meses | J38: 62 98498939 | L38: 77 999813371 | M38: cunhada Jô | Q38: Goiânia | U38: 44895 | W38: indicação paciente (mãeTatiane)
A39: =IF(E39<>0, MONTH(E39),"") -> 6 | B39: =IF(F39="","", IF(F39<12,"Criança",IF(F39<18,"Adolescente",IF(F39<26,"Jovem",IF(F39<60,"Adulto", "Idoso"))))) -> Adulto | C39: Italo Teixeira Viana | D39: Seção Avulsa | E39: 34854 | F39: =IF(E39>0, DATEDIF(E39,TODAY(),"Y"),"") -> 30 | G39: 44903 | H39: =IF(U39>0,U39,TODAY()) -> 44903 | I39: =IF(G39>0, ROUNDDOWN((H39-G39)/365,0)& " Anos e "& ROUNDDOWN(((H39-G39)-ROUNDDOWN((H39-G39)/365,0)*365)/30,0)&" meses","") -> 0 Anos e 0 meses | J39: 62 982140712 | U39: 44903 | W39: doctoralia
A40: =IF(E40<>0, MONTH(E40),"") -> 9 | B40: =IF(F40="","", IF(F40<12,"Criança",IF(F40<18,"Adolescente",IF(F40<26,"Jovem",IF(F40<60,"Adulto", "Idoso"))))) -> Adulto | C40: Yuri Júlio Medeiros de Souza | D40: Terapia | E40: 33131 | F40: =IF(E40>0, DATEDIF(E40,TODAY(),"Y"),"") -> 35 | G40: 44903 | H40: =IF(U40>0,U40,TODAY()) -> 44993 | I40: =IF(G40>0, ROUNDDOWN((H40-G40)/365,0)& " Anos e "& ROUNDDOWN(((H40-G40)-ROUNDDOWN((H40-G40)/365,0)*365)/30,0)&" meses","") -> 0 Anos e 3 meses | J40: 62 991522924 | K40: empresário - vestuário | Q40: Goiânia | U40: 44993 | W40: doctoralia
A41: =IF(E41<>0, MONTH(E41),"") -> 12 | B41: =IF(F41="","", IF(F41<12,"Criança",IF(F41<18,"Adolescente",IF(F41<26,"Jovem",IF(F41<60,"Adulto", "Idoso"))))) -> Adulto | C41: Aredson Afonso Pereira Junior | D41: Seção Avulsa | E41: 27383 | F41: =IF(E41>0, DATEDIF(E41,TODAY(),"Y"),"") -> 51 | G41: 44904 | H41: =IF(U41>0,U41,TODAY()) -> 44904 | I41: =IF(G41>0, ROUNDDOWN((H41-G41)/365,0)& " Anos e "& ROUNDDOWN(((H41-G41)-ROUNDDOWN((H41-G41)/365,0)*365)/30,0)&" meses","") -> 0 Anos e 0 meses | J41: 64 984109063 | U41: 44904 | W41: Google - pagina site
A42: =IF(E42<>0, MONTH(E42),"") | B42: Adulto | C42: Jaqueline Costa | D42: Terapia | F42: =IF(E42>0, DATEDIF(E42,TODAY(),"Y"),"") | G42: 44907 | H42: =IF(U42>0,U42,TODAY()) -> 45091 | I42: =IF(G42>0, ROUNDDOWN((H42-G42)/365,0)& " Anos e "& ROUNDDOWN(((H42-G42)-ROUNDDOWN((H42-G42)/365,0)*365)/30,0)&" meses","") -> 0 Anos e 6 meses | J42: 63 984377800 | N42: jakeline.costaadv@gmail.com | O42: Rua R-1, 27 | P42: Vila Juscelino Kubitschek | Q42: Uruaçu | R42: 76400-000 | U42: 45091 | W42: Indicação amigo Marcelo | X42: valor social
A43: =IF(E43<>0, MONTH(E43),"") -> 10 | B43: =IF(F43="","", IF(F43<12,"Criança",IF(F43<18,"Adolescente",IF(F43<26,"Jovem",IF(F43<60,"Adulto", "Idoso"))))) -> Adolescente | C43: Luis Felipe Tumelero Zago | D43: Avaliação | E43: 41208 | F43: =IF(E43>0, DATEDIF(E43,TODAY(),"Y"),"") -> 13 | G43: 44958 | H43: =IF(U43>0,U43,TODAY()) -> 45021 | I43: =IF(G43>0, ROUNDDOWN((H43-G43)/365,0)& " Anos e "& ROUNDDOWN(((H43-G43)-ROUNDDOWN((H43-G43)/365,0)*365)/30,0)&" meses","") -> 0 Anos e 2 meses | K43: estudante | L43: 66 999882985 | M43: mãe Anayara | N43: naytumelero@gmail.com | O43: Rua 57, 269 | P43: Setor Norte | Q43: Água Boa/MT | R43: 78635-000 | S43: Alaerte Alves Zago | T43: Anayara Tumelero | U43: 45021 | V43: 07528913162 | W43: doctoralia
A44: =IF(E44<>0, MONTH(E44),"") -> 5 | B44: =IF(F44="","", IF(F44<12,"Criança",IF(F44<18,"Adolescente",IF(F44<26,"Jovem",IF(F44<60,"Adulto", "Idoso"))))) -> Adulto | C44: Luana Portilho Godinho | D44: Seção Avulsa | E44: 33740 | F44: =IF(E44>0, DATEDIF(E44,TODAY(),"Y"),"") -> 33 | G44: 44958 | H44: =IF(U44>0,U44,TODAY()) -> 44958 | I44: =IF(G44>0, ROUNDDOWN((H44-G44)/365,0)& " Anos e "& ROUNDDOWN(((H44-G44)-ROUNDDOWN((H44-G44)/365,0)*365)/30,0)&" meses","") -> 0 Anos e 0 meses | J44: 34 610 631347 | K44: estudante - medicina | N44: luportilho.med@gmail.com | Q44: Espanha | T44: Iara Sousa Portilho | U44: 44958 | V44: 04112659113 | W44: doctoralia
A45: =IF(E45<>0, MONTH(E45),"") -> 9 | B45: =IF(F45="","", IF(F45<12,"Criança",IF(F45<18,"Adolescente",IF(F45<26,"Jovem",IF(F45<60,"Adulto", "Idoso"))))) -> Adolescente | C45: Ayke Ferreira Cabral | D45: Terapia | E45: 39721 | F45: =IF(E45>0, DATEDIF(E45,TODAY(),"Y"),"") -> 17 | G45: 44965 | H45: =IF(U45>0,U45,TODAY()) -> 45055 | I45: =IF(G45>0, ROUNDDOWN((H45-G45)/365,0)& " Anos e "& ROUNDDOWN(((H45-G45)-ROUNDDOWN((H45-G45)/365,0)*365)/30,0)&" meses","") -> 0 Anos e 3 meses | K45: estudante | L45: 62 981260166 | M45: mãe Renata | O45: Rua T.29, 484, Qd.41, Lt.08/09 - Ed. Excellence ap 1304 | P45: Setor Bueno | Q45: Goiânia | R45: 74210-051 | S45: Allyson Ribeiro e Silva Cabral | T45: Renata Claudia Santos Ferreira Cabral | U45: 45055 | W45: indicação paciente- irmão Arthur
A46: =IF(E46<>0, MONTH(E46),"") -> 4 | B46: =IF(F46="","", IF(F46<12,"Criança",IF(F46<18,"Adolescente",IF(F46<26,"Jovem",IF(F46<60,"Adulto", "Idoso"))))) -> Adulto | C46: Ana Paula Carneiro Silva Gratão | D46: Terapia | E46: 34429 | F46: =IF(E46>0, DATEDIF(E46,TODAY(),"Y"),"") -> 31 | G46: 44960 | H46: =IF(U46>0,U46,TODAY()) -> 45027 | I46: =IF(G46>0, ROUNDDOWN((H46-G46)/365,0)& " Anos e "& ROUNDDOWN(((H46-G46)-ROUNDDOWN((H46-G46)/365,0)*365)/30,0)&" meses","") -> 0 Anos e 2 meses | J46: 16 991542991 | K46: estudante - veterinária | U46: 45027 | W46: doctoralia
A47: =IF(E47<>0, MONTH(E47),"") | B47: Adulto | C47: Tatiane Gomes de Oliveira | D47: Seção Avulsa | F47: =IF(E47>0, DATEDIF(E47,TODAY(),"Y"),"") | G47: 44994 | H47: =IF(U47>0,U47,TODAY()) -> 45015 | I47: =IF(G47>0, ROUNDDOWN((H47-G47)/365,0)& " Anos e "& ROUNDDOWN(((H47-G47)-ROUNDDOWN((H47-G47)/365,0)*365)/30,0)&" meses","") -> 0 Anos e 0 meses | J47: 62 982943988 | K47: empresário - semijoias | Q47: Goiânia | T47: Estelita Gomes de Almeida + | U47: 45015 | W47: doctoralia
A48: =IF(E48<>0, MONTH(E48),"") -> 6 | B48: =IF(F48="","", IF(F48<12,"Criança",IF(F48<18,"Adolescente",IF(F48<26,"Jovem",IF(F48<60,"Adulto", "Idoso"))))) -> Criança | C48: Mateus Granzotto Furlanetto | D48: Avaliação | E48: 41818 | F48: =IF(E48>0, DATEDIF(E48,TODAY(),"Y"),"") -> 11 | G48: 45000 | H48: =IF(U48>0,U48,TODAY()) -> 45111 | I48: =IF(G48>0, ROUNDDOWN((H48-G48)/365,0)& " Anos e "& ROUNDDOWN(((H48-G48)-ROUNDDOWN((H48-G48)/365,0)*365)/30,0)&" meses","") -> 0 Anos e 3 meses | K48: estudante | L48: 62 992967665 / 62 984084486 | M48: mãe | O48: Rua C-238, 359 - Ed Hl Park Vaca Brava, ap 601 | P48: Jardim América | Q48: Goiânia | R48: 74290-150 | S48: Humberto Furlanetto de Oliveira | T48: Daiene Granzotto Miranda | U48: 45111 | V48: 71166689182 | W48: indicação Dayse
A49: =IF(E49<>0, MONTH(E49),"") -> 8 | B49: Adulto | C49: Vitória Alexandre Carvalho C. Fonseca | D49: Terapia | E49: 36376 | F49: =IF(E49>0, DATEDIF(E49,TODAY(),"Y"),"") -> 26 | G49: 45028 | H49: =IF(U49>0,U49,TODAY()) -> 45072 | I49: =IF(G49>0, ROUNDDOWN((H49-G49)/365,0)& " Anos e "& ROUNDDOWN(((H49-G49)-ROUNDDOWN((H49-G49)/365,0)*365)/30,0)&" meses","") -> 0 Anos e 1 meses | J49: 62 991189009 | K49: estudante - direito | L49: 62 99933-2423 | M49: esposo Ronan | N49: vitoria.alexandre1604@gmail.com | O49: Rua Angico, 140. APM Bloco 01 e 02, ap 203 | P49: Jardim Mariliza | Q49: Goiânia | R49: 74885-020 | U49: 45072 | W49: indicacação amiga Cristina | X49: valor social
A50: =IF(E50<>0, MONTH(E50),"") -> 4 | B50: =IF(F50="","", IF(F50<12,"Criança",IF(F50<18,"Adolescente",IF(F50<26,"Jovem",IF(F50<60,"Adulto", "Idoso"))))) -> Adulto | C50: Suyara Veloso e Lemos | D50: Avaliação | E50: 33345 | F50: =IF(E50>0, DATEDIF(E50,TODAY(),"Y"),"") -> 34 | G50: 45042 | H50: =IF(U50>0,U50,TODAY()) -> 45137 | I50: =IF(G50>0, ROUNDDOWN((H50-G50)/365,0)& " Anos e "& ROUNDDOWN(((H50-G50)-ROUNDDOWN((H50-G50)/365,0)*365)/30,0)&" meses","") -> 0 Anos e 3 meses | J50: 62 992373442 | K50: estudante - medicina | Q50: Goiânia | U50: 45137 | W50: indicação Dayse | X50: abandonou a avaliação
A51: =IF(E51<>0, MONTH(E51),"") -> 7 | B51: =IF(F51="","", IF(F51<12,"Criança",IF(F51<18,"Adolescente",IF(F51<26,"Jovem",IF(F51<60,"Adulto", "Idoso"))))) -> Adulto | C51: Thais Mendes da Silva | D51: Avaliação | E51: 34897 | F51: =IF(E51>0, DATEDIF(E51,TODAY(),"Y"),"") -> 30 | G51: 45049 | H51: =IF(U51>0,U51,TODAY()) -> 45206 | I51: =IF(G51>0, ROUNDDOWN((H51-G51)/365,0)& " Anos e "& ROUNDDOWN(((H51-G51)-ROUNDDOWN((H51-G51)/365,0)*365)/30,0)&" meses","") -> 0 Anos e 5 meses | J51: 62 985807365 | K51: estudante- eng elétrica | Q51: Goiânia | U51: 45206 | V51: 05061110161 | W51: indicação amigos/Familiares | X51: valor social
A52: =IF(E52<>0, MONTH(E52),"") -> 9 | B52: =IF(F52="","", IF(F52<12,"Criança",IF(F52<18,"Adolescente",IF(F52<26,"Jovem",IF(F52<60,"Adulto", "Idoso"))))) -> Jovem | C52: Neivander Braga Barros | D52: Seção Avulsa | E52: 37140 | F52: =IF(E52>0, DATEDIF(E52,TODAY(),"Y"),"") -> 24 | G52: 45076 | H52: =IF(U52>0,U52,TODAY()) -> 45076 | I52: =IF(G52>0, ROUNDDOWN((H52-G52)/365,0)& " Anos e "& ROUNDDOWN(((H52-G52)-ROUNDDOWN((H52-G52)/365,0)*365)/30,0)&" meses","") -> 0 Anos e 0 meses | J52: 66 992236157 | K52: piloto | Q52: Goiânia | U52: 45076 | W52: doctoralia
A53: =IF(E53<>0, MONTH(E53),"") -> 4 | B53: =IF(F53="","", IF(F53<12,"Criança",IF(F53<18,"Adolescente",IF(F53<26,"Jovem",IF(F53<60,"Adulto", "Idoso"))))) -> Adulto | C53: Miriane Cruvinel Fiuza | D53: Terapia | E53: 31505 | F53: =IF(E53>0, DATEDIF(E53,TODAY(),"Y"),"") -> 39 | G53: 45084 | H53: =IF(U53>0,U53,TODAY()) -> 45335 | I53: =IF(G53>0, ROUNDDOWN((H53-G53)/365,0)& " Anos e "& ROUNDDOWN(((H53-G53)-ROUNDDOWN((H53-G53)/365,0)*365)/30,0)&" meses","") -> 0 Anos e 8 meses | J53: 62 996139489 | K53: dona de casa | P53: Condomínio Aldeia | Q53: Goiânia | U53: 45335 | W53: indicação Dayse
A54: =IF(E54<>0, MONTH(E54),"") -> 12 | B54: =IF(F54="","", IF(F54<12,"Criança",IF(F54<18,"Adolescente",IF(F54<26,"Jovem",IF(F54<60,"Adulto", "Idoso"))))) -> Adulto | C54: Eurico Gomes de Lima | D54: Avaliação | E54: 32124 | F54: =IF(E54>0, DATEDIF(E54,TODAY(),"Y"),"") -> 38 | G54: 45086 | H54: =IF(U54>0,U54,TODAY()) -> 45181 | I54: =IF(G54>0, ROUNDDOWN((H54-G54)/365,0)& " Anos e "& ROUNDDOWN(((H54-G54)-ROUNDDOWN((H54-G54)/365,0)*365)/30,0)&" meses","") -> 0 Anos e 3 meses | J54: 62 991557171 | K54: empresário - locação máquinas | L54: 66 981215071 | M54: esposa Luciellen | Q54: Goiânia | U54: 45181 | V54: 91851114220 | W54: Doctoralia
A55: =IF(E55<>0, MONTH(E55),"") | B55: Idoso | C55: Alerte Maria Oliveira | D55: Seção Avulsa | F55: =IF(E55>0, DATEDIF(E55,TODAY(),"Y"),"") | G55: 45104 | H55: =IF(U55>0,U55,TODAY()) -> 45118 | I55: =IF(G55>0, ROUNDDOWN((H55-G55)/365,0)& " Anos e "& ROUNDDOWN(((H55-G55)-ROUNDDOWN((H55-G55)/365,0)*365)/30,0)&" meses","") -> 0 Anos e 0 meses | J55: 62 982555500 | Q55: Goiânia | U55: 45118 | W55: doctoralia
A56: =IF(E56<>0, MONTH(E56),"") -> 12 | B56: Adulto | C56: Fabiano Pereira Arantes | D56: Seção Avulsa | E56: 27735 | F56: =IF(E56>0, DATEDIF(E56,TODAY(),"Y"),"") -> 50 | G56: 45112 | H56: =IF(U56>0,U56,TODAY()) -> 45112 | I56: =IF(G56>0, ROUNDDOWN((H56-G56)/365,0)& " Anos e "& ROUNDDOWN(((H56-G56)-ROUNDDOWN((H56-G56)/365,0)*365)/30,0)&" meses","") -> 0 Anos e 0 meses | J56: 62 999071858 | Q56: Goiânia | U56: 45112 | W56: indicação paciente Suyara (esposa)
A57: =IF(E57<>0, MONTH(E57),"") | B57: Adulto | C57: Vinicius Garcês | D57: Seção Avulsa | F57: =IF(E57>0, DATEDIF(E57,TODAY(),"Y"),"") | G57: 45115 | H57: =IF(U57>0,U57,TODAY()) -> 45115 | I57: =IF(G57>0, ROUNDDOWN((H57-G57)/365,0)& " Anos e "& ROUNDDOWN(((H57-G57)-ROUNDDOWN((H57-G57)/365,0)*365)/30,0)&" meses","") -> 0 Anos e 0 meses | J57: 62 991678722 | N57: vinikrek123@gmail.com | Q57: Goiânia | U57: 45115 | W57: doctoralia | X57: autismo nivel moderado? prefere ir direto no psiquiatrico
A58: =IF(E58<>0, MONTH(E58),"") -> 10 | B58: =IF(F58="","", IF(F58<12,"Criança",IF(F58<18,"Adolescente",IF(F58<26,"Jovem",IF(F58<60,"Adulto", "Idoso"))))) -> Jovem | C58: Geovanna Gomes Alves | D58: Terapia | E58: 37190 | F58: =IF(E58>0, DATEDIF(E58,TODAY(),"Y"),"") -> 24 | G58: 45121 | H58: =IF(U58>0,U58,TODAY()) -> 45370 | I58: =IF(G58>0, ROUNDDOWN((H58-G58)/365,0)& " Anos e "& ROUNDDOWN(((H58-G58)-ROUNDDOWN((H58-G58)/365,0)*365)/30,0)&" meses","") -> 0 Anos e 8 meses | J58: 33 6 63428550 | K58: empresário/vestuário | O58: Rua CM 1Tropicale - Residencial Salinas | P58: Setor Candida de Morais | Q58: Goiânia | R58: 74463-150 | U58: 45370 | V58: 70705379132 | W58: Doctoralia/Google | X58: morava na França
A59: =IF(E59<>0, MONTH(E59),"") | B59: Adulto | C59: Jhessica Fernandes | D59: Terapia | F59: =IF(E59>0, DATEDIF(E59,TODAY(),"Y"),"") | G59: 45141 | H59: =IF(U59>0,U59,TODAY()) -> 45175 | I59: =IF(G59>0, ROUNDDOWN((H59-G59)/365,0)& " Anos e "& ROUNDDOWN(((H59-G59)-ROUNDDOWN((H59-G59)/365,0)*365)/30,0)&" meses","") -> 0 Anos e 1 meses | J59: 62 985481685 | K59: apropecuária | N59: jhessicafernan5fs@gmail.com | Q59: SãoLuís de Montes Belos/GO | U59: 45175 | W59: indicação amiga - Hebemar
A60: =IF(E60<>0, MONTH(E60),"") -> 6 | B60: =IF(F60="","", IF(F60<12,"Criança",IF(F60<18,"Adolescente",IF(F60<26,"Jovem",IF(F60<60,"Adulto", "Idoso"))))) -> Adolescente | C60: Arthur Apolo Ferreira Roriz | D60: Avaliação | E60: 41065 | F60: =IF(E60>0, DATEDIF(E60,TODAY(),"Y"),"") -> 13 | G60: 45169 | H60: =IF(U60>0,U60,TODAY()) -> 45270 | I60: =IF(G60>0, ROUNDDOWN((H60-G60)/365,0)& " Anos e "& ROUNDDOWN(((H60-G60)-ROUNDDOWN((H60-G60)/365,0)*365)/30,0)&" meses","") -> 0 Anos e 3 meses | K60: estudante | L60: 62 999833299 | M60: mãe Thais | Q60: Aparecida de Goiânia | S60: Willian Peres Roriz | T60: Thais Garcia Ferreira | U60: 45270 | V60: 15464004947 | W60: indicação aluna Integra
A61: =IF(E61<>0, MONTH(E61),"") | B61: Adulto | C61: Anna Flávia Costa Martins dosSantos | D61: Terapia | F61: =IF(E61>0, DATEDIF(E61,TODAY(),"Y"),"") | G61: 45175 | H61: =IF(U61>0,U61,TODAY()) -> 45224 | I61: =IF(G61>0, ROUNDDOWN((H61-G61)/365,0)& " Anos e "& ROUNDDOWN(((H61-G61)-ROUNDDOWN((H61-G61)/365,0)*365)/30,0)&" meses","") -> 0 Anos e 1 meses | J61: 351 964 058214 | N61: annaflaavia28@hotmail.com | Q61: Portugal | U61: 45224 | W61: Doctoralia
A62: =IF(E62<>0, MONTH(E62),"") -> 8 | B62: =IF(F62="","", IF(F62<12,"Criança",IF(F62<18,"Adolescente",IF(F62<26,"Jovem",IF(F62<60,"Adulto", "Idoso"))))) -> Idoso | C62: Terezinha Maria Oliveira Godoy | D62: Seção Avulsa | E62: 19225 | F62: =IF(E62>0, DATEDIF(E62,TODAY(),"Y"),"") -> 73 | G62: 45210 | H62: =IF(U62>0,U62,TODAY()) -> 45210 | I62: =IF(G62>0, ROUNDDOWN((H62-G62)/365,0)& " Anos e "& ROUNDDOWN(((H62-G62)-ROUNDDOWN((H62-G62)/365,0)*365)/30,0)&" meses","") -> 0 Anos e 0 meses | J62: 62 993723731 | L62: 62 92582020 | M62: filha Claudiana | Q62: Goiânia | U62: 45210 | W62: Doctoralia | X62: demanda: quero me separar?
A63: =IF(E63<>0, MONTH(E63),"") | B63: Adulto | C63: Nayara de Souza Brito | D63: Seção Avulsa | F63: =IF(E63>0, DATEDIF(E63,TODAY(),"Y"),"") | G63: 45210 | H63: =IF(U63>0,U63,TODAY()) -> 45210 | I63: =IF(G63>0, ROUNDDOWN((H63-G63)/365,0)& " Anos e "& ROUNDDOWN(((H63-G63)-ROUNDDOWN((H63-G63)/365,0)*365)/30,0)&" meses","") -> 0 Anos e 0 meses | J63: 62 981666458 | K63: professora | N63: nayarasb25@gmail.com | Q63: Goiânia | U63: 45210 | W63: Doctoralia | X63: demanda: tenho TDAH?
A64: =IF(E64<>0, MONTH(E64),"") -> 2 | B64: Adulto | C64: Ana Carolina Gomes Santana | D64: Seção Avulsa | E64: 34752 | F64: =IF(E64>0, DATEDIF(E64,TODAY(),"Y"),"") -> 30 | G64: 45212 | H64: =IF(U64>0,U64,TODAY()) -> 45212 | I64: =IF(G64>0, ROUNDDOWN((H64-G64)/365,0)& " Anos e "& ROUNDDOWN(((H64-G64)-ROUNDDOWN((H64-G64)/365,0)*365)/30,0)&" meses","") -> 0 Anos e 0 meses | J64: 62 991845535 | K64: engenheiro civil | L64: 62 981389186 | M64: esposo Caio | O64: Rua T37, 2300 - Ed. DNA Smart Style Bloco G, ap 1402 | P64: Setor Bueno | Q64: Goiânia | R64: 74230-023 | U64: 45212 | W64: indicação paciente Caio (esposa) | X64: sentimentos melancólicos
A65: =IF(E65<>0, MONTH(E65),"") -> 12 | B65: =IF(F65="","", IF(F65<12,"Criança",IF(F65<18,"Adolescente",IF(F65<26,"Jovem",IF(F65<60,"Adulto", "Idoso"))))) -> Criança | C65: Luisa Leal Gomes | D65: Terapia | E65: 42367 | F65: =IF(E65>0, DATEDIF(E65,TODAY(),"Y"),"") -> 10 | G65: 45216 | H65: =IF(U65>0,U65,TODAY()) -> 45317 | I65: =IF(G65>0, ROUNDDOWN((H65-G65)/365,0)& " Anos e "& ROUNDDOWN(((H65-G65)-ROUNDDOWN((H65-G65)/365,0)*365)/30,0)&" meses","") -> 0 Anos e 3 meses | K65: estudante | L65: 62 981625163/ 62 981189044 | M65: mãe Camilla / pai Sávio | Q65: Goiânia | S65: Sávio Barra Gomes | T65: Camilla Leal Souza Gomes | U65: 45317 | W65: indicação paciente - Stella
A66: =IF(E66<>0, MONTH(E66),"") | B66: Adulto | C66: Marcelo Cardoso Martins | D66: Terapia | F66: =IF(E66>0, DATEDIF(E66,TODAY(),"Y"),"") | G66: 45219 | H66: =IF(U66>0,U66,TODAY()) -> 45293 | I66: =IF(G66>0, ROUNDDOWN((H66-G66)/365,0)& " Anos e "& ROUNDDOWN(((H66-G66)-ROUNDDOWN((H66-G66)/365,0)*365)/30,0)&" meses","") -> 0 Anos e 2 meses | J66: 64 984133620 | K66: programador/computação | Q66: Goiânia | U66: 45293 | W66: Doctoralia
A67: =IF(E67<>0, MONTH(E67),"") -> 2 | B67: Adulto | C67: Paula Eduarda Amorim | D67: Seção Avulsa | E67: 34380 | F67: =IF(E67>0, DATEDIF(E67,TODAY(),"Y"),"") -> 31 | G67: 45224 | H67: =IF(U67>0,U67,TODAY()) -> 45224 | I67: =IF(G67>0, ROUNDDOWN((H67-G67)/365,0)& " Anos e "& ROUNDDOWN(((H67-G67)-ROUNDDOWN((H67-G67)/365,0)*365)/30,0)&" meses","") -> 0 Anos e 0 meses | J67: 62 995016035 | K67: engenheiro civil | Q67: Goiânia | U67: 45224 | W67: indicação amigo Marcelo | X67: sentimento inferioridade no trabalho
A68: =IF(E68<>0, MONTH(E68),"") -> 4 | B68: =IF(F68="","", IF(F68<12,"Criança",IF(F68<18,"Adolescente",IF(F68<26,"Jovem",IF(F68<60,"Adulto", "Idoso"))))) -> Adulto | C68: Jordana de Faria Maciel | D68: Terapia | E68: 33349 | F68: =IF(E68>0, DATEDIF(E68,TODAY(),"Y"),"") -> 34 | G68: 45239 | H68: =IF(U68>0,U68,TODAY()) -> 45269 | I68: =IF(G68>0, ROUNDDOWN((H68-G68)/365,0)& " Anos e "& ROUNDDOWN(((H68-G68)-ROUNDDOWN((H68-G68)/365,0)*365)/30,0)&" meses","") -> 0 Anos e 1 meses | J68: 62 999948593 | K68: médica | L68: 62 32615016 | M68: mãe Iraides | N68: jordanafmaciel@gmail.com | O68: R. 14, 254, Qd. 73 Lt 11/13 - Unique Residence | P68: Jardim Goiás | Q68: Goiânia | R68: 74810-190 | S68: Carlos Alberto Maciel + | T68: Iraides Pinto de Faria | U68: 45269 | V68: 03761412126 | W68: indicação psiquiatra - Jéssica
A69: =IF(E69<>0, MONTH(E69),"") -> 11 | B69: =IF(F69="","", IF(F69<12,"Criança",IF(F69<18,"Adolescente",IF(F69<26,"Jovem",IF(F69<60,"Adulto", "Idoso"))))) -> Adulto | C69: João Luiz Andrade Leitão | D69: Terapia | E69: 33548 | F69: =IF(E69>0, DATEDIF(E69,TODAY(),"Y"),"") -> 34 | G69: 45267 | H69: =IF(U69>0,U69,TODAY()) -> 45419 | I69: =IF(G69>0, ROUNDDOWN((H69-G69)/365,0)& " Anos e "& ROUNDDOWN(((H69-G69)-ROUNDDOWN((H69-G69)/365,0)*365)/30,0)&" meses","") -> 0 Anos e 5 meses | J69: 62984628781 | K69: engenheiro elétrico | L69: 62 995591902 | M69: mãe Luciene | N69: joao.leitaoengenharia@gmail.com | O69: Rua Jatobá | P69: Chácara Recreio Samabaia | Q69: Goiânia | R69: 74691-304 | S69: Fábio Pereira Leitão | T69: Luciene Maria de Andrade Leitão | U69: 45419 | V69: 03715766107 | W69: Doctoralia
A70: =IF(E70<>0, MONTH(E70),"") -> 3 | B70: =IF(F70="","", IF(F70<12,"Criança",IF(F70<18,"Adolescente",IF(F70<26,"Jovem",IF(F70<60,"Adulto", "Idoso"))))) -> Adulto | C70: Josiane Velten | D70: Seção Avulsa | E70: 34771 | F70: =IF(E70>0, DATEDIF(E70,TODAY(),"Y"),"") -> 30 | G70: 45268 | H70: =IF(U70>0,U70,TODAY()) -> 45279 | I70: =IF(G70>0, ROUNDDOWN((H70-G70)/365,0)& " Anos e "& ROUNDDOWN(((H70-G70)-ROUNDDOWN((H70-G70)/365,0)*365)/30,0)&" meses","") -> 0 Anos e 0 meses | J70: 27 998846503 | K70: pastora | L70: 51 998566038 | M70: esposo Heitor Marques | N70: josiane.velten@hotmail.com | O70: Rua Marechal Castelo Branco, 3339 | P70: Centro | Q70: Schroeder/SC | R70: 89275-000 | S70: Josias Velten | T70: Florentina Boldt Velten | U70: 45279 | V70: 12571653725 | W70: amizades IECLB | X70: valor social
A71: =IF(E71<>0, MONTH(E71),"") -> 1 | B71: =IF(F71="","", IF(F71<12,"Criança",IF(F71<18,"Adolescente",IF(F71<26,"Jovem",IF(F71<60,"Adulto", "Idoso"))))) -> Adulto | C71: Amanda Cristina de Souza | D71: Terapia | E71: 35444 | F71: =IF(E71>0, DATEDIF(E71,TODAY(),"Y"),"") -> 29 | G71: 45272 | H71: =IF(U71>0,U71,TODAY()) -> 45342 | I71: =IF(G71>0, ROUNDDOWN((H71-G71)/365,0)& " Anos e "& ROUNDDOWN(((H71-G71)-ROUNDDOWN((H71-G71)/365,0)*365)/30,0)&" meses","") -> 0 Anos e 2 meses | J71: 62 991000708 | L71: 62 992691761 | M71: irmã Anna Carolina | N71: amanda.chris04@gmail.com | O71: Alameda Fleury curado, 159 - Condomínio vida Sol | P71: Faiçalville | Q71: Goiânia | R71: 74350-650 | S71: Darci de Souza Lima | T71: Iolene Mariano de Oliveira | U71: 45342 | V71: 70096990112 | W71: indicação terceiros (alguém da FGR)
A72: =IF(E72<>0, MONTH(E72),"") -> 1 | B72: =IF(F72="","", IF(F72<12,"Criança",IF(F72<18,"Adolescente",IF(F72<26,"Jovem",IF(F72<60,"Adulto", "Idoso"))))) -> Adulto | C72: Ricardo Leite de Sousa | D72: Terapia | E72: 30691 | F72: =IF(E72>0, DATEDIF(E72,TODAY(),"Y"),"") -> 42 | G72: 45295 | H72: =IF(U72>0,U72,TODAY()) -> 45433 | I72: =IF(G72>0, ROUNDDOWN((H72-G72)/365,0)& " Anos e "& ROUNDDOWN(((H72-G72)-ROUNDDOWN((H72-G72)/365,0)*365)/30,0)&" meses","") -> 0 Anos e 4 meses | J72: 11 953001984 | K72: engenheiro elétrico | L72: 11 971498867 | M72: irmã Camila | N72: ricardo.lsousa84@gmail.com | O72: Rua Jatobá | P72: Chácara Recreio Samabaia | Q72: Goiânia | R72: 74691-305 | S72: Antonio Luis Gomes Sousa | T72: Solange Gramelick Leite G. Sousa | U72: 45433 | V72: 30915636859 | W72: indicação paciente - João Leitão
A73: =IF(E73<>0, MONTH(E73),"") -> 7 | B73: =IF(F73="","", IF(F73<12,"Criança",IF(F73<18,"Adolescente",IF(F73<26,"Jovem",IF(F73<60,"Adulto", "Idoso"))))) -> Criança | C73: Júlia Olegario dos Santos | D73: Terapia | E73: 42928 | F73: =IF(E73>0, DATEDIF(E73,TODAY(),"Y"),"") -> 8 | G73: 45314 | H73: =IF(U73>0,U73,TODAY()) -> 45386 | I73: =IF(G73>0, ROUNDDOWN((H73-G73)/365,0)& " Anos e "& ROUNDDOWN(((H73-G73)-ROUNDDOWN((H73-G73)/365,0)*365)/30,0)&" meses","") -> 0 Anos e 2 meses | K73: estudante 1° ano Ens Fundamental | L73: 62 982025350 / 62 982057486 | M73: Mãe/pai | N73: nolegario1988@icloud.com | O73: Rua das Roseiras. Qd 5 lt 1 casa 2. | P73: Parque das Paineiras. | Q73: Goiânia | R73: 74369-139 | S73: Murilo Soares dos Santos | T73: Natália Newman Olegario de Faria | U73: 45386 | V73: 08552269198 | W73: indicação paciente - Heitor (mãe Jhenifer) | X73: dificuldades financeiras p continuar terapia
A74: =IF(E74<>0, MONTH(E74),"") -> 2 | B74: =IF(F74="","", IF(F74<12,"Criança",IF(F74<18,"Adolescente",IF(F74<26,"Jovem",IF(F74<60,"Adulto", "Idoso"))))) -> Adulto | C74: Paulo Henrique Pinho de Morais | D74: Terapia | E74: 32906 | F74: =IF(E74>0, DATEDIF(E74,TODAY(),"Y"),"") -> 35 | G74: 45328 | H74: =IF(U74>0,U74,TODAY()) -> 45364 | I74: =IF(G74>0, ROUNDDOWN((H74-G74)/365,0)& " Anos e "& ROUNDDOWN(((H74-G74)-ROUNDDOWN((H74-G74)/365,0)*365)/30,0)&" meses","") -> 0 Anos e 1 meses | J74: 62 993500641 | K74: advogado | Q74: Goiânia | U74: 45364 | W74: Doctoralia
A75: =IF(E75<>0, MONTH(E75),"") -> 1 | B75: =IF(F75="","", IF(F75<12,"Criança",IF(F75<18,"Adolescente",IF(F75<26,"Jovem",IF(F75<60,"Adulto", "Idoso"))))) -> Adulto | C75: Larissa Silva Pinto | D75: Seção Avulsa | E75: 32877 | F75: =IF(E75>0, DATEDIF(E75,TODAY(),"Y"),"") -> 36 | G75: 45342 | H75: =IF(U75>0,U75,TODAY()) -> 45342 | I75: =IF(G75>0, ROUNDDOWN((H75-G75)/365,0)& " Anos e "& ROUNDDOWN(((H75-G75)-ROUNDDOWN((H75-G75)/365,0)*365)/30,0)&" meses","") -> 0 Anos e 0 meses | J75: 62 986310031 | Q75: Goiânia | U75: 45342 | W75: indicação pacientes - Luana | X75: autoconehecimento e relacionamentos
A76: =IF(E76<>0, MONTH(E76),"") | B76: Adulto | C76: Estefânia da Conceição de Souza Rabelo | D76: Seção Avulsa | F76: =IF(E76>0, DATEDIF(E76,TODAY(),"Y"),"") | G76: 45342 | H76: =IF(U76>0,U76,TODAY()) -> 45349 | I76: =IF(G76>0, ROUNDDOWN((H76-G76)/365,0)& " Anos e "& ROUNDDOWN(((H76-G76)-ROUNDDOWN((H76-G76)/365,0)*365)/30,0)&" meses","") -> 0 Anos e 0 meses | J76: 62 982265518 | K76: vendedora | N76: ester.cristojesus21@gmail.com | Q76: Goiânia | U76: 45349 | W76: Doctoralia | X76: abuso sexual e dificuldades no casamento
A77: =IF(E77<>0, MONTH(E77),"") -> 4 | B77: =IF(F77="","", IF(F77<12,"Criança",IF(F77<18,"Adolescente",IF(F77<26,"Jovem",IF(F77<60,"Adulto", "Idoso"))))) -> Adulto | C77: Rosimere Lima Vasconcelos Resende | D77: Seção Avulsa | E77: 30782 | F77: =IF(E77>0, DATEDIF(E77,TODAY(),"Y"),"") -> 41 | G77: 45344 | H77: =IF(U77>0,U77,TODAY()) -> 45344 | I77: =IF(G77>0, ROUNDDOWN((H77-G77)/365,0)& " Anos e "& ROUNDDOWN(((H77-G77)-ROUNDDOWN((H77-G77)/365,0)*365)/30,0)&" meses","") -> 0 Anos e 0 meses | J77: 62 981197964 | K77: dona de casa | P77: Condomínio Aldeia | Q77: Goiânia | U77: 45344 | W77: Indicação pacinete - Miriane | X77: problemas do casamento
A78: =IF(E78<>0, MONTH(E78),"") -> 1 | B78: =IF(F78="","", IF(F78<12,"Criança",IF(F78<18,"Adolescente",IF(F78<26,"Jovem",IF(F78<60,"Adulto", "Idoso"))))) -> Jovem | C78: João Guilherme Rodrigues de Souza | D78: Seção Avulsa | E78: 39450 | F78: =IF(E78>0, DATEDIF(E78,TODAY(),"Y"),"") -> 18 | G78: 45370 | H78: =IF(U78>0,U78,TODAY()) -> 45378 | I78: =IF(G78>0, ROUNDDOWN((H78-G78)/365,0)& " Anos e "& ROUNDDOWN(((H78-G78)-ROUNDDOWN((H78-G78)/365,0)*365)/30,0)&" meses","") -> 0 Anos e 0 meses | J78: 1 415 8107204 | K78: estudante | L78: 1 650 4524841 | M78: Mãe Kamyla | Q78: Califórnia/EUA | T78: Kamyla Ferrante | U78: 45378 | W78: indicação de colegas - Amanda | X78: baixo autoestima
A79: =IF(E79<>0, MONTH(E79),"") -> 4 | B79: =IF(F79="","", IF(F79<12,"Criança",IF(F79<18,"Adolescente",IF(F79<26,"Jovem",IF(F79<60,"Adulto", "Idoso"))))) -> Adulto | C79: Renata Balbino Dias | D79: Seção Avulsa | E79: 36266 | F79: =IF(E79>0, DATEDIF(E79,TODAY(),"Y"),"") -> 26 | G79: 45364 | H79: =IF(U79>0,U79,TODAY()) -> 45377 | I79: =IF(G79>0, ROUNDDOWN((H79-G79)/365,0)& " Anos e "& ROUNDDOWN(((H79-G79)-ROUNDDOWN((H79-G79)/365,0)*365)/30,0)&" meses","") -> 0 Anos e 0 meses | J79: 62 991309344 | K79: veterinária | Q79: Goiânia | U79: 45377 | W79: indicação paciente - Luana | X79: problemas no relacionamento
A80: =IF(E80<>0, MONTH(E80),"") -> 1 | B80: =IF(F80="","", IF(F80<12,"Criança",IF(F80<18,"Adolescente",IF(F80<26,"Jovem",IF(F80<60,"Adulto", "Idoso"))))) -> Idoso | C80: Cleide Pessoni Pereira | D80: Terapia | E80: 20119 | F80: =IF(E80>0, DATEDIF(E80,TODAY(),"Y"),"") -> 70 | G80: 45387 | H80: =IF(U80>0,U80,TODAY()) -> 45499 | I80: =IF(G80>0, ROUNDDOWN((H80-G80)/365,0)& " Anos e "& ROUNDDOWN(((H80-G80)-ROUNDDOWN((H80-G80)/365,0)*365)/30,0)&" meses","") -> 0 Anos e 3 meses | J80: 62 999090018 | K80: motorista de entrega/ aposentada | L80: 62 998084050 | M80: filha Pollyanna | Q80: Goiânia | U80: 45499 | W80: indicação paciente - Yara
A81: =IF(E81<>0, MONTH(E81),"") -> 6 | B81: =IF(F81="","", IF(F81<12,"Criança",IF(F81<18,"Adolescente",IF(F81<26,"Jovem",IF(F81<60,"Adulto", "Idoso"))))) -> Adulto | C81: Renata Gonçalves da Silva | D81: Terapia | E81: 35231 | F81: =IF(E81>0, DATEDIF(E81,TODAY(),"Y"),"") -> 29 | G81: 45401 | H81: =IF(U81>0,U81,TODAY()) -> 45510 | I81: =IF(G81>0, ROUNDDOWN((H81-G81)/365,0)& " Anos e "& ROUNDDOWN(((H81-G81)-ROUNDDOWN((H81-G81)/365,0)*365)/30,0)&" meses","") -> 0 Anos e 3 meses | J81: 62 981242574 | K81: empresária/vestuário | Q81: Goiânia | U81: 45510 | W81: indicação paciente - Luana
A82: =IF(E82<>0, MONTH(E82),"") -> 7 | B82: =IF(F82="","", IF(F82<12,"Criança",IF(F82<18,"Adolescente",IF(F82<26,"Jovem",IF(F82<60,"Adulto", "Idoso"))))) -> Idoso | C82: Valcy Jeremias Moreira | D82: Terapia | E82: 21749 | F82: =IF(E82>0, DATEDIF(E82,TODAY(),"Y"),"") -> 66 | G82: 45404 | H82: =IF(U82>0,U82,TODAY()) -> 45532 | I82: =IF(G82>0, ROUNDDOWN((H82-G82)/365,0)& " Anos e "& ROUNDDOWN(((H82-G82)-ROUNDDOWN((H82-G82)/365,0)*365)/30,0)&" meses","") -> 0 Anos e 4 meses | J82: 62 996879868 | K82: empresária/vestuário | O82: Rua 15, 108 - Ed Aldebaran, ap 100 | P82: Setor Oeste | Q82: Goiânia | R82: 74140-035 | U82: 45532 | V82: 04692391820 | W82: indicação Dayse
A83: =IF(E83<>0, MONTH(E83),"") -> 2 | B83: =IF(F83="","", IF(F83<12,"Criança",IF(F83<18,"Adolescente",IF(F83<26,"Jovem",IF(F83<60,"Adulto", "Idoso"))))) -> Adolescente | C83: Julia A. Moreira | D83: Terapia | E83: 39850 | F83: =IF(E83>0, DATEDIF(E83,TODAY(),"Y"),"") -> 16 | G83: 45412 | H83: =IF(U83>0,U83,TODAY()) -> 45541 | I83: =IF(G83>0, ROUNDDOWN((H83-G83)/365,0)& " Anos e "& ROUNDDOWN(((H83-G83)-ROUNDDOWN((H83-G83)/365,0)*365)/30,0)&" meses","") -> 0 Anos e 4 meses | J83: 62 999891959 | K83: estudante - ens médio 1° | L83: 62 996879868 / 62 991069297 | M83: pai/mãe | O83: Rua 15, 108 - Ed Aldebaran, ap 101 | P83: Setor Oeste | Q83: Goiânia | R83: 74140-036 | S83: Valcy Jeremias Moreira | T83: Neila | U83: 45541 | W83: indicação Dayse
A84: =IF(E84<>0, MONTH(E84),"") -> 9 | B84: =IF(F84="","", IF(F84<12,"Criança",IF(F84<18,"Adolescente",IF(F84<26,"Jovem",IF(F84<60,"Adulto", "Idoso"))))) -> Adulto | C84: Constância de Oliveira Lima | D84: Seção Avulsa | E84: 33875 | F84: =IF(E84>0, DATEDIF(E84,TODAY(),"Y"),"") -> 33 | G84: 45419 | H84: =IF(U84>0,U84,TODAY()) -> 45433 | I84: =IF(G84>0, ROUNDDOWN((H84-G84)/365,0)& " Anos e "& ROUNDDOWN(((H84-G84)-ROUNDDOWN((H84-G84)/365,0)*365)/30,0)&" meses","") -> 0 Anos e 0 meses | J84: 62 996131014 | K84: secretária de consultório | Q84: Goiânia | U84: 45433 | W84: indicação paciente - Núbia | X84: baixa autoestima autossabotagem
A85: =IF(E85<>0, MONTH(E85),"") -> 10 | B85: =IF(F85="","", IF(F85<12,"Criança",IF(F85<18,"Adolescente",IF(F85<26,"Jovem",IF(F85<60,"Adulto", "Idoso"))))) -> Adolescente | C85: Alexandra Moreira Santos | D85: Terapia | E85: 40479 | F85: =IF(E85>0, DATEDIF(E85,TODAY(),"Y"),"") -> 15 | G85: 45422 | H85: =IF(U85>0,U85,TODAY()) -> 45506 | I85: =IF(G85>0, ROUNDDOWN((H85-G85)/365,0)& " Anos e "& ROUNDDOWN(((H85-G85)-ROUNDDOWN((H85-G85)/365,0)*365)/30,0)&" meses","") -> 0 Anos e 2 meses | K85: estudante - ens fundamental | L85: 62 998575477 / 62 982142476 | M85: mãe Ayara/ pai Alex | Q85: Goiânia | U85: 45506 | W85: indicação paciente - Luiza (Mariana mãe)
A86: =IF(E86<>0, MONTH(E86),"") -> 4 | B86: =IF(F86="","", IF(F86<12,"Criança",IF(F86<18,"Adolescente",IF(F86<26,"Jovem",IF(F86<60,"Adulto", "Idoso"))))) -> Adulto | C86: Élida Custódia da Cunha Souza | D86: Terapia | E86: 34068 | F86: =IF(E86>0, DATEDIF(E86,TODAY(),"Y"),"") -> 32 | G86: 45463 | H86: =IF(U86>0,U86,TODAY()) -> 45504 | I86: =IF(G86>0, ROUNDDOWN((H86-G86)/365,0)& " Anos e "& ROUNDDOWN(((H86-G86)-ROUNDDOWN((H86-G86)/365,0)*365)/30,0)&" meses","") -> 0 Anos e 1 meses | J86: 351 910 108853 | K86: acompanhante de bebida bar | Q86: Portugal | U86: 45504 | W86: indicação paciente - Renata Gonçalves
A87: =IF(E87<>0, MONTH(E87),"") -> 9 | B87: =IF(F87="","", IF(F87<12,"Criança",IF(F87<18,"Adolescente",IF(F87<26,"Jovem",IF(F87<60,"Adulto", "Idoso"))))) -> Adulto | C87: Lucimeire Itaides Santana Arruda (karol) | D87: Seção Avulsa | E87: 25107 | F87: =IF(E87>0, DATEDIF(E87,TODAY(),"Y"),"") -> 57 | G87: 45468 | H87: =IF(U87>0,U87,TODAY()) -> 45468 | I87: =IF(G87>0, ROUNDDOWN((H87-G87)/365,0)& " Anos e "& ROUNDDOWN(((H87-G87)-ROUNDDOWN((H87-G87)/365,0)*365)/30,0)&" meses","") -> 0 Anos e 0 meses | J87: 62 991134304 | Q87: Goiânia | U87: 45468 | W87: indicação pacinete - Luana | X87: angústia pontual com o pai idoso que venho morar com ela
A88: =IF(E88<>0, MONTH(E88),"") -> 12 | B88: =IF(F88="","", IF(F88<12,"Criança",IF(F88<18,"Adolescente",IF(F88<26,"Jovem",IF(F88<60,"Adulto", "Idoso"))))) -> Adulto | C88: Alexandre Brasil de Abreu | D88: Terapia | E88: 31756 | F88: =IF(E88>0, DATEDIF(E88,TODAY(),"Y"),"") -> 39 | G88: 45538 | H88: =IF(U88>0,U88,TODAY()) -> 45603 | I88: =IF(G88>0, ROUNDDOWN((H88-G88)/365,0)& " Anos e "& ROUNDDOWN(((H88-G88)-ROUNDDOWN((H88-G88)/365,0)*365)/30,0)&" meses","") -> 0 Anos e 2 meses | J88: 62 981150180 | K88: empresário/academia | Q88: Goiânia | U88: 45603 | W88: indicação paciente - Yara
A89: =IF(E89<>0, MONTH(E89),"") -> 2 | B89: =IF(F89="","", IF(F89<12,"Criança",IF(F89<18,"Adolescente",IF(F89<26,"Jovem",IF(F89<60,"Adulto", "Idoso"))))) -> Adulto | C89: Natália Rocha | D89: Terapia | E89: 31105 | F89: =IF(E89>0, DATEDIF(E89,TODAY(),"Y"),"") -> 40 | G89: 45555 | H89: =IF(U89>0,U89,TODAY()) -> 45631 | I89: =IF(G89>0, ROUNDDOWN((H89-G89)/365,0)& " Anos e "& ROUNDDOWN(((H89-G89)-ROUNDDOWN((H89-G89)/365,0)*365)/30,0)&" meses","") -> 0 Anos e 2 meses | J89: 62 985933743 | K89: trabalhava na cademia c o ex esposo | Q89: Goiânia | U89: 45631 | W89: indicação paciente - Alexandre
A90: =IF(E90<>0, MONTH(E90),"") -> 11 | B90: =IF(F90="","", IF(F90<12,"Criança",IF(F90<18,"Adolescente",IF(F90<26,"Jovem",IF(F90<60,"Adulto", "Idoso"))))) -> Adulto | C90: Alinne Ungarelli Oliveira | D90: Terapia | E90: 29187 | F90: =IF(E90>0, DATEDIF(E90,TODAY(),"Y"),"") -> 46 | G90: 45555 | H90: =IF(U90>0,U90,TODAY()) -> 45673 | I90: =IF(G90>0, ROUNDDOWN((H90-G90)/365,0)& " Anos e "& ROUNDDOWN(((H90-G90)-ROUNDDOWN((H90-G90)/365,0)*365)/30,0)&" meses","") -> 0 Anos e 3 meses | J90: 62 999030975 | K90: fisioterapeuca tribunal justiça | Q90: Goiânia | U90: 45673 | W90: indicação Dayse
A91: =IF(E91<>0, MONTH(E91),"") -> 12 | B91: =IF(F91="","", IF(F91<12,"Criança",IF(F91<18,"Adolescente",IF(F91<26,"Jovem",IF(F91<60,"Adulto", "Idoso"))))) -> Jovem | C91: Gabriel Ferreira Mendanha | D91: Terapia | E91: 38708 | F91: =IF(E91>0, DATEDIF(E91,TODAY(),"Y"),"") -> 20 | G91: 45212 | H91: =IF(U91>0,U91,TODAY()) -> 45688 | I91: =IF(G91>0, ROUNDDOWN((H91-G91)/365,0)& " Anos e "& ROUNDDOWN(((H91-G91)-ROUNDDOWN((H91-G91)/365,0)*365)/30,0)&" meses","") -> 1 Anos e 3 meses | J91: 62 999424618 | K91: estudante - ens médio | L91: 62 999774653 / 62 996793814 | M91: paiLuciano/ mãe Marilene | N91: gabeestrelinha@gmail.com | O91: Rua A 21, Qd 23A, Lt 23, Cond. Jardins Atenas | P91: Jardins Atenas | Q91: Goiânia | R91: 74885-573 | S91: Luciano José Mendanha | T91: Marilene Ferreira Silva Mendanha | U91: 45688 | V91: 04038107108 | W91: Doctoralia
A92: =IF(E92<>0, MONTH(E92),"") -> 1 | B92: =IF(F92="","", IF(F92<12,"Criança",IF(F92<18,"Adolescente",IF(F92<26,"Jovem",IF(F92<60,"Adulto", "Idoso"))))) -> Adulto | C92: Yara Kelly Sousa França | D92: Terapia | E92: 30689 | F92: =IF(E92>0, DATEDIF(E92,TODAY(),"Y"),"") -> 42 | G92: 45191 | H92: =IF(U92>0,U92,TODAY()) -> 45681 | I92: =IF(G92>0, ROUNDDOWN((H92-G92)/365,0)& " Anos e "& ROUNDDOWN(((H92-G92)-ROUNDDOWN((H92-G92)/365,0)*365)/30,0)&" meses","") -> 1 Anos e 4 meses | J92: 62 991829420 | K92: empresária/ financeiro e construção | L92: 62 985510616 | M92: esposa Pollyanna | N92: yarakelly@yapsolucoes.com.br | O92: Rua Timbure, 81 - Lá vita Residence, ap. 1303 | P92: Santa Genoveva | Q92: Goiânia | R92: 74670-040 | S92: Divino Pereira franca + | T92: Antonia de Sousa lima | U92: 45681 | V92: 00655831169 | W92: indicação Dayse
A93: =IF(E93<>0, MONTH(E93),"") -> 4 | B93: =IF(F93="","", IF(F93<12,"Criança",IF(F93<18,"Adolescente",IF(F93<26,"Jovem",IF(F93<60,"Adulto", "Idoso"))))) -> Adulto | C93: Wesley Dias Soares | D93: Terapia | E93: 33331 | F93: =IF(E93>0, DATEDIF(E93,TODAY(),"Y"),"") -> 34 | G93: 44881 | H93: =IF(U93>0,U93,TODAY()) -> 45688 | I93: =IF(G93>0, ROUNDDOWN((H93-G93)/365,0)& " Anos e "& ROUNDDOWN(((H93-G93)-ROUNDDOWN((H93-G93)/365,0)*365)/30,0)&" meses","") -> 2 Anos e 2 meses | J93: 62 981407845 | K93: engenheiro civil | L93: 62 992481156/ 62 983086715 | M93: mãe Irany/ esposa Tainá | N93: wesley.soares@hotmail.com.br | Q93: Senador Canedo/GO | T93: Iracy | U93: 45688 | W93: indicação paciente - Caio e Ana
A94: =IF(E94<>0, MONTH(E94),"") -> 7 | B94: =IF(F94="","", IF(F94<12,"Criança",IF(F94<18,"Adolescente",IF(F94<26,"Jovem",IF(F94<60,"Adulto", "Idoso"))))) -> Adolescente | C94: Marianna Pereira Martins | D94: Terapia | E94: 39646 | F94: =IF(E94>0, DATEDIF(E94,TODAY(),"Y"),"") -> 17 | G94: 45567 | H94: =IF(U94>0,U94,TODAY()) -> 45700 | I94: =IF(G94>0, ROUNDDOWN((H94-G94)/365,0)& " Anos e "& ROUNDDOWN(((H94-G94)-ROUNDDOWN((H94-G94)/365,0)*365)/30,0)&" meses","") -> 0 Anos e 4 meses | J94: 61 993043722 | K94: estudante - ensino médio | L94: 63 992555373 | M94: mãe Luanna | N94: marianna.peereira@gmail.com | O94: Avenida T-5, Ed. Zeus Park House - Apart 1802 | P94: Setor Bueno | Q94: Goiânia | R94: 74230-045 | S94: Amarildo Martins Mariano | T94: Luanna Carneiro Pereira CPF 73013145153 | U94: 45700 | V94: 05715819199 | W94: doctoralia
A95: =IF(E95<>0, MONTH(E95),"") -> 9 | B95: =IF(F95="","", IF(F95<12,"Criança",IF(F95<18,"Adolescente",IF(F95<26,"Jovem",IF(F95<60,"Adulto", "Idoso"))))) -> Adolescente | C95: Luiza Lima Santana Rodrigues | D95: Terapia | E95: 40079 | F95: =IF(E95>0, DATEDIF(E95,TODAY(),"Y"),"") -> 16 | G95: 44630 | H95: =IF(U95>0,U95,TODAY()) -> 46039 | I95: =IF(G95>0, ROUNDDOWN((H95-G95)/365,0)& " Anos e "& ROUNDDOWN(((H95-G95)-ROUNDDOWN((H95-G95)/365,0)*365)/30,0)&" meses","") -> 3 Anos e 10 meses | J95: 62 996701829 | K95: estudante | L95: 62 996871826 | M95: mãe Mariana | N95: marianagl.arquitetura@gmail.com | O95: Rua C 229, 213 - Ed. Essência Homeclub, ap 1302A | P95: Jardim América | Q95: Goiânia | R95: 74290-110 | S95: Eduardo Santana Rodrigues | T95: Mariana Guimarães de Lima | W95: indicação terceiros/outro -local de atendiemnto
A96: =IF(E96<>0, MONTH(E96),"") -> 8 | B96: =IF(F96="","", IF(F96<12,"Criança",IF(F96<18,"Adolescente",IF(F96<26,"Jovem",IF(F96<60,"Adulto", "Idoso"))))) -> Adulto | C96: Gilbrair Alcantara de Oliveira | D96: Terapia | E96: 28716 | F96: =IF(E96>0, DATEDIF(E96,TODAY(),"Y"),"") -> 47 | G96: 44757 | H96: =IF(U96>0,U96,TODAY()) -> 46039 | I96: =IF(G96>0, ROUNDDOWN((H96-G96)/365,0)& " Anos e "& ROUNDDOWN(((H96-G96)-ROUNDDOWN((H96-G96)/365,0)*365)/30,0)&" meses","") -> 3 Anos e 6 meses | J96: 62 984176267 | K96: farmacêutico | L96: 62 984034386 / 62 984011949 | M96: esposa Renata/ irmã Adriana | N96: gilbrair@gmail.com | O96: Rua Tamboril, Qd 133, Lt 30 | P96: Santa Genoveva | Q96: Goiânia | R96: 74672-540 | V96: 84407123168 | W96: indicação Dayse
A97: =IF(E97<>0, MONTH(E97),"") -> 11 | B97: =IF(F97="","", IF(F97<12,"Criança",IF(F97<18,"Adolescente",IF(F97<26,"Jovem",IF(F97<60,"Adulto", "Idoso"))))) -> Adolescente | C97: Heitor Luiz Mota e Silva | D97: Avaliação/Terapia | E97: 41583 | F97: =IF(E97>0, DATEDIF(E97,TODAY(),"Y"),"") -> 12 | G97: 44810 | H97: =IF(U97>0,U97,TODAY()) -> 46039 | I97: =IF(G97>0, ROUNDDOWN((H97-G97)/365,0)& " Anos e "& ROUNDDOWN(((H97-G97)-ROUNDDOWN((H97-G97)/365,0)*365)/30,0)&" meses","") -> 3 Anos e 4 meses | K97: estudante ens fundamental | L97: 62 982929235 / 62 982260581 | M97: mãe/pai | O97: Rua Getúlio Vargas Qd 20 Lt:35/36 - casa 2 | P97: Parque Amazonas | Q97: Goiânia | R97: 74340-080 | S97: Alessandro José da silva | T97: Jhenifer Gomes Mota da Silva | V97: 71492680133 | W97: doctoralia/google | X97: CPF pai 003.198.221-25
A98: =IF(E98<>0, MONTH(E98),"") -> 1 | B98: =IF(F98="","", IF(F98<12,"Criança",IF(F98<18,"Adolescente",IF(F98<26,"Jovem",IF(F98<60,"Adulto", "Idoso"))))) -> Adulto | C98: Ariadna Santos Rodrigues | D98: Terapia | E98: 30690 | F98: =IF(E98>0, DATEDIF(E98,TODAY(),"Y"),"") -> 42 | G98: 44939 | H98: =IF(U98>0,U98,TODAY()) -> 46039 | I98: =IF(G98>0, ROUNDDOWN((H98-G98)/365,0)& " Anos e "& ROUNDDOWN(((H98-G98)-ROUNDDOWN((H98-G98)/365,0)*365)/30,0)&" meses","") -> 3 Anos e 0 meses | J98: 62 982483847 | K98: pedagoga | Q98: Goiânia | W98: indicação supervisora Juliana | X98: ate 07/2023 fo valor social
A99: =IF(E99<>0, MONTH(E99),"") -> 5 | B99: =IF(F99="","", IF(F99<12,"Criança",IF(F99<18,"Adolescente",IF(F99<26,"Jovem",IF(F99<60,"Adulto", "Idoso"))))) -> Jovem | C99: Caio Vinicius Dollis Camargos | D99: Avaliação/Terapia | E99: 37035 | F99: =IF(E99>0, DATEDIF(E99,TODAY(),"Y"),"") -> 24 | G99: 45086 | H99: =IF(U99>0,U99,TODAY()) -> 46039 | I99: =IF(G99>0, ROUNDDOWN((H99-G99)/365,0)& " Anos e "& ROUNDDOWN(((H99-G99)-ROUNDDOWN((H99-G99)/365,0)*365)/30,0)&" meses","") -> 2 Anos e 7 meses | J99: 62 999926359 | K99: estudande - relações internacionais | L99: 62 982294105 | M99: mãe Juliana | O99: Rua J-71, 233, Qd 125, Lt 8, | P99: Setor Jaó | Q99: Goiânia | R99: 74674-380 | S99: Wladimyr Vinycius de Moraes Camargos | T99: Juliana Dollis | V99: 02316583113 | W99: indicação Dayse | X99: avaliação iniciou 25/01/2023
A100: =IF(E100<>0, MONTH(E100),"") -> 11 | B100: =IF(F100="","", IF(F100<12,"Criança",IF(F100<18,"Adolescente",IF(F100<26,"Jovem",IF(F100<60,"Adulto", "Idoso"))))) -> Adulto | C100: Mayara Vieira Silva | D100: Terapia | E100: 33207 | F100: =IF(E100>0, DATEDIF(E100,TODAY(),"Y"),"") -> 35 | G100: 45106 | H100: =IF(U100>0,U100,TODAY()) -> 46039 | I100: =IF(G100>0, ROUNDDOWN((H100-G100)/365,0)& " Anos e "& ROUNDDOWN(((H100-G100)-ROUNDDOWN((H100-G100)/365,0)*365)/30,0)&" meses","") -> 2 Anos e 6 meses | J100: 62 984193325 | K100: professora universitária | L100: 62 984369474 | M100: esposo Douglas | N100: mayaravieirasilva@gmail.com | O100: Av: Leblon, Q: 147 - Cond New Park, Torre 3, ap.801 | P100: Jardim Atlântico | Q100: Goiânia | R100: 74843-440 | S100: Wilson Vieira | T100: Aparecida de Fátima Silva | V100: 04103251123 | W100: Doctoralia | X100: mora em ceres e goiânia
A101: =IF(E101<>0, MONTH(E101),"") -> 8 | B101: =IF(F101="","", IF(F101<12,"Criança",IF(F101<18,"Adolescente",IF(F101<26,"Jovem",IF(F101<60,"Adulto", "Idoso"))))) -> Adulto | C101: Luana Guisela Pereira Borba | D101: Terapia | E101: 35658 | F101: =IF(E101>0, DATEDIF(E101,TODAY(),"Y"),"") -> 28 | G101: 45118 | H101: =IF(U101>0,U101,TODAY()) -> 46039 | I101: =IF(G101>0, ROUNDDOWN((H101-G101)/365,0)& " Anos e "& ROUNDDOWN(((H101-G101)-ROUNDDOWN((H101-G101)/365,0)*365)/30,0)&" meses","") -> 2 Anos e 6 meses | J101: 62 993219359 | K101: advogada pública secret Saude | L101: 62 991906688 | M101: mãe Sanderli | N101: luanaguisela@hotmail.com | O101: Rua C-84. Qd. 150 , Lt. 01 - casa 01 | P101: Setor Sudoeste | Q101: Goiânia | R101: 74303-180 | S101: Atanir Eduardo Borba | T101: Sanderli Dionisio Pereira Borba | V101: 03660821160 | W101: indicação supervisora Juliana
...

Sheet Gráficos 22

Sheet Gráficos 23

Sheet Aniversariantes do Mês
B2: Data de Nascimento | C2: Paciente
B3: 20119 | C3: Cleide Pessoni Pereira
B4: 30689 | C4: Yara Kelly Sousa França
B5: 30690 | C5: Ariadna Santos Rodrigues
B6: 30691 | C6: Ricardo Leite de Sousa
B7: 31787 | C7: Flavio Vieira Barbosa
B8: 32877 | C8: Larissa Silva Pinto
B9: 35444 | C9: Amanda Cristina de Souza
B10: 39450 | C10: João Guilherme Rodrigues de Souza
